Workbook

Sheet Prices
A1: Date | B1: ACWX | C1: AGG | D1: EEM | E1: IEF | F1: RWR | G1: TIP | H1: VNQ | I1: VONV | J1: ^GSPC | K1: ^IRX | L1: ^MID | M1: ^RLG | N1: ^RLV | O1: ^RUT
A2: 42621 | B2: 32.145954 | C2: 84.383873 | D2: 30.513186 | E2: 88.212257 | F2: 70.726501 | G2: 85.3228 | H2: 60.298496 | I2: 37.62851 | J2: 2181.3 | K2: 0.333 | L2: 1574.28 | M2: 1048.34 | N2: 1052.6 | O2: 1258.36
A3: 42622 | B3: 31.440628 | C3: 84.015427 | D3: 29.485104 | E3: 87.793091 | F3: 68.021393 | G3: 84.733727 | H3: 57.910507 | I3: 36.683281 | J3: 2127.8101 | K3: 0.333 | L3: 1528.3101 | M3: 1022.33 | N3: 1026.33 | O3: 1219.21
A4: 42625 | B4: 31.670631 | C4: 84.083084 | D4: 29.685892 | E4: 87.872154 | F4: 68.843468 | G4: 84.763206 | H4: 58.596622 | I4: 37.211967 | J4: 2159.04 | K4: 0.34999999 | L4: 1545.97 | M4: 1037.27 | N4: 1040.87 | O4: 1235.87
A5: 42626 | B5: 31.011305 | C5: 83.850014 | D5: 28.938931 | E5: 87.547874 | F5: 67.079895 | G5: 84.38768 | H5: 57.125469 | I5: 36.583168 | J5: 2127.02 | K5: 0.345 | L5: 1517.26 | M5: 1024.6 | N5: 1022.1 | O5: 1212.3199
A6: 42627 | B6: 31.018967 | C6: 83.955292 | D6: 29.027287 | E6: 87.745552 | F6: 67.353897 | G6: 84.52021 | H6: 57.308372 | I6: 36.430977 | J6: 2125.77 | K6: 0.315 | L6: 1512.78 | M6: 1026.3199 | N6: 1019.09 | O6: 1211.59
A7: 42628 | B7: 31.325634 | C7: 84.007858 | D7: 29.525257 | E7: 87.769333 | F7: 67.606857 | G7: 84.498123 | H7: 57.525108 | I7: 36.823471 | J7: 2147.26 | K7: 0.278 | L7: 1528.6899 | M7: 1037.5 | N7: 1028.47 | O7: 1227.02
A8: 42629 | B8: 30.95763 | C8: 84.068054 | D8: 29.324467 | E8: 87.864243 | F8: 67.591972 | G8: 84.638016 | H8: 57.552204 | I8: 36.607193 | J8: 2139.1599 | K8: 0.273 | L8: 1520.96 | M8: 1034.74 | N8: 1023.56 | O8: 1224.78
A9: 42632 | B9: 31.156969 | C9: 84.000381 | D9: 29.557388 | E9: 87.713959 | F9: 68.179855 | G9: 84.53492 | H9: 58.073719 | I9: 36.675293 | J9: 2139.1201 | K9: 0.23800001 | L9: 1532.39 | M9: 1033.99 | N9: 1025.41 | O9: 1232.53
A10: 42633 | B10: 31.287298 | C10: 84.030426 | D10: 29.573452 | E10: 87.848419 | F10: 68.165672 | G10: 84.52021 | H10: 57.985699 | I10: 36.681328 | J10: 2139.76 | K10: 0.28799999 | L10: 1525.35 | M10: 1035.35 | N10: 1023.89 | O10: 1228.33
A11: 42634 | B11: 31.885292 | C11: 84.24099 | D11: 30.400738 | E11: 87.990746 | F11: 68.994385 | G11: 84.917839 | H11: 58.730751 | I11: 37.05217 | J11: 2163.1201 | K11: 0.223 | L11: 1544.67 | M11: 1045.8101 | N11: 1036.0601 | O11: 1245.04
A12: 42635 | B12: 32.199623 | C12: 84.41394 | D12: 30.617596 | E12: 88.251823 | F12: 70.240982 | G12: 85.337517 | H12: 59.780582 | I12: 37.326271 | J12: 2177.1799 | K12: 0.16 | L12: 1562.9399 | M12: 1053.62 | N12: 1042.71 | O12: 1263.4399
A13: 42636 | B13: 31.877628 | C13: 84.391411 | D13: 30.224035 | E13: 88.291298 | F13: 70.453468 | G13: 85.573143 | H13: 59.963467 | I13: 37.096512 | J13: 2164.6899 | K13: 0.16500001 | L13: 1550.8199 | M13: 1047.95 | N13: 1036.52 | O13: 1254.62
... A47: 42684 | B47: 30.758307 | C47: 82.605705 | D47: 28.288351 | E47: 85.131348 | F47: 62.471031 | G47: 84.358223 | H47: 52.878658 | I47: 37.801918 | J47: 2167.48 | K47: 0.458 | L47: 1547.63 | M47: 1030.1899 | N47: 1053.5 | O47: 1251.61
A48: 42685 | B48: 30.505312 | C48: 82.454773 | D48: 27.750202 | E48: 84.956879 | F48: 62.881851 | G48: 84.122612 | H48: 53.197002 | I48: 37.761604 | J48: 2164.45 | L48: 1562.99 | M48: 1030.37 | N48: 1051.86 | O48: 1282.38
A49: 42688 | B49: 30.305979 | C49: 82.122688 | D49: 27.549416 | E49: 84.465172 | F49: 64.461311 | G49: 83.47467 | H49: 54.456818 | I49: 38.011543 | J49: 2164.2 | K49: 0.50300002 | L49: 1588.12 | M49: 1025.47 | N49: 1059.38 | O49: 1298.6
A50: 42689 | B50: 30.566641 | C50: 82.183044 | D50: 28.103613 | E50: 84.465172 | F50: 63.767189 | G50: 83.526215 | H50: 54.003029 | I50: 38.289661 | J50: 2180.3899 | K50: 0.48800001 | L50: 1595.63 | M50: 1032.78 | N50: 1067.46 | O50: 1302.14
A51: 42690 | B51: 30.28298 | C51: 82.364189 | D51: 27.870689 | E51: 84.544472 | F51: 63.540531 | G51: 83.702866 | H51: 53.84724 | I51: 38.112305 | J51: 2176.9399 | K51: 0.45300001 | L51: 1595.53 | M51: 1035.71 | N51: 1061.41 | O51: 1302.2
A52: 42691 | B52: 30.466976 | C52: 82.054764 | D52: 27.910849 | E52: 84.1717 | F52: 62.903099 | G52: 83.563011 | H52: 53.298595 | I52: 38.229195 | J52: 2187.1201 | K52: 0.41999999 | L52: 1605.24 | M52: 1043.13 | N52: 1064.37 | O52: 1309.48
A53: 42692 | B53: 30.198643 | C53: 81.790619 | D53: 27.782345 | E53: 83.798958 | F53: 63.002258 | G53: 83.437851 | H53: 53.45438 | I53: 38.192909 | J53: 2181.8999 | K53: 0.41800001 | L53: 1605.9301 | M53: 1039.52 | N53: 1063.25 | O53: 1315.64
A54: 42695 | B54: 30.474644 | C54: 81.858482 | D54: 28.055428 | E54: 83.870346 | F54: 62.747284 | G54: 83.63665 | H54: 53.291828 | I54: 38.45895 | J54: 2198.1799 | K54: 0.41999999 | L54: 1616.6801 | M54: 1047.8101 | N54: 1070.59 | O54: 1322.23
A55: 42696 | B55: 30.612648 | C55: 81.934013 | D55: 28.481115 | E55: 83.949623 | F55: 63.788483 | G55: 83.710281 | H55: 54.226543 | I55: 38.555702 | J55: 2202.9399 | K55: 0.47499999 | L55: 1628.53 | M55: 1050.72 | N55: 1072.74 | O55: 1334.34
A56: 42697 | B56: 30.474644 | C56: 81.647202 | D56: 28.175901 | E56: 83.648285 | F56: 63.52639 | G56: 83.43045 | H56: 53.996246 | I56: 38.648418 | J56: 2204.72 | K56: 0.48500001 | L56: 1635.5699 | M56: 1049.98 | N56: 1075.97 | O56: 1342.09
A57: 42699 | B57: 30.589636 | C57: 81.639641 | D57: 28.312443 | E57: 83.576874 | F57: 63.852219 | G57: 83.290573 | H57: 54.307823 | I57: 38.781441 | J57: 2213.3501 | K57: 0.47999999 | L57: 1640.8101 | M57: 1054.01 | N57: 1080.23 | O57: 1347.2
A58: 42702 | B58: 30.489975 | C58: 81.926445 | D58: 28.424889 | E58: 83.957573 | F58: 64.241776 | G58: 83.415764 | H58: 54.55843 | I58: 38.547642 | J58: 2201.72 | K58: 0.44999999 | L58: 1628.6801 | M58: 1049.0601 | N58: 1073.05 | O58: 1329.83
A59: 42703 | B59: 30.620317 | C59: 82.017021 | D59: 28.46505 | E59: 84.0448 | F59: 64.765915 | G59: 83.49678 | H59: 55.079975 | I59: 38.55167 | J59: 2204.6599 | K59: 0.46799999 | L59: 1631.11 | M59: 1052.23 | N59: 1072.62 | O59: 1328.22
A60: 42704 | B60: 30.604973 | C60: 81.692482 | D60: 28.513248 | E60: 83.481712 | F60: 64.185104 | G60: 83.540932 | H60: 54.450066 | I60: 38.757259 | J60: 2198.8101 | K60: 0.46799999 | L60: 1627.52 | M60: 1041.8101 | N60: 1077.79 | O60: 1322.34
... A769: 43734 | B769: 38.18961 | C769: 92.0392 | D769: 35.113865 | E769: 94.427345 | F769: 82.786011 | G769: 91.299606 | H769: 72.390205 | I769: 48.593388 | J769: 2977.6201 | K769: 1.77 | L769: 1936.97 | M769: 1609.27 | N769: 1261.6801 | O769: 1533.33
A770: 43735 | B770: 37.949673 | C770: 92.153259 | D770: 34.661827 | E770: 94.561966 | F770: 82.675354 | G770: 91.158318 | H770: 71.988052 | I770: 48.51543 | J770: 2961.79 | K770: 1.73 | L770: 1922.74 | O770: 1520.48
A771: 43738 | B771: 38.098598 | C771: 92.177666 | D771: 34.857994 | E771: 94.637711 | F771: 82.651649 | G771: 91.236794 | H771: 72.111809 | I771: 48.69733 | J771: 2976.74 | K771: 1.77 | L771: 1935.48 | M771: 1605.39 | N771: 1263.1 | O771: 1523.37
A772: 43739 | B772: 37.77594 | C772: 92.345039 | D772: 34.610649 | E772: 94.899765 | F772: 81.821739 | G772: 91.414436 | H772: 71.431267 | I772: 47.956726 | J772: 2940.25 | K772: 1.753 | L772: 1900.02 | M772: 1589.53 | N772: 1243.9399 | O772: 1493.4301
A773: 43740 | B773: 37.089252 | C773: 92.410301 | D773: 34.346252 | E773: 95.228477 | F773: 81.632034 | G773: 91.414436 | H773: 71.129684 | I773: 47.146839 | J773: 2887.6101 | K773: 1.735 | L773: 1873.8199 | M773: 1561.5601 | N773: 1222.47 | O773: 1479.63
A774: 43741 | B774: 37.387085 | C774: 92.769539 | D774: 34.789764 | E774: 95.725662 | F774: 82.359215 | G774: 91.70517 | H774: 71.81794 | I774: 47.350395 | J774: 2910.6299 | K774: 1.665 | L774: 1884.62 | M774: 1578.83 | N774: 1228.84 | O774: 1486.35
A775: 43742 | B775: 37.684929 | C775: 92.916473 | D775: 34.943287 | E775: 95.911087 | F775: 82.801826 | G775: 91.988068 | H775: 72.251007 | I775: 47.987057 | J775: 2952.01 | K775: 1.655 | L775: 1903.79 | M775: 1602.5699 | N775: 1244.7 | O775: 1500.7
A776: 43745 | B776: 37.536011 | C776: 92.663414 | D776: 34.653301 | E776: 95.590828 | F776: 82.635849 | G776: 91.736641 | H776: 72.096344 | I776: 47.748837 | J776: 2938.79 | K776: 1.673 | L776: 1894.05 | M776: 1596.71 | N776: 1238.74 | O776: 1497.79
A777: 43746 | B777: 37.163715 | C777: 92.696045 | D777: 34.40596 | E777: 95.793083 | F777: 82.248543 | G777: 91.650146 | H777: 71.717392 | I777: 46.951946 | J777: 2893.0601 | K777: 1.655 | L777: 1860.86 | M777: 1571.72 | N777: 1218.5699 | O777: 1472.6
A778: 43747 | B778: 37.461544 | C778: 92.647064 | D778: 34.670361 | E778: 95.548676 | F778: 82.351303 | G778: 91.461563 | H778: 71.85659 | I778: 47.341732 | J778: 2919.3999 | K778: 1.628 | L778: 1873.79 | M778: 1588.9399 | N778: 1227.3199 | O778: 1479.46
A779: 43748 | B779: 37.77594 | C779: 92.328697 | D779: 35.028568 | E779: 94.950363 | F779: 82.422447 | G779: 91.170776 | H779: 71.972595 | I779: 47.705532 | J779: 2938.1299 | K779: 1.633 | L779: 1884.17 | M779: 1597.03 | N779: 1236.04 | O779: 1485.36
A780: 43749 | B780: 38.355064 | C780: 92.026657 | D780: 35.591503 | E780: 94.301491 | F780: 82.46196 | G780: 90.887886 | H780: 71.941681 | I780: 48.194931 | J780: 2970.27 | K780: 1.623 | L780: 1916.5699 | M780: 1615.29 | N780: 1250 | O780: 1511.9
A781: 43752 | B781: 38.239246 | C781: 92.181755 | D781: 35.437958 | E781: 94.562691 | F781: 82.477768 | G781: 91.037163 | H781: 71.972595 | I781: 48.125656 | J781: 2966.1499 | K781: 1.618 | L781: 1909.03 | M781: 1614.38 | N781: 1247.1 | O781: 1505.4301
A782: 43753 | B782: 38.628086 | C782: 91.8797 | D782: 35.75354 | E782: 94.107643 | F782: 82.730675 | G782: 90.730659 | H782: 72.065384 | I782: 48.476448 | J782: 2995.6799 | K782: 1.618 | L782: 1924.3101 | M782: 1632.22 | N782: 1257.52 | O782: 1523.3
... A2478: 46220 | B2478: 74.010002 | C2478: 97.520554 | D2478: 63.290001 | E2478: 93.184166 | F2478: 117.61 | G2478: 107.48133 | H2478: 100.02 | I2478: 108.77 | J2478: 7457.6899 | K2478: 3.707 | L2478: 3775.1699 | M2478: 4809.71 | N2478: 2438.0901 | O2478: 2962.22
A2479: 46223 | B2479: 73.739998 | C2479: 97.272293 | D2479: 63.560001 | E2479: 92.886269 | F2479: 117.19 | G2479: 107.26294 | H2479: 99.480003 | I2479: 108.29 | J2479: 7443.2798 | K2479: 3.7049999 | L2479: 3744.5801 | N2479: 2427.1799 | O2479: 2942.4299
A2480: 46224 | B2480: 75.080002 | C2480: 97.063744 | D2480: 65.339996 | E2480: 92.657867 | F2480: 117.61 | G2480: 107.09418 | H2480: 99.519997 | I2480: 108.49 | J2480: 7509.2002 | K2480: 3.73 | L2480: 3784.23 | N2480: 2432.6001 | O2480: 2987.3999
A2481: 46225 | B2481: 75.059998 | C2481: 96.904846 | D2481: 64.989998 | E2481: 92.449333 | F2481: 116.72 | G2481: 106.98498 | H2481: 99.019997 | I2481: 108.52 | J2481: 7498.96 | K2481: 3.7449999 | L2481: 3783.03 | N2481: 2432.95 | O2481: 2959.9399
A2482: 46226 | B2482: 74.309998 | C2482: 96.666504 | D2482: 64.599998 | E2482: 92.20108 | F2482: 116.7 | G2482: 106.70702 | H2482: 98.690002 | I2482: 107.96 | J2482: 7408.2998 | K2482: 3.8 | L2482: 3769.22 | N2482: 2420.01 | O2482: 2940.1599
A2483: 46227 | B2483: 74.099998 | C2483: 96.785683 | D2483: 63.330002 | E2483: 92.379829 | F2483: 119.19 | G2483: 106.71695 | H2483: 100.81 | I2483: 108.85 | J2483: 7411.98 | K2483: 3.8050001 | L2483: 3783.8601 | N2483: 2440.22 | O2483: 2930
A2484: 46230 | B2484: 74.43 | C2484: 97.014091 | D2484: 63.619999 | E2484: 92.628082 | F2484: 118.65 | G2484: 106.60775 | H2484: 100.54 | I2484: 109.5 | J2484: 7413.1802 | K2484: 3.7969999 | L2484: 3795.78 | N2484: 2454.26 | O2484: 2948.04
A2485: 46231 | B2485: 73.940002 | C2485: 97.242493 | D2485: 62.360001 | E2485: 92.90612 | F2485: 118.77 | G2485: 106.87579 | H2485: 100.95 | I2485: 110.5 | J2485: 7428.7798 | K2485: 3.76 | L2485: 3798.3701 | N2485: 2476.6201 | O2485: 2953.8
A2486: 46232 | B2486: 73.169998 | C2486: 96.875061 | D2486: 61.07 | E2486: 92.518845 | F2486: 118.26 | G2486: 106.98498 | H2486: 100.66 | I2486: 109.38 | J2486: 7316.1499 | K2486: 3.658 | L2486: 3734.24 | N2486: 2451.24 | O2486: 2906.3101
A2487: 46233 | B2487: 75.379997 | C2487: 96.944572 | D2487: 63.59 | E2487: 92.558563 | F2487: 116.4 | G2487: 106.95519 | H2487: 99.489998 | I2487: 110 | J2487: 7437.6299 | K2487: 3.675 | L2487: 3764.47 | N2487: 2463.28 | O2487: 2946.1001
A2488: 46234 | B2488: 75.25 | C2488: 96.696312 | D2488: 64.089996 | E2488: 92.300377 | F2488: 115.94 | G2488: 106.84599 | H2488: 98.949997 | I2488: 110.42 | J2488: 7489.7202 | K2488: 3.6819999 | L2488: 3758.6399 | N2488: 2474.3401 | O2488: 2931.3401
A2489: 46237 | B2489: 75.660004 | C2489: 96.923515 | D2489: 64.32 | E2489: 92.487709 | F2489: 115.92 | G2489: 106.86 | H2489: 99.07 | I2489: 111.48 | J2489: 7600.5 | K2489: 3.7 | L2489: 3800.4199 | N2489: 2498.25 | O2489: 2981.9099
A2490: 46238 | B2490: 76.860001 | C2490: 97.322136 | D2490: 66 | E2490: 92.916176 | F2490: 115.02 | G2490: 107.05 | H2490: 98.919998 | I2490: 112.53 | J2490: 7736.52 | K2490: 3.73 | L2490: 3868.4099 | N2490: 2522.29 | O2490: 3036.98
... A2513: 46269 | B2513: 78.5 | C2513: 97 | D2513: 68.699997 | E2513: 92.25 | F2513: 111.33 | G2513: 106.97 | H2513: 96.019997 | I2513: 113.01 | J2513: 7718.6001 | K2513: 3.757 | L2513: 3784.99 | N2513: 2527.49 | O2513: 2975.6499

Sheet Returns
A1: Date | B1: ACWX | C1: AGG | D1: EEM | E1: IEF | F1: RWR | G1: TIP | H1: VNQ | I1: VONV | J1: ^GSPC | K1: ^IRX | L1: ^MID | M1: ^RLG | N1: ^RLV | O1: ^RUT
A2: Annual Arithmetic Average | B2: =(1+AVERAGE(B7:B879,B1399:B2484))^252-1 -> 0.08422986 | C2: =(1+AVERAGE(C7:C879,C1399:C2484))^252-1 -> 0.023342289 | D2: =(1+AVERAGE(D7:D879,D1399:D2484))^252-1 -> 0.079635892 | E2: =(1+AVERAGE(E7:E879,E1399:E2484))^252-1 -> 0.014326235 | F2: =(1+AVERAGE(F7:F879,F1399:F2484))^252-1 -> 0.033021617 | G2: =(1+AVERAGE(G7:G879,G1399:G2484))^252-1 -> 0.014786153 | H2: =(1+AVERAGE(H7:H879,H1399:H2484))^252-1 -> 0.031191862 | I2: =(1+AVERAGE(I7:I879,I1399:I2484))^252-1 -> 0.094978166 | ... O2: =(1+AVERAGE(O7:O879,O1399:O2484))^252-1 -> 0.069254547
A3: Standard Deviation | B3: =_xlfn.STDEV.S(B7:B879,B1399:B2484)*SQRT(252) -> 0.14870493 | C3: =_xlfn.STDEV.S(C7:C879,C1399:C2484)*SQRT(252) -> 0.050775353 | D3: =_xlfn.STDEV.S(D7:D879,D1399:D2484)*SQRT(252) -> 0.18623654 | E3: =_xlfn.STDEV.S(E7:E879,E1399:E2484)*SQRT(252) -> 0.066325712 | F3: =_xlfn.STDEV.S(F7:F879,F1399:F2484)*SQRT(252) -> 0.17371515 | G3: =_xlfn.STDEV.S(G7:G879,G1399:G2484)*SQRT(252) -> 0.051998938 | H3: =_xlfn.STDEV.S(H7:H879,H1399:H2484)*SQRT(252) -> 0.17137514 | I3: =_xlfn.STDEV.S(I7:I879,I1399:I2484)*SQRT(252) -> 0.13754132 | ... O3: =_xlfn.STDEV.S(O7:O879,O1399:O2484)*SQRT(252) -> 0.19839628
A4: Skew | B4: =SKEW(B7:B879,B1399:B2484) -> -0.18715326 | C4: =SKEW(C7:C879,C1399:C2484) -> 0.044676854 | D4: =SKEW(D7:D879,D1399:D2484) -> -0.27984006 | E4: =SKEW(E7:E879,E1399:E2484) -> 0.11729158 | F4: =SKEW(F7:F879,F1399:F2484) -> -0.27674381 | G4: =SKEW(G7:G879,G1399:G2484) -> 0.037046192 | H4: =SKEW(H7:H879,H1399:H2484) -> -0.24837675 | I4: =SKEW(I7:I879,I1399:I2484) -> -0.43600693 | ... O4: =SKEW(O7:O879,O1399:O2484) -> -0.070627631
A5: Excess Kurtosis | B5: =KURT(B7:B879,B1399:B2484) -> 4.3177231 | C5: =KURT(C7:C879,C1399:C2484) -> 2.8538865 | D5: =KURT(D7:D879,D1399:D2484) -> 2.6022015 | E5: =KURT(E7:E879,E1399:E2484) -> 1.8853993 | F5: =KURT(F7:F879,F1399:F2484) -> 3.2315239 | G5: =KURT(G7:G879,G1399:G2484) -> 3.5125697 | H5: =KURT(H7:H879,H1399:H2484) -> 3.2319612 | I5: =KURT(I7:I879,I1399:I2484) -> 5.8998982 | ... O5: =KURT(O7:O879,O1399:O2484) -> 2.7052293
A6: 42621
A7: 42622 | B7: =LN(Prices!B3/Prices!B2) -> -0.022185656 | C7: =LN(Prices!C3/Prices!C2) -> -0.0043758726 | D7: =LN(Prices!D3/Prices!D2) -> -0.034273728 | E7: =LN(Prices!E3/Prices!E2) -> -0.0047631207 | F7: =LN(Prices!F3/Prices!F2) -> -0.038998091 | G7: =LN(Prices!G3/Prices!G2) -> -0.0069279968 | H7: =LN(Prices!H3/Prices!H2) -> -0.040408326 | I7: =LN(Prices!I3/Prices!I2) -> -0.025440904 | J7: =LN(Prices!J3/Prices!J2) -> -0.024827742 | K7: =(Prices!K3-Prices!K2)/100 -> 0 | L7: =LN(Prices!L3/Prices!L2) -> -0.029635455 | M7: =LN(Prices!M3/Prices!M2) -> -0.025123576 | N7: =LN(Prices!N3/Prices!N2) -> -0.025273981 | O7: =LN(Prices!O3/Prices!O2) -> -0.031606198
A8: 42625 | B8: =LN(Prices!B4/Prices!B3) -> 0.0072888539 | C8: =LN(Prices!C4/Prices!C3) -> 0.00080497411 | D8: =LN(Prices!D4/Prices!D3) -> 0.0067867463 | E8: =LN(Prices!E4/Prices!E3) -> 0.00090016008 | F8: =LN(Prices!F4/Prices!F3) -> 0.012013088 | G8: =LN(Prices!G4/Prices!G3) -> 0.00034785267 | H8: =LN(Prices!H4/Prices!H3) -> 0.011778218 | I8: =LN(Prices!I4/Prices!I3) -> 0.014309325 | J8: =LN(Prices!J4/Prices!J3) -> 0.014570387 | K8: =(Prices!K4-Prices!K3)/100 -> 0.0001699999 | L8: =LN(Prices!L4/Prices!L3) -> 0.011488938 | M8: =LN(Prices!M4/Prices!M3) -> 0.014507928 | N8: =LN(Prices!N4/Prices!N3) -> 0.014067608 | O8: =LN(Prices!O4/Prices!O3) -> 0.013572096
A9: 42626 | B9: =LN(Prices!B5/Prices!B4) -> -0.021037987 | C9: =LN(Prices!C5/Prices!C4) -> -0.0027757545 | D9: =LN(Prices!D5/Prices!D4) -> -0.025484155 | E9: =LN(Prices!E5/Prices!E4) -> -0.0036971851 | F9: =LN(Prices!F5/Prices!F4) -> -0.025950972 | G9: =LN(Prices!G5/Prices!G4) -> -0.0044401428 | H9: =LN(Prices!H5/Prices!H4) -> -0.025426995 | I9: =LN(Prices!I5/Prices!I4) -> -0.017042171 | J9: =LN(Prices!J5/Prices!J4) -> -0.014941748 | K9: =(Prices!K5-Prices!K4)/100 -> -4.9999952e-05 | L9: =LN(Prices!L5/Prices!L4) -> -0.018745443 | M9: =LN(Prices!M5/Prices!M4) -> -0.012290012 | N9: =LN(Prices!N5/Prices!N4) -> -0.018197587 | O9: =LN(Prices!O5/Prices!O4) -> -0.019239337
A10: 42627 | B10: =LN(Prices!B6/Prices!B5) -> 0.00024703485 | C10: =LN(Prices!C6/Prices!C5) -> 0.001254764 | D10: =LN(Prices!D6/Prices!D5) -> 0.0030485373 | E10: =LN(Prices!E6/Prices!E5) -> 0.002255392 | F10: =LN(Prices!F6/Prices!F5) -> 0.0040763926 | G10: =LN(Prices!G6/Prices!G5) -> 0.0015692605 | H10: =LN(Prices!H6/Prices!H5) -> 0.003196667 | I10: =LN(Prices!I6/Prices!I5) -> -0.0041688191 | J10: =LN(Prices!J6/Prices!J5) -> -0.0005878494 | K10: =(Prices!K6-Prices!K5)/100 -> -0.00030000001 | L10: =LN(Prices!L6/Prices!L5) -> -0.0029570459 | M10: =LN(Prices!M6/Prices!M5) -> 0.0016772679 | N10: =LN(Prices!N6/Prices!N5) -> -0.0029492119 | O10: =LN(Prices!O6/Prices!O5) -> -0.00060231652
A11: 42628 | B11: =LN(Prices!B7/Prices!B6) -> 0.0098378945 | C11: =LN(Prices!C7/Prices!C6) -> 0.00062592932 | D11: =LN(Prices!D7/Prices!D6) -> 0.017009768 | E11: =LN(Prices!E7/Prices!E6) -> 0.00027098355 | F11: =LN(Prices!F7/Prices!F6) -> 0.0037486527 | G11: =LN(Prices!G7/Prices!G6) -> -0.00026135741 | H11: =LN(Prices!H7/Prices!H6) -> 0.0037747893 | I11: =LN(Prices!I7/Prices!I6) -> 0.010716017 | J11: =LN(Prices!J7/Prices!J6) -> 0.010058516 | K11: =(Prices!K7-Prices!K6)/100 -> -0.00037 | L11: =LN(Prices!L7/Prices!L6) -> 0.010462084 | M11: =LN(Prices!M7/Prices!M6) -> 0.010834436 | N11: =LN(Prices!N7/Prices!N6) -> 0.0091621339 | O11: =LN(Prices!O7/Prices!O6) -> 0.012654963
A12: 42629 | B12: =LN(Prices!B8/Prices!B7) -> -0.01181724 | C12: =LN(Prices!C8/Prices!C7) -> 0.0007162945 | D12: =LN(Prices!D8/Prices!D7) -> -0.0068238616 | E12: =LN(Prices!E8/Prices!E7) -> 0.0010807692 | F12: =LN(Prices!F8/Prices!F7) -> -0.00022019346 | G12: =LN(Prices!G8/Prices!G7) -> 0.0016542013 | H12: =LN(Prices!H8/Prices!H7) -> 0.00047091463 | I12: =LN(Prices!I8/Prices!I7) -> -0.0058906917 | J12: =LN(Prices!J8/Prices!J7) -> -0.0037794278 | K12: =(Prices!K8-Prices!K7)/100 -> -4.9999952e-05 | L12: =LN(Prices!L8/Prices!L7) -> -0.0050694324 | M12: =LN(Prices!M8/Prices!M7) -> -0.0026637951 | N12: =LN(Prices!N8/Prices!N7) -> -0.0047854881 | O12: =LN(Prices!O8/Prices!O7) -> -0.0018272215
A13: 42632 | B13: =LN(Prices!B9/Prices!B8) -> 0.0064184459 | C13: =LN(Prices!C9/Prices!C8) -> -0.00080529973 | D13: =LN(Prices!D9/Prices!D8) -> 0.0079115312 | E13: =LN(Prices!E9/Prices!E8) -> -0.0017118737 | F13: =LN(Prices!F9/Prices!F8) -> 0.0086599213 | G13: =LN(Prices!G9/Prices!G8) -> -0.001218824 | H13: =LN(Prices!H9/Prices!H8) -> 0.0090207873 | I13: =LN(Prices!I9/Prices!I8) -> 0.0018585613 | J13: =LN(Prices!J9/Prices!J8) -> -1.8603234e-05 | K13: =(Prices!K9-Prices!K8)/100 -> -0.00034999996 | L13: =LN(Prices!L9/Prices!L8) -> 0.0074869289 | M13: =LN(Prices!M9/Prices!M8) -> -0.00072508258 | N13: =LN(Prices!N9/Prices!N8) -> 0.0018058216 | O13: =LN(Prices!O9/Prices!O8) -> 0.0063077312
A14: 42633 | B14: =LN(Prices!B10/Prices!B9) -> 0.0041742606 | C14: =LN(Prices!C10/Prices!C9) -> 0.00035760771 | D14: =LN(Prices!D10/Prices!D9) -> 0.00054332698 | E14: =LN(Prices!E10/Prices!E9) -> 0.0015317687 | F14: =LN(Prices!F10/Prices!F9) -> -0.00020804561 | G14: =LN(Prices!G10/Prices!G9) -> -0.00017401983 | H14: =LN(Prices!H10/Prices!H9) -> -0.0015168152 | I14: =LN(Prices!I10/Prices!I9) -> 0.0001645346 | J14: =LN(Prices!J10/Prices!J9) -> 0.00029909348 | K14: =(Prices!K10-Prices!K9)/100 -> 0.00049999982 | L14: =LN(Prices!L10/Prices!L9) -> -0.0046047418 | M14: =LN(Prices!M10/Prices!M9) -> 0.0013144148 | N14: =LN(Prices!N10/Prices!N9) -> -0.0014834527 | O14: =LN(Prices!O10/Prices!O9) -> -0.0034135037
A15: 42634 | B15: =LN(Prices!B11/Prices!B10) -> 0.018932632 | C15: =LN(Prices!C11/Prices!C10) -> 0.0025026683 | D15: =LN(Prices!D11/Prices!D10) -> 0.02758981 | E15: =LN(Prices!E11/Prices!E10) -> 0.0016188246 | F15: =LN(Prices!F11/Prices!F10) -> 0.012084022 | G15: =LN(Prices!G11/Prices!G10) -> 0.0046935091 | H15: =LN(Prices!H11/Prices!H10) -> 0.012767051 | I15: =LN(Prices!I11/Prices!I10) -> 0.010059067 | J15: =LN(Prices!J11/Prices!J10) -> 0.010858 | K15: =(Prices!K11-Prices!K10)/100 -> -0.00064999983 | L15: =LN(Prices!L11/Prices!L10) -> 0.012586448 | M15: =LN(Prices!M11/Prices!M10) -> 0.010052251 | N15: =LN(Prices!N11/Prices!N10) -> 0.011816 | O15: =LN(Prices!O11/Prices!O10) -> 0.013512202
A16: 42635 | B16: =LN(Prices!B12/Prices!B11) -> 0.0098099085 | C16: =LN(Prices!C12/Prices!C11) -> 0.0020509428 | D16: =LN(Prices!D12/Prices!D11) -> 0.0071079891 | E16: =LN(Prices!E12/Prices!E11) -> 0.002962713 | F16: =LN(Prices!F12/Prices!F11) -> 0.01790681 | G16: =LN(Prices!G12/Prices!G11) -> 0.0049299898 | H16: =LN(Prices!H12/Prices!H11) -> 0.017717442 | I16: =LN(Prices!I12/Prices!I11) -> 0.0073704825 | J16: =LN(Prices!J12/Prices!J11) -> 0.0064787519 | K16: =(Prices!K12-Prices!K11)/100 -> -0.00063000008 | L16: =LN(Prices!L12/Prices!L11) -> 0.011758302 | M16: =LN(Prices!M12/Prices!M11) -> 0.0074400884 | N16: =LN(Prices!N12/Prices!N11) -> 0.006397942 | O16: =LN(Prices!O12/Prices!O11) -> 0.014670424
A17: 42636 | B17: =LN(Prices!B13/Prices!B12) -> -0.01005029 | C17: =LN(Prices!C13/Prices!C12) -> -0.00026692995 | D17: =LN(Prices!D13/Prices!D12) -> -0.012937388 | E17: =LN(Prices!E13/Prices!E12) -> 0.00044719372 | F17: =LN(Prices!F13/Prices!F12) -> 0.0030205375 | G17: =LN(Prices!G13/Prices!G12) -> 0.0027573046 | H17: =LN(Prices!H13/Prices!H12) -> 0.0030545878 | I17: =LN(Prices!I13/Prices!I12) -> -0.0061744519 | J17: =LN(Prices!J13/Prices!J12) -> -0.005753293 | K17: =(Prices!K13-Prices!K12)/100 -> 5.0000101e-05 | L17: =LN(Prices!L13/Prices!L12) -> -0.0077848368 | M17: =LN(Prices!M13/Prices!M12) -> -0.0053960209 | N17: =LN(Prices!N13/Prices!N12) -> -0.0059540885 | O17: =LN(Prices!O13/Prices!O12) -> -0.0070053792
A18: 42639 | B18: =LN(Prices!B14/Prices!B13) -> -0.011124858 | C18: =LN(Prices!C14/Prices!C13) -> 0.0012460873 | D18: =LN(Prices!D14/Prices!D13) -> -0.014723765 | E18: =LN(Prices!E14/Prices!E13) -> 0.0028630353 | F18: =LN(Prices!F14/Prices!F13) -> 0.0023093195 | G18: =LN(Prices!G14/Prices!G13) -> 0.00042973072 | H18: =LN(Prices!H14/Prices!H13) -> 0.0023692155 | I18: =LN(Prices!I14/Prices!I13) -> -0.0088403257 | J18: =LN(Prices!J14/Prices!J13) -> -0.0086248501 | K18: =(Prices!K14-Prices!K13)/100 -> 7.9999864e-05 | L18: =LN(Prices!L14/Prices!L13) -> -0.0053663333 | M18: =LN(Prices!M14/Prices!M13) -> -0.0076823734 | N18: =LN(Prices!N14/Prices!N13) -> -0.0087695259 | O18: =LN(Prices!O14/Prices!O13) -> -0.010963624
... A773: 43734 | B773: =LN(Prices!B769/Prices!B768) -> 0.0026033798 | C773: =LN(Prices!C769/Prices!C768) -> 0.0016825653 | D773: =LN(Prices!D769/Prices!D768) -> -0.00024277628 | E773: =LN(Prices!E769/Prices!E768) -> 0.0021408914 | F773: =LN(Prices!F769/Prices!F768) -> 0.0094970493 | G773: =LN(Prices!G769/Prices!G768) -> 0.00060234626 | H773: =LN(Prices!H769/Prices!H768) -> 0.0083675686 | I773: =LN(Prices!I769/Prices!I768) -> -0.0032656996 | J773: =LN(Prices!J769/Prices!J768) -> -0.002431871 | K773: =(Prices!K769-Prices!K768)/100 -> -0.00075000048 | L773: =LN(Prices!L769/Prices!L768) -> -0.0053857009 | M773: =LN(Prices!M769/Prices!M768) -> -0.0019368872 | N773: =LN(Prices!N769/Prices!N768) -> -0.0034418345 | O773: =LN(Prices!O769/Prices!O768) -> -0.011232401
A774: 43735 | B774: =LN(Prices!B770/Prices!B769) -> -0.0063025974 | C774: =LN(Prices!C770/Prices!C769) -> 0.0012384814 | D774: =LN(Prices!D770/Prices!D769) -> -0.012957066 | E774: =LN(Prices!E770/Prices!E769) -> 0.0014246381 | F774: =LN(Prices!F770/Prices!F769) -> -0.001337554 | G774: =LN(Prices!G770/Prices!G769) -> -0.0015487273 | H774: =LN(Prices!H770/Prices!H769) -> -0.0055708396 | I774: =LN(Prices!I770/Prices!I769) -> -0.0016055632 | J774: =LN(Prices!J770/Prices!J769) -> -0.0053305346 | K774: =(Prices!K770-Prices!K769)/100 -> -0.00039999962 | L774: =LN(Prices!L770/Prices!L769) -> -0.0073736343 | O774: =LN(Prices!O770/Prices!O769) -> -0.0084157506
A775: 43738 | B775: =LN(Prices!B771/Prices!B770) -> 0.0039166169 | C775: =LN(Prices!C771/Prices!C770) -> 0.00026481105 | D775: =LN(Prices!D771/Prices!D770) -> 0.0056434988 | E775: =LN(Prices!E771/Prices!E770) -> 0.00080068459 | F775: =LN(Prices!F771/Prices!F770) -> -0.00028675931 | G775: =LN(Prices!G771/Prices!G770) -> 0.00086050505 | H775: =LN(Prices!H771/Prices!H770) -> 0.0017176483 | I775: =LN(Prices!I771/Prices!I770) -> 0.0037423119 | J775: =LN(Prices!J771/Prices!J770) -> 0.0050349102 | K775: =(Prices!K771-Prices!K770)/100 -> 0.00039999962 | L775: =LN(Prices!L771/Prices!L770) -> 0.0066041007 | O775: =LN(Prices!O771/Prices!O770) -> 0.0018989211
A776: 43739 | B776: =LN(Prices!B772/Prices!B771) -> -0.0085051057 | C776: =LN(Prices!C772/Prices!C771) -> 0.0018141258 | D776: =LN(Prices!D772/Prices!D771) -> -0.0071210838 | E776: =LN(Prices!E772/Prices!E771) -> 0.002765201 | F776: =LN(Prices!F772/Prices!F771) -> -0.010091813 | G776: =LN(Prices!G772/Prices!G771) -> 0.0019451594 | H776: =LN(Prices!H772/Prices!H771) -> -0.0094821306 | I776: =LN(Prices!I772/Prices!I771) -> -0.015325149 | J776: =LN(Prices!J772/Prices!J771) -> -0.012334127 | K776: =(Prices!K772-Prices!K771)/100 -> -0.0001699996 | L776: =LN(Prices!L772/Prices!L771) -> -0.018490925 | M776: =LN(Prices!M772/Prices!M771) -> -0.0099283334 | N776: =LN(Prices!N772/Prices!N771) -> -0.015285283 | O776: =LN(Prices!O772/Prices!O771) -> -0.019849459
A777: 43740 | B777: =LN(Prices!B773/Prices!B772) -> -0.018345154 | C777: =LN(Prices!C773/Prices!C772) -> 0.00070646774 | D777: =LN(Prices!D773/Prices!D772) -> -0.0076684989 | E777: =LN(Prices!E773/Prices!E772) -> 0.0034578008 | F777: =LN(Prices!F773/Prices!F772) -> -0.0023212065 | G777: =LN(Prices!G773/Prices!G772) -> 0 | H777: =LN(Prices!H773/Prices!H772) -> -0.0042309312 | I777: =LN(Prices!I773/Prices!I772) -> -0.017032096 | J777: =LN(Prices!J773/Prices!J772) -> -0.018065404 | K777: =(Prices!K773-Prices!K772)/100 -> -0.00018000007 | L777: =LN(Prices!L773/Prices!L772) -> -0.013885323 | M777: =LN(Prices!M773/Prices!M772) -> -0.017753034 | N777: =LN(Prices!N773/Prices!N772) -> -0.017410336 | O777: =LN(Prices!O773/Prices!O772) -> -0.009283464
A778: 43741 | B778: =LN(Prices!B774/Prices!B773) -> 0.007998086 | C778: =LN(Prices!C774/Prices!C773) -> 0.0038798837 | D778: =LN(Prices!D774/Prices!D773) -> 0.012830304 | E778: =LN(Prices!E774/Prices!E773) -> 0.0052073852 | F778: =LN(Prices!F774/Prices!F773) -> 0.008868586 | G778: =LN(Prices!G774/Prices!G773) -> 0.0031753408 | H778: =LN(Prices!H774/Prices!H773) -> 0.0096295497 | I778: =LN(Prices!I774/Prices!I773) -> 0.0043081975 | J778: =LN(Prices!J774/Prices!J773) -> 0.0079403048 | K778: =(Prices!K774-Prices!K773)/100 -> -0.00070000052 | L778: =LN(Prices!L774/Prices!L773) -> 0.0057471072 | M778: =LN(Prices!M774/Prices!M773) -> 0.010998679 | N778: =LN(Prices!N774/Prices!N773) -> 0.0051972289 | O778: =LN(Prices!O774/Prices!O773) -> 0.0045313739
A779: 43742 | B779: =LN(Prices!B775/Prices!B774) -> 0.0079349276 | C779: =LN(Prices!C775/Prices!C774) -> 0.0015826129 | D779: =LN(Prices!D775/Prices!D774) -> 0.0044031557 | E779: =LN(Prices!E775/Prices!E774) -> 0.0019351702 | F779: =LN(Prices!F775/Prices!F774) -> 0.0053597719 | G779: =LN(Prices!G775/Prices!G774) -> 0.0030801153 | H779: =LN(Prices!H775/Prices!H774) -> 0.0060119635 | I779: =LN(Prices!I775/Prices!I774) -> 0.013356157 | J779: =LN(Prices!J775/Prices!J774) -> 0.014116785 | K779: =(Prices!K775-Prices!K774)/100 -> -9.9999905e-05 | L779: =LN(Prices!L775/Prices!L774) -> 0.01012045 | M779: =LN(Prices!M775/Prices!M774) -> 0.014924519 | N779: =LN(Prices!N775/Prices!N774) -> 0.012823891 | O779: =LN(Prices!O775/Prices!O774) -> 0.0096081996
A780: 43745 | B780: =LN(Prices!B776/Prices!B775) -> -0.0039594918 | C780: =LN(Prices!C776/Prices!C775) -> -0.0027272303 | D780: =LN(Prices!D776/Prices!D775) -> -0.0083333779 | E780: =LN(Prices!E776/Prices!E775) -> -0.0033447122 | F780: =LN(Prices!F776/Prices!F775) -> -0.0020065264 | G780: =LN(Prices!G776/Prices!G775) -> -0.0027369955 | H780: =LN(Prices!H776/Prices!H775) -> -0.0021429301 | I780: =LN(Prices!I776/Prices!I775) -> -0.0049766226 | J780: =LN(Prices!J776/Prices!J775) -> -0.0044883523 | K780: =(Prices!K776-Prices!K775)/100 -> 0.00018000007 | L780: =LN(Prices!L776/Prices!L775) -> -0.0051292373 | M780: =LN(Prices!M776/Prices!M775) -> -0.0036633193 | N780: =LN(Prices!N776/Prices!N775) -> -0.0047997717 | O780: =LN(Prices!O776/Prices!O775) -> -0.001940919
A781: 43746 | B781: =LN(Prices!B777/Prices!B776) -> -0.0099678669 | C781: =LN(Prices!C777/Prices!C776) -> 0.00035208261 | D781: =LN(Prices!D777/Prices!D776) -> -0.0071631874 | E781: =LN(Prices!E777/Prices!E776) -> 0.0021136084 | F781: =LN(Prices!F777/Prices!F776) -> -0.004697921 | G781: =LN(Prices!G777/Prices!G776) -> -0.00094330081 | H781: =LN(Prices!H777/Prices!H776) -> -0.0052700516 | I781: =LN(Prices!I777/Prices!I776) -> -0.016830042 | J781: =LN(Prices!J777/Prices!J776) -> -0.01568316 | K781: =(Prices!K777-Prices!K776)/100 -> -0.00018000007 | L781: =LN(Prices!L777/Prices!L776) -> -0.017678681 | M781: =LN(Prices!M777/Prices!M776) -> -0.015774695 | N781: =LN(Prices!N777/Prices!N776) -> -0.01641673 | O781: =LN(Prices!O777/Prices!O776) -> -0.016961185
A782: 43747 | B782: =LN(Prices!B778/Prices!B777) -> 0.0079820227 | C782: =LN(Prices!C778/Prices!C777) -> -0.00052854098 | D782: =LN(Prices!D778/Prices!D777) -> 0.007655352 | E782: =LN(Prices!E778/Prices!E777) -> -0.0025546727 | F782: =LN(Prices!F778/Prices!F777) -> 0.0012486078 | G782: =LN(Prices!G778/Prices!G777) -> -0.0020597639 | H782: =LN(Prices!H778/Prices!H777) -> 0.001939047 | I782: =LN(Prices!I778/Prices!I777) -> 0.0082675317 | J782: =LN(Prices!J778/Prices!J777) -> 0.0090632965 | K782: =(Prices!K778-Prices!K777)/100 -> -0.0002699995 | L782: =LN(Prices!L778/Prices!L777) -> 0.0069244 | M782: =LN(Prices!M778/Prices!M777) -> 0.010896548 | N782: =LN(Prices!N778/Prices!N777) -> 0.0071548906 | O782: =LN(Prices!O778/Prices!O777) -> 0.0046476006
A783: 43748 | B783: =LN(Prices!B779/Prices!B778) -> 0.008357476 | C783: =LN(Prices!C779/Prices!C778) -> -0.0034422599 | D783: =LN(Prices!D779/Prices!D778) -> 0.010278805 | E783: =LN(Prices!E779/Prices!E778) -> -0.0062815471 | F783: =LN(Prices!F779/Prices!F778) -> 0.00086353692 | G783: =LN(Prices!G779/Prices!G778) -> -0.0031843976 | H783: =LN(Prices!H779/Prices!H778) -> 0.0016130936 | I783: =LN(Prices!I779/Prices!I778) -> 0.0076551772 | J783: =LN(Prices!J779/Prices!J778) -> 0.0063952024 | K783: =(Prices!K779-Prices!K778)/100 -> 4.9999952e-05 | L783: =LN(Prices!L779/Prices!L778) -> 0.0055242903 | M783: =LN(Prices!M779/Prices!M778) -> 0.0050785823 | N783: =LN(Prices!N779/Prices!N778) -> 0.0070798659 | O783: =LN(Prices!O779/Prices!O778) -> 0.0039800273
A784: 43749 | B784: =LN(Prices!B780/Prices!B779) -> 0.015214186 | C784: =LN(Prices!C780/Prices!C779) -> -0.0032767193 | D784: =LN(Prices!D780/Prices!D779) -> 0.015942969 | E784: =LN(Prices!E780/Prices!E779) -> -0.0068572635 | F784: =LN(Prices!F780/Prices!F779) -> 0.00047927679 | G784: =LN(Prices!G780/Prices!G779) -> -0.0031076857 | H784: =LN(Prices!H780/Prices!H779) -> -0.00042962113 | I784: =LN(Prices!I780/Prices!I779) -> 0.010206483 | J784: =LN(Prices!J780/Prices!J779) -> 0.01087958 | K784: =(Prices!K780-Prices!K779)/100 -> -9.9999905e-05 | L784: =LN(Prices!L780/Prices!L779) -> 0.017049673 | M784: =LN(Prices!M780/Prices!M779) -> 0.011368859 | N784: =LN(Prices!N780/Prices!N779) -> 0.011230799 | O784: =LN(Prices!O780/Prices!O779) -> 0.017709997
A785: 43752 | B785: =LN(Prices!B781/Prices!B780) -> -0.0030241962 | C785: =LN(Prices!C781/Prices!C780) -> 0.0016839404 | D785: =LN(Prices!D781/Prices!D780) -> -0.0043234347 | E785: =LN(Prices!E781/Prices!E780) -> 0.0027660101 | F785: =LN(Prices!F781/Prices!F780) -> 0.00019168342 | G785: =LN(Prices!G781/Prices!G780) -> 0.0016410799 | H785: =LN(Prices!H781/Prices!H780) -> 0.00042962113 | I785: =LN(Prices!I781/Prices!I780) -> -0.0014384238 | J785: =LN(Prices!J781/Prices!J780) -> -0.0013880817 | K785: =(Prices!K781-Prices!K780)/100 -> -4.9999952e-05 | L785: =LN(Prices!L781/Prices!L780) -> -0.0039418271 | M785: =LN(Prices!M781/Prices!M780) -> -0.00056354624 | N785: =LN(Prices!N781/Prices!N780) -> -0.0023227149 | O785: =LN(Prices!O781/Prices!O780) -> -0.0042885468
A786: 43753 | B786: =LN(Prices!B782/Prices!B781) -> 0.010117251 | C786: =LN(Prices!C782/Prices!C781) -> -0.0032821172 | D786: =LN(Prices!D782/Prices!D781) -> 0.0088657874 | E786: =LN(Prices!E782/Prices!E781) -> -0.0048237418 | F786: =LN(Prices!F782/Prices!F781) -> 0.0030616716 | G786: =LN(Prices!G782/Prices!G781) -> -0.0033724735 | H786: =LN(Prices!H782/Prices!H781) -> 0.0012883923 | I786: =LN(Prices!I782/Prices!I781) -> 0.0072626466 | J786: =LN(Prices!J782/Prices!J781) -> 0.0099064454 | K786: =(Prices!K782-Prices!K781)/100 -> 0 | L786: =LN(Prices!L782/Prices!L781) -> 0.0079722174 | M786: =LN(Prices!M782/Prices!M781) -> 0.010990048 | N786: =LN(Prices!N782/Prices!N781) -> 0.0083207066 | O786: =LN(Prices!O782/Prices!O781) -> 0.011800459
A787: 43754 | B787: =LN(Prices!B783/Prices!B782) -> 0.0012842673 | C787: =LN(Prices!C783/Prices!C782) -> 0.0017755759 | D787: =LN(Prices!D783/Prices!D782) -> 0.0028585174 | E787: =LN(Prices!E783/Prices!E782) -> 0.0019681667 | F787: =LN(Prices!F783/Prices!F782) -> 0.00076411673 | G787: =LN(Prices!G783/Prices!G782) -> 0.0015581205 | H787: =LN(Prices!H783/Prices!H782) -> 0.00010734406 | I787: =LN(Prices!I783/Prices!I782) -> -0.00062555908 | J787: =LN(Prices!J783/Prices!J782) -> -0.0020015446 | K787: =(Prices!K783-Prices!K782)/100 -> -3.000021e-05 | L787: =LN(Prices!L783/Prices!L782) -> -0.00099307424 | M787: =LN(Prices!M783/Prices!M782) -> -0.0037442273 | N787: =LN(Prices!N783/Prices!N782) -> -0.0013209578 | O787: =LN(Prices!O783/Prices!O782) -> 0.0011547258
... A879: 43889 | B879: =LN(Prices!B875/Prices!B874) -> -0.0060791193 | C879: =LN(Prices!C875/Prices!C874) -> 0.0073404913 | D879: =LN(Prices!D875/Prices!D874) -> -0.0036951754 | E879: =LN(Prices!E875/Prices!E874) -> 0.01114826 | F879: =LN(Prices!F875/Prices!F874) -> -0.023674115 | G879: =LN(Prices!G875/Prices!G874) -> 0.0015838973 | H879: =LN(Prices!H875/Prices!H874) -> -0.024432692 | I879: =LN(Prices!I875/Prices!I874) -> -0.014709707 | J879: =LN(Prices!J875/Prices!J874) -> -0.0082724631 | K879: =(Prices!K875-Prices!K874)/100 -> -0.0016499996 | L879: =LN(Prices!L875/Prices!L874) -> -0.020629219 | M879: =LN(Prices!M875/Prices!M874) -> -0.0017803736 | N879: =LN(Prices!N875/Prices!N874) -> -0.016118301 | O879: =LN(Prices!O875/Prices!O874) -> -0.014417048
A881: 43892 | B881: =LN(Prices!B876/Prices!B875) -> 0.015907296 | C881: =LN(Prices!C876/Prices!C875) -> -0.00035338105 | D881: =LN(Prices!D876/Prices!D875) -> 0.021485273 | E881: =LN(Prices!E876/Prices!E875) -> -0.00068293411 | F881: =LN(Prices!F876/Prices!F875) -> 0.036485485 | G881: =LN(Prices!G876/Prices!G875) -> 0.0023301263 | H881: =LN(Prices!H876/Prices!H875) -> 0.041824531 | I881: =LN(Prices!I876/Prices!I875) -> 0.039238746 | J881: =LN(Prices!J876/Prices!J875) -> 0.045010869 | K881: =(Prices!K876-Prices!K875)/100 -> -0.00095000029 | L881: =LN(Prices!L876/Prices!L875) -> 0.033324927 | M881: =LN(Prices!M876/Prices!M875) -> 0.046191899 | N881: =LN(Prices!N876/Prices!N875) -> 0.040681662 | O881: =LN(Prices!O876/Prices!O875) -> 0.028089366
A882: 43893 | B882: =LN(Prices!B877/Prices!B876) -> -0.0064667434 | C882: =LN(Prices!C877/Prices!C876) -> 0.006790612 | D882: =LN(Prices!D877/Prices!D876) -> -0.0067861177 | E882: =LN(Prices!E877/Prices!E876) -> 0.011552997 | F882: =LN(Prices!F877/Prices!F876) -> -0.0041147653 | G882: =LN(Prices!G877/Prices!G876) -> 0.010089254 | H882: =LN(Prices!H877/Prices!H876) -> -0.0023085076 | I882: =LN(Prices!I877/Prices!I876) -> -0.023692348 | J882: =LN(Prices!J877/Prices!J876) -> -0.028510485 | K882: =(Prices!K877-Prices!K876)/100 -> -0.0021700001 | L882: =LN(Prices!L877/Prices!L876) -> -0.021711293 | M882: =LN(Prices!M877/Prices!M876) -> -0.029755554 | N882: =LN(Prices!N877/Prices!N876) -> -0.025459851 | O882: =LN(Prices!O877/Prices!O876) -> -0.021574663
A883: 43894 | B883: =LN(Prices!B878/Prices!B877) -> 0.023436799 | C883: =LN(Prices!C878/Prices!C877) -> -0.00077134287 | D883: =LN(Prices!D878/Prices!D877) -> 0.017597008 | E883: =LN(Prices!E878/Prices!E877) -> -0.0021984773 | F883: =LN(Prices!F878/Prices!F877) -> 0.036139209 | G883: =LN(Prices!G878/Prices!G877) -> -0.0014818628 | H883: =LN(Prices!H878/Prices!H877) -> 0.037059156 | I883: =LN(Prices!I878/Prices!I877) -> 0.037482066 | J883: =LN(Prices!J878/Prices!J877) -> 0.041336349 | K883: =(Prices!K878-Prices!K877)/100 -> -0.0024299997 | L883: =LN(Prices!L878/Prices!L877) -> 0.034526954 | M883: =LN(Prices!M878/Prices!M877) -> 0.041735932 | N883: =LN(Prices!N878/Prices!N877) -> 0.038777889 | O883: =LN(Prices!O878/Prices!O877) -> 0.029909959
A884: 43895 | B884: =LN(Prices!B879/Prices!B878) -> -0.024108263 | C884: =LN(Prices!C879/Prices!C878) -> 0.0030815709 | D884: =LN(Prices!D879/Prices!D878) -> -0.021251563 | E884: =LN(Prices!E879/Prices!E878) -> 0.0088487184 | F884: =LN(Prices!F879/Prices!F878) -> -0.023438071 | G884: =LN(Prices!G879/Prices!G878) -> 0.0031264416 | H884: =LN(Prices!H879/Prices!H878) -> -0.021658538 | I884: =LN(Prices!I879/Prices!I878) -> -0.033309076 | J884: =LN(Prices!J879/Prices!J878) -> -0.034510782 | K884: =(Prices!K879-Prices!K878)/100 -> -0.00079999983 | L884: =LN(Prices!L879/Prices!L878) -> -0.037020236 | M884: =LN(Prices!M879/Prices!M878) -> -0.033281824 | N884: =LN(Prices!N879/Prices!N878) -> -0.035560769 | O884: =LN(Prices!O879/Prices!O878) -> -0.034807274
A885: 43896 | B885: =LN(Prices!B880/Prices!B879) -> -0.014658023 | C885: =LN(Prices!C880/Prices!C879) -> 0.0073241513 | D885: =LN(Prices!D880/Prices!D879) -> -0.020716232 | E885: =LN(Prices!E880/Prices!E879) -> 0.010100491 | F885: =LN(Prices!F880/Prices!F879) -> -0.018283279 | G885: =LN(Prices!G880/Prices!G879) -> 0.006631728 | H885: =LN(Prices!H880/Prices!H879) -> -0.017383912 | I885: =LN(Prices!I880/Prices!I879) -> -0.020474635 | J885: =LN(Prices!J880/Prices!J879) -> -0.017200944 | K885: =(Prices!K880-Prices!K879)/100 -> -0.0018000004 | L885: =LN(Prices!L880/Prices!L879) -> -0.01809655 | M885: =LN(Prices!M880/Prices!M879) -> -0.015808197 | N885: =LN(Prices!N880/Prices!N879) -> -0.020017007 | O885: =LN(Prices!O880/Prices!O879) -> -0.020218976
A886: 43899 | B886: =LN(Prices!B881/Prices!B880) -> -0.083342095 | C886: =LN(Prices!C881/Prices!C880) -> -0.0012737483 | D886: =LN(Prices!D881/Prices!D880) -> -0.070720696 | E886: =LN(Prices!E881/Prices!E880) -> 0.0089299819 | F886: =LN(Prices!F881/Prices!F880) -> -0.081157876 | G886: =LN(Prices!G881/Prices!G880) -> -0.020778983 | H886: =LN(Prices!H881/Prices!H880) -> -0.080226464 | I886: =LN(Prices!I881/Prices!I880) -> -0.095366733 | J886: =LN(Prices!J881/Prices!J880) -> -0.079010413 | K886: =(Prices!K881-Prices!K880)/100 -> -0.00084999979 | L886: =LN(Prices!L881/Prices!L880) -> -0.095747492 | M886: =LN(Prices!M881/Prices!M880) -> -0.071487139 | N886: =LN(Prices!N881/Prices!N880) -> -0.091350284 | O886: =LN(Prices!O881/Prices!O880) -> -0.098375855
A887: 43900 | B887: =LN(Prices!B882/Prices!B881) -> 0.038745763 | C887: =LN(Prices!C882/Prices!C881) -> -0.011363416 | D887: =LN(Prices!D882/Prices!D881) -> 0.049566875 | E887: =LN(Prices!E882/Prices!E881) -> -0.018527825 | F887: =LN(Prices!F882/Prices!F881) -> 0.037728072 | G887: =LN(Prices!G882/Prices!G881) -> -0.029080487 | H887: =LN(Prices!H882/Prices!H881) -> 0.041380445 | I887: =LN(Prices!I882/Prices!I881) -> 0.045598386 | J887: =LN(Prices!J882/Prices!J881) -> 0.048215052 | K887: =(Prices!K882-Prices!K881)/100 -> 0.00059999973 | L887: =LN(Prices!L882/Prices!L881) -> 0.03785687 | M887: =LN(Prices!M882/Prices!M881) -> 0.051697555 | N887: =LN(Prices!N882/Prices!N881) -> 0.042376758 | O887: =LN(Prices!O882/Prices!O881) -> 0.02812145
A888: 43901 | B888: =LN(Prices!B883/Prices!B882) -> -0.051168374 | C888: =LN(Prices!C883/Prices!C882) -> -0.014366225 | D888: =LN(Prices!D883/Prices!D882) -> -0.047696594 | E888: =LN(Prices!E883/Prices!E882) -> -0.010028859 | F888: =LN(Prices!F883/Prices!F882) -> -0.071222191 | G888: =LN(Prices!G883/Prices!G882) -> -0.022906027 | H888: =LN(Prices!H883/Prices!H882) -> -0.061968903 | I888: =LN(Prices!I883/Prices!I882) -> -0.055098971 | J888: =LN(Prices!J883/Prices!J882) -> -0.050102893 | K888: =(Prices!K883-Prices!K882)/100 -> -0.00021999985 | L888: =LN(Prices!L883/Prices!L882) -> -0.068291321 | M888: =LN(Prices!M883/Prices!M882) -> -0.047835669 | N888: =LN(Prices!N883/Prices!N882) -> -0.055360021 | O888: =LN(Prices!O883/Prices!O882) -> -0.066252407
A889: 43902 | B889: =LN(Prices!B884/Prices!B883) -> -0.11793917 | C889: =LN(Prices!C884/Prices!C883) -> -0.040833203 | D889: =LN(Prices!D884/Prices!D883) -> -0.10547909 | E889: =LN(Prices!E884/Prices!E883) -> 0.00050821952 | F889: =LN(Prices!F884/Prices!F883) -> -0.10533491 | G889: =LN(Prices!G884/Prices!G883) -> -0.0023725145 | H889: =LN(Prices!H884/Prices!H883) -> -0.10680961 | I889: =LN(Prices!I884/Prices!I883) -> -0.10439378 | J889: =LN(Prices!J884/Prices!J883) -> -0.099944852 | K889: =(Prices!K884-Prices!K883)/100 -> -0.00094999999 | L889: =LN(Prices!L884/Prices!L883) -> -0.1049841 | M889: =LN(Prices!M884/Prices!M883) -> -0.09629694 | N889: =LN(Prices!N884/Prices!N883) -> -0.10565842 | O889: =LN(Prices!O884/Prices!O883) -> -0.11857726
A890: 43903 | B890: =LN(Prices!B885/Prices!B884) -> 0.064010915 | C890: =LN(Prices!C885/Prices!C884) -> 0.015587049 | D890: =LN(Prices!D885/Prices!D884) -> 0.069605548 | E890: =LN(Prices!E885/Prices!E884) -> -0.0065401974 | F890: =LN(Prices!F885/Prices!F884) -> 0.080857175 | G890: =LN(Prices!G885/Prices!G884) -> 0.0039511825 | H890: =LN(Prices!H885/Prices!H884) -> 0.083677387 | I890: =LN(Prices!I885/Prices!I884) -> 0.088640449 | J890: =LN(Prices!J885/Prices!J884) -> 0.088808407 | K890: =(Prices!K885-Prices!K884)/100 -> -0.00030000001 | L890: =LN(Prices!L885/Prices!L884) -> 0.080763841 | M890: =LN(Prices!M885/Prices!M884) -> 0.086506129 | N890: =LN(Prices!N885/Prices!N884) -> 0.086617077 | O890: =LN(Prices!O885/Prices!O884) -> 0.074786407
A891: 43906 | B891: =LN(Prices!B886/Prices!B885) -> -0.1159706 | C891: =LN(Prices!C886/Prices!C885) -> 0.016578677 | D891: =LN(Prices!D886/Prices!D885) -> -0.13329407 | E891: =LN(Prices!E886/Prices!E885) -> 0.026073798 | F891: =LN(Prices!F886/Prices!F885) -> -0.20224726 | G891: =LN(Prices!G886/Prices!G885) -> -0.0069468384 | H891: =LN(Prices!H886/Prices!H885) -> -0.1951363 | I891: =LN(Prices!I886/Prices!I885) -> -0.12383546 | J891: =LN(Prices!J886/Prices!J885) -> -0.1276522 | K891: =(Prices!K886-Prices!K885)/100 -> -0.00057999998 | L891: =LN(Prices!L886/Prices!L885) -> -0.14788406 | M891: =LN(Prices!M886/Prices!M885) -> -0.13181563 | N891: =LN(Prices!N886/Prices!N885) -> -0.12802407 | O891: =LN(Prices!O886/Prices!O885) -> -0.15399089
A892: 43907 | B892: =LN(Prices!B887/Prices!B886) -> 0.052522279 | C892: =LN(Prices!C887/Prices!C886) -> -0.026190365 | D892: =LN(Prices!D887/Prices!D886) -> 0.066650628 | E892: =LN(Prices!E887/Prices!E886) -> -0.02539282 | F892: =LN(Prices!F887/Prices!F886) -> 0.058623954 | G892: =LN(Prices!G887/Prices!G886) -> -0.028369495 | H892: =LN(Prices!H887/Prices!H886) -> 0.056197745 | I892: =LN(Prices!I887/Prices!I886) -> 0.05798896 | J892: =LN(Prices!J887/Prices!J886) -> 0.058226313 | K892: =(Prices!K887-Prices!K886)/100 -> -0.00019999996 | L892: =LN(Prices!L887/Prices!L886) -> 0.05054048 | M892: =LN(Prices!M887/Prices!M886) -> 0.053878488 | N892: =LN(Prices!N887/Prices!N886) -> 0.058114238 | O892: =LN(Prices!O887/Prices!O886) -> 0.064474023
... A1397: 44637 | B1397: =LN(Prices!B1392/Prices!B1391) -> 0.006000236 | C1397: =LN(Prices!C1392/Prices!C1391) -> 0.0016702475 | D1397: =LN(Prices!D1392/Prices!D1391) -> -0.0051300474 | E1397: =LN(Prices!E1392/Prices!E1391) -> -0.0019293289 | F1397: =LN(Prices!F1392/Prices!F1391) -> 0.011513003 | G1397: =LN(Prices!G1392/Prices!G1391) -> 0.013544248 | H1397: =LN(Prices!H1392/Prices!H1391) -> 0.015342833 | I1397: =LN(Prices!I1392/Prices!I1391) -> 0.012382695 | J1397: =LN(Prices!J1392/Prices!J1391) -> 0.012272205 | K1397: =(Prices!K1392-Prices!K1391)/100 -> -0.00072999984 | L1397: =LN(Prices!L1392/Prices!L1391) -> 0.0098498101 | M1397: =LN(Prices!M1392/Prices!M1391) -> 0.014129814 | N1397: =LN(Prices!N1392/Prices!N1391) -> 0.011934027 | O1397: =LN(Prices!O1392/Prices!O1391) -> 0.016749526
A1399: 44638 | B1399: =LN(Prices!B1393/Prices!B1392) -> 0.010939485 | C1399: =LN(Prices!C1393/Prices!C1392) -> 0.0022229131 | D1399: =LN(Prices!D1393/Prices!D1392) -> 0.014209792 | E1399: =LN(Prices!E1393/Prices!E1392) -> 0.0029384076 | F1399: =LN(Prices!F1393/Prices!F1392) -> 0.0032278041 | G1399: =LN(Prices!G1393/Prices!G1392) -> -0.0030730591 | H1399: =LN(Prices!H1393/Prices!H1392) -> 0 | I1399: =LN(Prices!I1393/Prices!I1392) -> 0.0028993123 | J1399: =LN(Prices!J1393/Prices!J1392) -> 0.011594814 | K1399: =(Prices!K1393-Prices!K1392)/100 -> 0.00022999972 | L1399: =LN(Prices!L1393/Prices!L1392) -> 0.0079813301 | M1399: =LN(Prices!M1393/Prices!M1392) -> 0.020785358 | N1399: =LN(Prices!N1393/Prices!N1392) -> 0.0039897153 | O1399: =LN(Prices!O1393/Prices!O1392) -> 0.010175496
A1400: 44641 | B1400: =LN(Prices!B1394/Prices!B1393) -> -0.0076643191 | C1400: =LN(Prices!C1394/Prices!C1393) -> -0.0098543203 | D1400: =LN(Prices!D1394/Prices!D1393) -> -0.015552347 | E1400: =LN(Prices!E1394/Prices!E1393) -> -0.013104555 | F1400: =LN(Prices!F1394/Prices!F1393) -> -0.0045244638 | G1400: =LN(Prices!G1394/Prices!G1393) -> -0.0088775511 | H1400: =LN(Prices!H1394/Prices!H1393) -> -0.0061277144 | I1400: =LN(Prices!I1394/Prices!I1393) -> 0.0020664608 | J1400: =LN(Prices!J1394/Prices!J1393) -> -0.00043475485 | K1400: =(Prices!K1394-Prices!K1393)/100 -> 0.00072000027 | L1400: =LN(Prices!L1394/Prices!L1393) -> -0.0034652596 | M1400: =LN(Prices!M1394/Prices!M1393) -> -0.0037161252 | N1400: =LN(Prices!N1394/Prices!N1393) -> 0.0015065917 | O1400: =LN(Prices!O1394/Prices!O1393) -> -0.0097301166
A1401: 44642 | B1401: =LN(Prices!B1395/Prices!B1394) -> 0.011664489 | C1401: =LN(Prices!C1395/Prices!C1394) -> -0.0027133021 | D1401: =LN(Prices!D1395/Prices!D1394) -> 0.017974716 | E1401: =LN(Prices!E1395/Prices!E1394) -> -0.005496064 | F1401: =LN(Prices!F1395/Prices!F1394) -> 0.0033340509 | G1401: =LN(Prices!G1395/Prices!G1394) -> -0.0046286435 | H1401: =LN(Prices!H1395/Prices!H1394) -> 0.0025498939 | I1401: =LN(Prices!I1395/Prices!I1394) -> 0.0063088948 | J1401: =LN(Prices!J1395/Prices!J1394) -> 0.0112407 | K1401: =(Prices!K1395-Prices!K1394)/100 -> 0.00064999968 | L1401: =LN(Prices!L1395/Prices!L1394) -> 0.0063879902 | M1401: =LN(Prices!M1395/Prices!M1394) -> 0.017476386 | N1401: =LN(Prices!N1395/Prices!N1394) -> 0.0061015903 | O1401: =LN(Prices!O1395/Prices!O1394) -> 0.010784234
A1402: 44643 | B1402: =LN(Prices!B1396/Prices!B1395) -> -0.010511089 | C1402: =LN(Prices!C1396/Prices!C1395) -> 0.0041133951 | D1402: =LN(Prices!D1396/Prices!D1395) -> -0.0066199495 | E1402: =LN(Prices!E1396/Prices!E1395) -> 0.0067032647 | F1402: =LN(Prices!F1396/Prices!F1395) -> -0.011097598 | G1402: =LN(Prices!G1396/Prices!G1395) -> 0.012480148 | H1402: =LN(Prices!H1396/Prices!H1395) -> -0.011282769 | I1402: =LN(Prices!I1396/Prices!I1395) -> -0.011966364 | J1402: =LN(Prices!J1396/Prices!J1395) -> -0.01234863 | K1402: =(Prices!K1396-Prices!K1395)/100 -> -0.00039999992 | L1402: =LN(Prices!L1396/Prices!L1395) -> -0.018356389 | M1402: =LN(Prices!M1396/Prices!M1395) -> -0.014042249 | N1402: =LN(Prices!N1396/Prices!N1395) -> -0.011208711 | O1402: =LN(Prices!O1396/Prices!O1395) -> -0.017452292
A1403: 44644 | B1403: =LN(Prices!B1397/Prices!B1396) -> 0.0065109198 | C1403: =LN(Prices!C1397/Prices!C1396) -> -0.0022413073 | D1403: =LN(Prices!D1397/Prices!D1396) -> 0.0052993677 | E1403: =LN(Prices!E1397/Prices!E1396) -> -0.0055828877 | F1403: =LN(Prices!F1397/Prices!F1396) -> 0.0063565119 | G1403: =LN(Prices!G1397/Prices!G1396) -> -0.0061809535 | H1403: =LN(Prices!H1397/Prices!H1396) -> 0.0063103969 | I1403: =LN(Prices!I1397/Prices!I1396) -> 0.010793562 | J1403: =LN(Prices!J1397/Prices!J1396) -> 0.014242012 | K1403: =(Prices!K1397-Prices!K1396)/100 -> 3.000021e-05 | L1403: =LN(Prices!L1397/Prices!L1396) -> 0.010933155 | M1403: =LN(Prices!M1397/Prices!M1396) -> 0.018151008 | N1403: =LN(Prices!N1397/Prices!N1396) -> 0.0096745546 | O1403: =LN(Prices!O1397/Prices!O1396) -> 0.011255909
A1404: 44645 | B1404: =LN(Prices!B1398/Prices!B1397) -> -0.00076387653 | C1404: =LN(Prices!C1398/Prices!C1397) -> -0.0079793484 | D1404: =LN(Prices!D1398/Prices!D1397) -> -0.0079595733 | E1404: =LN(Prices!E1398/Prices!E1397) -> -0.010316165 | F1404: =LN(Prices!F1398/Prices!F1397) -> 0.013288038 | G1404: =LN(Prices!G1398/Prices!G1397) -> -0.0068590574 | H1404: =LN(Prices!H1398/Prices!H1397) -> 0.012408229 | I1404: =LN(Prices!I1398/Prices!I1397) -> 0.0093036198 | J1404: =LN(Prices!J1398/Prices!J1397) -> 0.0050533807 | K1404: =(Prices!K1398-Prices!K1397)/100 -> 0.00036999971 | L1404: =LN(Prices!L1398/Prices!L1397) -> 0.0069440559 | M1404: =LN(Prices!M1398/Prices!M1397) -> -0.0010112145 | N1404: =LN(Prices!N1398/Prices!N1397) -> 0.0094364448 | O1404: =LN(Prices!O1398/Prices!O1397) -> 0.0012231074
A1405: 44648 | B1405: =LN(Prices!B1399/Prices!B1398) -> -0.0013380035 | C1405: =LN(Prices!C1399/Prices!C1398) -> 0.0024472479 | D1405: =LN(Prices!D1399/Prices!D1398) -> 0.0033243163 | E1405: =LN(Prices!E1399/Prices!E1398) -> 0.0022597507 | F1405: =LN(Prices!F1399/Prices!F1398) -> 0.009679391 | G1405: =LN(Prices!G1399/Prices!G1398) -> -0.0011211063 | H1405: =LN(Prices!H1399/Prices!H1398) -> 0.010581306 | I1405: =LN(Prices!I1399/Prices!I1398) -> -0.00054497575 | J1405: =LN(Prices!J1399/Prices!J1398) -> 0.007119551 | K1405: =(Prices!K1399-Prices!K1398)/100 -> -0.00011999965 | L1405: =LN(Prices!L1399/Prices!L1398) -> 0.00169818 | M1405: =LN(Prices!M1399/Prices!M1398) -> 0.014834573 | N1405: =LN(Prices!N1399/Prices!N1398) -> -0.00047875644 | O1405: =LN(Prices!O1399/Prices!O1398) -> 3.8535781e-05
A1406: 44649 | B1406: =LN(Prices!B1400/Prices!B1399) -> 0.01875942 | C1406: =LN(Prices!C1400/Prices!C1399) -> 0.004690178 | D1406: =LN(Prices!D1400/Prices!D1399) -> 0.016891979 | E1406: =LN(Prices!E1400/Prices!E1399) -> 0.0049729307 | F1406: =LN(Prices!F1400/Prices!F1399) -> 0.02924075 | G1406: =LN(Prices!G1400/Prices!G1399) -> -0.0036119668 | H1406: =LN(Prices!H1400/Prices!H1399) -> 0.028918332 | I1406: =LN(Prices!I1400/Prices!I1399) -> 0.0096278974 | J1406: =LN(Prices!J1400/Prices!J1399) -> 0.012182044 | K1406: =(Prices!K1400-Prices!K1399)/100 -> 0.00046999991 | L1406: =LN(Prices!L1400/Prices!L1399) -> 0.020646302 | M1406: =LN(Prices!M1400/Prices!M1399) -> 0.017773028 | N1406: =LN(Prices!N1400/Prices!N1399) -> 0.0093766591 | O1406: =LN(Prices!O1400/Prices!O1399) -> 0.026141572
A1407: 44650 | B1407: =LN(Prices!B1401/Prices!B1400) -> -0.0035730607 | C1407: =LN(Prices!C1401/Prices!C1400) -> 0.0027101797 | D1407: =LN(Prices!D1401/Prices!D1400) -> -0.002832033 | E1407: =LN(Prices!E1401/Prices!E1400) -> 0.0039227792 | F1407: =LN(Prices!F1401/Prices!F1400) -> -0.0083038221 | G1407: =LN(Prices!G1401/Prices!G1400) -> 0.0048928993 | H1407: =LN(Prices!H1401/Prices!H1400) -> -0.0072654182 | I1407: =LN(Prices!I1401/Prices!I1400) -> -0.0029734787 | J1407: =LN(Prices!J1401/Prices!J1400) -> -0.006313589 | K1407: =(Prices!K1401-Prices!K1400)/100 -> -0.00030000031 | L1407: =LN(Prices!L1401/Prices!L1400) -> -0.014935796 | M1407: =LN(Prices!M1401/Prices!M1400) -> -0.011432783 | N1407: =LN(Prices!N1401/Prices!N1400) -> -0.0029772284 | O1407: =LN(Prices!O1401/Prices!O1400) -> -0.019900437
A1408: 44651 | B1408: =LN(Prices!B1402/Prices!B1401) -> -0.015377614 | C1408: =LN(Prices!C1402/Prices!C1401) -> -0.00046682033 | D1408: =LN(Prices!D1402/Prices!D1401) -> -0.015166762 | E1408: =LN(Prices!E1402/Prices!E1401) -> 0.0018631116 | F1408: =LN(Prices!F1402/Prices!F1401) -> -0.01194653 | G1408: =LN(Prices!G1402/Prices!G1401) -> -0.0032059253 | H1408: =LN(Prices!H1402/Prices!H1401) -> -0.012289261 | I1408: =LN(Prices!I1402/Prices!I1401) -> -0.014726157 | J1408: =LN(Prices!J1402/Prices!J1401) -> -0.015776335 | K1408: =(Prices!K1402-Prices!K1401)/100 -> -0.00031999975 | L1408: =LN(Prices!L1402/Prices!L1401) -> -0.014352742 | M1408: =LN(Prices!M1402/Prices!M1401) -> -0.016164887 | N1408: =LN(Prices!N1402/Prices!N1401) -> -0.015198088 | O1408: =LN(Prices!O1402/Prices!O1401) -> -0.010064579
A1409: 44652 | B1409: =LN(Prices!B1403/Prices!B1402) -> 0.0097097517 | C1409: =LN(Prices!C1403/Prices!C1402) -> -0.0017784065 | D1409: =LN(Prices!D1403/Prices!D1402) -> 0.01647478 | E1409: =LN(Prices!E1403/Prices!E1402) -> -0.0065331576 | F1409: =LN(Prices!F1403/Prices!F1402) -> 0.017825121 | G1409: =LN(Prices!G1403/Prices!G1402) -> -0.0055250507 | H1409: =LN(Prices!H1403/Prices!H1402) -> 0.019283217 | I1409: =LN(Prices!I1403/Prices!I1402) -> 0.0045229924 | J1409: =LN(Prices!J1403/Prices!J1402) -> 0.003404421 | K1409: =(Prices!K1403-Prices!K1402)/100 -> 6.9999993e-05 | L1409: =LN(Prices!L1403/Prices!L1402) -> 0.0061031169 | M1409: =LN(Prices!M1403/Prices!M1402) -> 0.0032261047 | N1409: =LN(Prices!N1403/Prices!N1402) -> 0.0047590672 | O1409: =LN(Prices!O1403/Prices!O1402) -> 0.010083726
A1410: 44655 | B1410: =LN(Prices!B1404/Prices!B1403) -> 0.0079260426 | C1410: =LN(Prices!C1404/Prices!C1403) -> 0.00084327923 | D1410: =LN(Prices!D1404/Prices!D1403) -> 0.017492985 | E1410: =LN(Prices!E1404/Prices!E1403) -> -0.00065648845 | F1410: =LN(Prices!F1404/Prices!F1403) -> -0.0091684574 | G1410: =LN(Prices!G1404/Prices!G1403) -> -0.00073162334 | H1410: =LN(Prices!H1404/Prices!H1403) -> -0.0048996955 | I1410: =LN(Prices!I1404/Prices!I1403) -> -0.0015054683 | J1410: =LN(Prices!J1404/Prices!J1403) -> 0.0080583825 | K1410: =(Prices!K1404-Prices!K1403)/100 -> 0.00037999988 | L1410: =LN(Prices!L1404/Prices!L1403) -> -0.0023901652 | M1410: =LN(Prices!M1404/Prices!M1403) -> 0.017573952 | N1410: =LN(Prices!N1404/Prices!N1403) -> -0.0016082258 | O1410: =LN(Prices!O1404/Prices!O1403) -> 0.0020684504
... A2484: 46220 | B2484: =LN(Prices!B2478/Prices!B2477) -> -0.0076721512 | C2484: =LN(Prices!C2478/Prices!C2477) -> 0.00071304147 | D2484: =LN(Prices!D2478/Prices!D2477) -> -0.01412012 | E2484: =LN(Prices!E2478/Prices!E2477) -> 0.0012796141 | F2484: =LN(Prices!F2478/Prices!F2477) -> -0.00042506951 | G2484: =LN(Prices!G2478/Prices!G2477) -> 0.0027746133 | H2484: =LN(Prices!H2478/Prices!H2477) -> -0.00049980562 | I2484: =LN(Prices!I2478/Prices!I2477) -> -0.0055925026 | J2484: =LN(Prices!J2478/Prices!J2477) -> -0.010149876 | K2484: =(Prices!K2478-Prices!K2477)/100 -> 9.9999905e-05 | L2484: =LN(Prices!L2478/Prices!L2477) -> -0.0056447418 | M2484: =LN(Prices!M2478/Prices!M2477) -> -0.01446331 | N2484: =LN(Prices!N2478/Prices!N2477) -> -0.0059378255 | O2484: =LN(Prices!O2478/Prices!O2477) -> -0.0041605364

Sheet Histograms

Sheet Correlation Matrix
C1: B | D1: C | E1: D | F1: E | G1: F | H1: G | I1: H | J1: I | K1: J | L1: K | M1: L | N1: M | O1: N | P1: O | T1: row/column
C2: ACWX | D2: AGG | E2: EEM | F2: IEF | G2: RWR | H2: TIP | I2: VNQ | J2: VONV | K2: ^GSPC | L2: ^IRX | M2: ^MID | N2: ^RLG | O2: ^RLV | P2: ^RUT | S2: ACWX | T2: 1
A3: B | B3: ACWX | C3: =CORREL(_xlfn.VSTACK(INDIRECT("Returns!"&C$1&"7:"&C$1&"879"),INDIRECT("Returns!"&C$1&"1399:"&C$1&"2484")),_xlfn.VSTACK(INDIRECT("Returns!"&$A3&"7:"&$A3&"879"),INDIRECT("Returns!"&$A3&"1399:"&$A3&"2484"))) -> 1 | D3: =CORREL(_xlfn.VSTACK(INDIRECT("Returns!"&D$1&"7:"&D$1&"879"),INDIRECT("Returns!"&D$1&"1399:"&D$1&"2484")),_xlfn.VSTACK(INDIRECT("Returns!"&$A3&"7:"&$A3&"879"),INDIRECT("Returns!"&$A3&"1399:"&$A3&"2484"))) -> 0.22152024 | E3: =CORREL(_xlfn.VSTACK(INDIRECT("Returns!"&E$1&"7:"&E$1&"879"),INDIRECT("Returns!"&E$1&"1399:"&E$1&"2484")),_xlfn.VSTACK(INDIRECT("Returns!"&$A3&"7:"&$A3&"879"),INDIRECT("Returns!"&$A3&"1399:"&$A3&"2484"))) -> 0.90568604 | F3: =CORREL(_xlfn.VSTACK(INDIRECT("Returns!"&F$1&"7:"&F$1&"879"),INDIRECT("Returns!"&F$1&"1399:"&F$1&"2484")),_xlfn.VSTACK(INDIRECT("Returns!"&$A3&"7:"&$A3&"879"),INDIRECT("Returns!"&$A3&"1399:"&$A3&"2484"))) -> 0.078698733 | G3: =CORREL(_xlfn.VSTACK(INDIRECT("Returns!"&G$1&"7:"&G$1&"879"),INDIRECT("Returns!"&G$1&"1399:"&G$1&"2484")),_xlfn.VSTACK(INDIRECT("Returns!"&$A3&"7:"&$A3&"879"),INDIRECT("Returns!"&$A3&"1399:"&$A3&"2484"))) -> 0.51950329 | H3: =CORREL(_xlfn.VSTACK(INDIRECT("Returns!"&H$1&"7:"&H$1&"879"),INDIRECT("Returns!"&H$1&"1399:"&H$1&"2484")),_xlfn.VSTACK(INDIRECT("Returns!"&$A3&"7:"&$A3&"879"),INDIRECT("Returns!"&$A3&"1399:"&$A3&"2484"))) -> 0.18751279 | I3: =CORREL(_xlfn.VSTACK(INDIRECT("Returns!"&I$1&"7:"&I$1&"879"),INDIRECT("Returns!"&I$1&"1399:"&I$1&"2484")),_xlfn.VSTACK(INDIRECT("Returns!"&$A3&"7:"&$A3&"879"),INDIRECT("Returns!"&$A3&"1399:"&$A3&"2484"))) -> 0.53924106 | J3: =CORREL(_xlfn.VSTACK(INDIRECT("Returns!"&J$1&"7:"&J$1&"879"),INDIRECT("Returns!"&J$1&"1399:"&J$1&"2484")),_xlfn.VSTACK(INDIRECT("Returns!"&$A3&"7:"&$A3&"879"),INDIRECT("Returns!"&$A3&"1399:"&$A3&"2484"))) -> 0.79602623 | ... P3: =CORREL(_xlfn.VSTACK(INDIRECT("Returns!"&P$1&"7:"&P$1&"879"),INDIRECT("Returns!"&P$1&"1399:"&P$1&"2484")),_xlfn.VSTACK(INDIRECT("Returns!"&$A3&"7:"&$A3&"879"),INDIRECT("Returns!"&$A3&"1399:"&$A3&"2484"))) -> 0.75662886 | S3: AGG | T3: =T2+1 -> 2
A4: C | B4: AGG | C4: =CORREL(_xlfn.VSTACK(INDIRECT("Returns!"&C$1&"7:"&C$1&"879"),INDIRECT("Returns!"&C$1&"1399:"&C$1&"2484")),_xlfn.VSTACK(INDIRECT("Returns!"&$A4&"7:"&$A4&"879"),INDIRECT("Returns!"&$A4&"1399:"&$A4&"2484"))) -> 0.22152024 | D4: =CORREL(_xlfn.VSTACK(INDIRECT("Returns!"&D$1&"7:"&D$1&"879"),INDIRECT("Returns!"&D$1&"1399:"&D$1&"2484")),_xlfn.VSTACK(INDIRECT("Returns!"&$A4&"7:"&$A4&"879"),INDIRECT("Returns!"&$A4&"1399:"&$A4&"2484"))) -> 1 | E4: =CORREL(_xlfn.VSTACK(INDIRECT("Returns!"&E$1&"7:"&E$1&"879"),INDIRECT("Returns!"&E$1&"1399:"&E$1&"2484")),_xlfn.VSTACK(INDIRECT("Returns!"&$A4&"7:"&$A4&"879"),INDIRECT("Returns!"&$A4&"1399:"&$A4&"2484"))) -> 0.17019222 | F4: =CORREL(_xlfn.VSTACK(INDIRECT("Returns!"&F$1&"7:"&F$1&"879"),INDIRECT("Returns!"&F$1&"1399:"&F$1&"2484")),_xlfn.VSTACK(INDIRECT("Returns!"&$A4&"7:"&$A4&"879"),INDIRECT("Returns!"&$A4&"1399:"&$A4&"2484"))) -> 0.9652793 | G4: =CORREL(_xlfn.VSTACK(INDIRECT("Returns!"&G$1&"7:"&G$1&"879"),INDIRECT("Returns!"&G$1&"1399:"&G$1&"2484")),_xlfn.VSTACK(INDIRECT("Returns!"&$A4&"7:"&$A4&"879"),INDIRECT("Returns!"&$A4&"1399:"&$A4&"2484"))) -> 0.34046875 | H4: =CORREL(_xlfn.VSTACK(INDIRECT("Returns!"&H$1&"7:"&H$1&"879"),INDIRECT("Returns!"&H$1&"1399:"&H$1&"2484")),_xlfn.VSTACK(INDIRECT("Returns!"&$A4&"7:"&$A4&"879"),INDIRECT("Returns!"&$A4&"1399:"&$A4&"2484"))) -> 0.84575256 | I4: =CORREL(_xlfn.VSTACK(INDIRECT("Returns!"&I$1&"7:"&I$1&"879"),INDIRECT("Returns!"&I$1&"1399:"&I$1&"2484")),_xlfn.VSTACK(INDIRECT("Returns!"&$A4&"7:"&$A4&"879"),INDIRECT("Returns!"&$A4&"1399:"&$A4&"2484"))) -> 0.37177556 | J4: =CORREL(_xlfn.VSTACK(INDIRECT("Returns!"&J$1&"7:"&J$1&"879"),INDIRECT("Returns!"&J$1&"1399:"&J$1&"2484")),_xlfn.VSTACK(INDIRECT("Returns!"&$A4&"7:"&$A4&"879"),INDIRECT("Returns!"&$A4&"1399:"&$A4&"2484"))) -> 0.12604141 | ... P4: =CORREL(_xlfn.VSTACK(INDIRECT("Returns!"&P$1&"7:"&P$1&"879"),INDIRECT("Returns!"&P$1&"1399:"&P$1&"2484")),_xlfn.VSTACK(INDIRECT("Returns!"&$A4&"7:"&$A4&"879"),INDIRECT("Returns!"&$A4&"1399:"&$A4&"2484"))) -> 0.15348626 | S4: EEM | T4: =T3+1 -> 3
A5: D | B5: EEM | C5: =CORREL(_xlfn.VSTACK(INDIRECT("Returns!"&C$1&"7:"&C$1&"879"),INDIRECT("Returns!"&C$1&"1399:"&C$1&"2484")),_xlfn.VSTACK(INDIRECT("Returns!"&$A5&"7:"&$A5&"879"),INDIRECT("Returns!"&$A5&"1399:"&$A5&"2484"))) -> 0.90568604 | D5: =CORREL(_xlfn.VSTACK(INDIRECT("Returns!"&D$1&"7:"&D$1&"879"),INDIRECT("Returns!"&D$1&"1399:"&D$1&"2484")),_xlfn.VSTACK(INDIRECT("Returns!"&$A5&"7:"&$A5&"879"),INDIRECT("Returns!"&$A5&"1399:"&$A5&"2484"))) -> 0.17019222 | E5: =CORREL(_xlfn.VSTACK(INDIRECT("Returns!"&E$1&"7:"&E$1&"879"),INDIRECT("Returns!"&E$1&"1399:"&E$1&"2484")),_xlfn.VSTACK(INDIRECT("Returns!"&$A5&"7:"&$A5&"879"),INDIRECT("Returns!"&$A5&"1399:"&$A5&"2484"))) -> 1 | F5: =CORREL(_xlfn.VSTACK(INDIRECT("Returns!"&F$1&"7:"&F$1&"879"),INDIRECT("Returns!"&F$1&"1399:"&F$1&"2484")),_xlfn.VSTACK(INDIRECT("Returns!"&$A5&"7:"&$A5&"879"),INDIRECT("Returns!"&$A5&"1399:"&$A5&"2484"))) -> 0.042947545 | G5: =CORREL(_xlfn.VSTACK(INDIRECT("Returns!"&G$1&"7:"&G$1&"879"),INDIRECT("Returns!"&G$1&"1399:"&G$1&"2484")),_xlfn.VSTACK(INDIRECT("Returns!"&$A5&"7:"&$A5&"879"),INDIRECT("Returns!"&$A5&"1399:"&$A5&"2484"))) -> 0.38653614 | H5: =CORREL(_xlfn.VSTACK(INDIRECT("Returns!"&H$1&"7:"&H$1&"879"),INDIRECT("Returns!"&H$1&"1399:"&H$1&"2484")),_xlfn.VSTACK(INDIRECT("Returns!"&$A5&"7:"&$A5&"879"),INDIRECT("Returns!"&$A5&"1399:"&$A5&"2484"))) -> 0.13474346 | I5: =CORREL(_xlfn.VSTACK(INDIRECT("Returns!"&I$1&"7:"&I$1&"879"),INDIRECT("Returns!"&I$1&"1399:"&I$1&"2484")),_xlfn.VSTACK(INDIRECT("Returns!"&$A5&"7:"&$A5&"879"),INDIRECT("Returns!"&$A5&"1399:"&$A5&"2484"))) -> 0.40523451 | J5: =CORREL(_xlfn.VSTACK(INDIRECT("Returns!"&J$1&"7:"&J$1&"879"),INDIRECT("Returns!"&J$1&"1399:"&J$1&"2484")),_xlfn.VSTACK(INDIRECT("Returns!"&$A5&"7:"&$A5&"879"),INDIRECT("Returns!"&$A5&"1399:"&$A5&"2484"))) -> 0.64705571 | ... P5: =CORREL(_xlfn.VSTACK(INDIRECT("Returns!"&P$1&"7:"&P$1&"879"),INDIRECT("Returns!"&P$1&"1399:"&P$1&"2484")),_xlfn.VSTACK(INDIRECT("Returns!"&$A5&"7:"&$A5&"879"),INDIRECT("Returns!"&$A5&"1399:"&$A5&"2484"))) -> 0.64265609 | S5: IEF | T5: =T4+1 -> 4
A6: E | B6: IEF | C6: =CORREL(_xlfn.VSTACK(INDIRECT("Returns!"&C$1&"7:"&C$1&"879"),INDIRECT("Returns!"&C$1&"1399:"&C$1&"2484")),_xlfn.VSTACK(INDIRECT("Returns!"&$A6&"7:"&$A6&"879"),INDIRECT("Returns!"&$A6&"1399:"&$A6&"2484"))) -> 0.078698733 | D6: =CORREL(_xlfn.VSTACK(INDIRECT("Returns!"&D$1&"7:"&D$1&"879"),INDIRECT("Returns!"&D$1&"1399:"&D$1&"2484")),_xlfn.VSTACK(INDIRECT("Returns!"&$A6&"7:"&$A6&"879"),INDIRECT("Returns!"&$A6&"1399:"&$A6&"2484"))) -> 0.9652793 | E6: =CORREL(_xlfn.VSTACK(INDIRECT("Returns!"&E$1&"7:"&E$1&"879"),INDIRECT("Returns!"&E$1&"1399:"&E$1&"2484")),_xlfn.VSTACK(INDIRECT("Returns!"&$A6&"7:"&$A6&"879"),INDIRECT("Returns!"&$A6&"1399:"&$A6&"2484"))) -> 0.042947545 | F6: =CORREL(_xlfn.VSTACK(INDIRECT("Returns!"&F$1&"7:"&F$1&"879"),INDIRECT("Returns!"&F$1&"1399:"&F$1&"2484")),_xlfn.VSTACK(INDIRECT("Returns!"&$A6&"7:"&$A6&"879"),INDIRECT("Returns!"&$A6&"1399:"&$A6&"2484"))) -> 1 | G6: =CORREL(_xlfn.VSTACK(INDIRECT("Returns!"&G$1&"7:"&G$1&"879"),INDIRECT("Returns!"&G$1&"1399:"&G$1&"2484")),_xlfn.VSTACK(INDIRECT("Returns!"&$A6&"7:"&$A6&"879"),INDIRECT("Returns!"&$A6&"1399:"&$A6&"2484"))) -> 0.25096877 | H6: =CORREL(_xlfn.VSTACK(INDIRECT("Returns!"&H$1&"7:"&H$1&"879"),INDIRECT("Returns!"&H$1&"1399:"&H$1&"2484")),_xlfn.VSTACK(INDIRECT("Returns!"&$A6&"7:"&$A6&"879"),INDIRECT("Returns!"&$A6&"1399:"&$A6&"2484"))) -> 0.84402639 | I6: =CORREL(_xlfn.VSTACK(INDIRECT("Returns!"&I$1&"7:"&I$1&"879"),INDIRECT("Returns!"&I$1&"1399:"&I$1&"2484")),_xlfn.VSTACK(INDIRECT("Returns!"&$A6&"7:"&$A6&"879"),INDIRECT("Returns!"&$A6&"1399:"&$A6&"2484"))) -> 0.27975501 | J6: =CORREL(_xlfn.VSTACK(INDIRECT("Returns!"&J$1&"7:"&J$1&"879"),INDIRECT("Returns!"&J$1&"1399:"&J$1&"2484")),_xlfn.VSTACK(INDIRECT("Returns!"&$A6&"7:"&$A6&"879"),INDIRECT("Returns!"&$A6&"1399:"&$A6&"2484"))) -> -0.02401501 | ... P6: =CORREL(_xlfn.VSTACK(INDIRECT("Returns!"&P$1&"7:"&P$1&"879"),INDIRECT("Returns!"&P$1&"1399:"&P$1&"2484")),_xlfn.VSTACK(INDIRECT("Returns!"&$A6&"7:"&$A6&"879"),INDIRECT("Returns!"&$A6&"1399:"&$A6&"2484"))) -> 0.0087472368 | S6: RWR | T6: =T5+1 -> 5
A7: F | B7: RWR | C7: =CORREL(_xlfn.VSTACK(INDIRECT("Returns!"&C$1&"7:"&C$1&"879"),INDIRECT("Returns!"&C$1&"1399:"&C$1&"2484")),_xlfn.VSTACK(INDIRECT("Returns!"&$A7&"7:"&$A7&"879"),INDIRECT("Returns!"&$A7&"1399:"&$A7&"2484"))) -> 0.51950329 | D7: =CORREL(_xlfn.VSTACK(INDIRECT("Returns!"&D$1&"7:"&D$1&"879"),INDIRECT("Returns!"&D$1&"1399:"&D$1&"2484")),_xlfn.VSTACK(INDIRECT("Returns!"&$A7&"7:"&$A7&"879"),INDIRECT("Returns!"&$A7&"1399:"&$A7&"2484"))) -> 0.34046875 | E7: =CORREL(_xlfn.VSTACK(INDIRECT("Returns!"&E$1&"7:"&E$1&"879"),INDIRECT("Returns!"&E$1&"1399:"&E$1&"2484")),_xlfn.VSTACK(INDIRECT("Returns!"&$A7&"7:"&$A7&"879"),INDIRECT("Returns!"&$A7&"1399:"&$A7&"2484"))) -> 0.38653614 | F7: =CORREL(_xlfn.VSTACK(INDIRECT("Returns!"&F$1&"7:"&F$1&"879"),INDIRECT("Returns!"&F$1&"1399:"&F$1&"2484")),_xlfn.VSTACK(INDIRECT("Returns!"&$A7&"7:"&$A7&"879"),INDIRECT("Returns!"&$A7&"1399:"&$A7&"2484"))) -> 0.25096877 | G7: =CORREL(_xlfn.VSTACK(INDIRECT("Returns!"&G$1&"7:"&G$1&"879"),INDIRECT("Returns!"&G$1&"1399:"&G$1&"2484")),_xlfn.VSTACK(INDIRECT("Returns!"&$A7&"7:"&$A7&"879"),INDIRECT("Returns!"&$A7&"1399:"&$A7&"2484"))) -> 1 | H7: =CORREL(_xlfn.VSTACK(INDIRECT("Returns!"&H$1&"7:"&H$1&"879"),INDIRECT("Returns!"&H$1&"1399:"&H$1&"2484")),_xlfn.VSTACK(INDIRECT("Returns!"&$A7&"7:"&$A7&"879"),INDIRECT("Returns!"&$A7&"1399:"&$A7&"2484"))) -> 0.31057339 | I7: =CORREL(_xlfn.VSTACK(INDIRECT("Returns!"&I$1&"7:"&I$1&"879"),INDIRECT("Returns!"&I$1&"1399:"&I$1&"2484")),_xlfn.VSTACK(INDIRECT("Returns!"&$A7&"7:"&$A7&"879"),INDIRECT("Returns!"&$A7&"1399:"&$A7&"2484"))) -> 0.98572895 | J7: =CORREL(_xlfn.VSTACK(INDIRECT("Returns!"&J$1&"7:"&J$1&"879"),INDIRECT("Returns!"&J$1&"1399:"&J$1&"2484")),_xlfn.VSTACK(INDIRECT("Returns!"&$A7&"7:"&$A7&"879"),INDIRECT("Returns!"&$A7&"1399:"&$A7&"2484"))) -> 0.68461119 | ... P7: =CORREL(_xlfn.VSTACK(INDIRECT("Returns!"&P$1&"7:"&P$1&"879"),INDIRECT("Returns!"&P$1&"1399:"&P$1&"2484")),_xlfn.VSTACK(INDIRECT("Returns!"&$A7&"7:"&$A7&"879"),INDIRECT("Returns!"&$A7&"1399:"&$A7&"2484"))) -> 0.62327184 | S7: TIP | T7: =T6+1 -> 6
A8: G | B8: TIP | C8: =CORREL(_xlfn.VSTACK(INDIRECT("Returns!"&C$1&"7:"&C$1&"879"),INDIRECT("Returns!"&C$1&"1399:"&C$1&"2484")),_xlfn.VSTACK(INDIRECT("Returns!"&$A8&"7:"&$A8&"879"),INDIRECT("Returns!"&$A8&"1399:"&$A8&"2484"))) -> 0.18751279 | D8: =CORREL(_xlfn.VSTACK(INDIRECT("Returns!"&D$1&"7:"&D$1&"879"),INDIRECT("Returns!"&D$1&"1399:"&D$1&"2484")),_xlfn.VSTACK(INDIRECT("Returns!"&$A8&"7:"&$A8&"879"),INDIRECT("Returns!"&$A8&"1399:"&$A8&"2484"))) -> 0.84575256 | E8: =CORREL(_xlfn.VSTACK(INDIRECT("Returns!"&E$1&"7:"&E$1&"879"),INDIRECT("Returns!"&E$1&"1399:"&E$1&"2484")),_xlfn.VSTACK(INDIRECT("Returns!"&$A8&"7:"&$A8&"879"),INDIRECT("Returns!"&$A8&"1399:"&$A8&"2484"))) -> 0.13474346 | F8: =CORREL(_xlfn.VSTACK(INDIRECT("Returns!"&F$1&"7:"&F$1&"879"),INDIRECT("Returns!"&F$1&"1399:"&F$1&"2484")),_xlfn.VSTACK(INDIRECT("Returns!"&$A8&"7:"&$A8&"879"),INDIRECT("Returns!"&$A8&"1399:"&$A8&"2484"))) -> 0.84402639 | G8: =CORREL(_xlfn.VSTACK(INDIRECT("Returns!"&G$1&"7:"&G$1&"879"),INDIRECT("Returns!"&G$1&"1399:"&G$1&"2484")),_xlfn.VSTACK(INDIRECT("Returns!"&$A8&"7:"&$A8&"879"),INDIRECT("Returns!"&$A8&"1399:"&$A8&"2484"))) -> 0.31057339 | H8: =CORREL(_xlfn.VSTACK(INDIRECT("Returns!"&H$1&"7:"&H$1&"879"),INDIRECT("Returns!"&H$1&"1399:"&H$1&"2484")),_xlfn.VSTACK(INDIRECT("Returns!"&$A8&"7:"&$A8&"879"),INDIRECT("Returns!"&$A8&"1399:"&$A8&"2484"))) -> 1 | I8: =CORREL(_xlfn.VSTACK(INDIRECT("Returns!"&I$1&"7:"&I$1&"879"),INDIRECT("Returns!"&I$1&"1399:"&I$1&"2484")),_xlfn.VSTACK(INDIRECT("Returns!"&$A8&"7:"&$A8&"879"),INDIRECT("Returns!"&$A8&"1399:"&$A8&"2484"))) -> 0.33608118 | J8: =CORREL(_xlfn.VSTACK(INDIRECT("Returns!"&J$1&"7:"&J$1&"879"),INDIRECT("Returns!"&J$1&"1399:"&J$1&"2484")),_xlfn.VSTACK(INDIRECT("Returns!"&$A8&"7:"&$A8&"879"),INDIRECT("Returns!"&$A8&"1399:"&$A8&"2484"))) -> 0.12324602 | ... P8: =CORREL(_xlfn.VSTACK(INDIRECT("Returns!"&P$1&"7:"&P$1&"879"),INDIRECT("Returns!"&P$1&"1399:"&P$1&"2484")),_xlfn.VSTACK(INDIRECT("Returns!"&$A8&"7:"&$A8&"879"),INDIRECT("Returns!"&$A8&"1399:"&$A8&"2484"))) -> 0.12512782 | S8: VNQ | T8: =T7+1 -> 7
A9: H | B9: VNQ | C9: =CORREL(_xlfn.VSTACK(INDIRECT("Returns!"&C$1&"7:"&C$1&"879"),INDIRECT("Returns!"&C$1&"1399:"&C$1&"2484")),_xlfn.VSTACK(INDIRECT("Returns!"&$A9&"7:"&$A9&"879"),INDIRECT("Returns!"&$A9&"1399:"&$A9&"2484"))) -> 0.53924106 | D9: =CORREL(_xlfn.VSTACK(INDIRECT("Returns!"&D$1&"7:"&D$1&"879"),INDIRECT("Returns!"&D$1&"1399:"&D$1&"2484")),_xlfn.VSTACK(INDIRECT("Returns!"&$A9&"7:"&$A9&"879"),INDIRECT("Returns!"&$A9&"1399:"&$A9&"2484"))) -> 0.37177556 | E9: =CORREL(_xlfn.VSTACK(INDIRECT("Returns!"&E$1&"7:"&E$1&"879"),INDIRECT("Returns!"&E$1&"1399:"&E$1&"2484")),_xlfn.VSTACK(INDIRECT("Returns!"&$A9&"7:"&$A9&"879"),INDIRECT("Returns!"&$A9&"1399:"&$A9&"2484"))) -> 0.40523451 | F9: =CORREL(_xlfn.VSTACK(INDIRECT("Returns!"&F$1&"7:"&F$1&"879"),INDIRECT("Returns!"&F$1&"1399:"&F$1&"2484")),_xlfn.VSTACK(INDIRECT("Returns!"&$A9&"7:"&$A9&"879"),INDIRECT("Returns!"&$A9&"1399:"&$A9&"2484"))) -> 0.27975501 | G9: =CORREL(_xlfn.VSTACK(INDIRECT("Returns!"&G$1&"7:"&G$1&"879"),INDIRECT("Returns!"&G$1&"1399:"&G$1&"2484")),_xlfn.VSTACK(INDIRECT("Returns!"&$A9&"7:"&$A9&"879"),INDIRECT("Returns!"&$A9&"1399:"&$A9&"2484"))) -> 0.98572895 | H9: =CORREL(_xlfn.VSTACK(INDIRECT("Returns!"&H$1&"7:"&H$1&"879"),INDIRECT("Returns!"&H$1&"1399:"&H$1&"2484")),_xlfn.VSTACK(INDIRECT("Returns!"&$A9&"7:"&$A9&"879"),INDIRECT("Returns!"&$A9&"1399:"&$A9&"2484"))) -> 0.33608118 | I9: =CORREL(_xlfn.VSTACK(INDIRECT("Returns!"&I$1&"7:"&I$1&"879"),INDIRECT("Returns!"&I$1&"1399:"&I$1&"2484")),_xlfn.VSTACK(INDIRECT("Returns!"&$A9&"7:"&$A9&"879"),INDIRECT("Returns!"&$A9&"1399:"&$A9&"2484"))) -> 1 | J9: =CORREL(_xlfn.VSTACK(INDIRECT("Returns!"&J$1&"7:"&J$1&"879"),INDIRECT("Returns!"&J$1&"1399:"&J$1&"2484")),_xlfn.VSTACK(INDIRECT("Returns!"&$A9&"7:"&$A9&"879"),INDIRECT("Returns!"&$A9&"1399:"&$A9&"2484"))) -> 0.69406223 | ... P9: =CORREL(_xlfn.VSTACK(INDIRECT("Returns!"&P$1&"7:"&P$1&"879"),INDIRECT("Returns!"&P$1&"1399:"&P$1&"2484")),_xlfn.VSTACK(INDIRECT("Returns!"&$A9&"7:"&$A9&"879"),INDIRECT("Returns!"&$A9&"1399:"&$A9&"2484"))) -> 0.63683824 | S9: VONV | T9: =T8+1 -> 8
A10: I | B10: VONV | C10: =CORREL(_xlfn.VSTACK(INDIRECT("Returns!"&C$1&"7:"&C$1&"879"),INDIRECT("Returns!"&C$1&"1399:"&C$1&"2484")),_xlfn.VSTACK(INDIRECT("Returns!"&$A10&"7:"&$A10&"879"),INDIRECT("Returns!"&$A10&"1399:"&$A10&"2484"))) -> 0.79602623 | D10: =CORREL(_xlfn.VSTACK(INDIRECT("Returns!"&D$1&"7:"&D$1&"879"),INDIRECT("Returns!"&D$1&"1399:"&D$1&"2484")),_xlfn.VSTACK(INDIRECT("Returns!"&$A10&"7:"&$A10&"879"),INDIRECT("Returns!"&$A10&"1399:"&$A10&"2484"))) -> 0.12604141 | E10: =CORREL(_xlfn.VSTACK(INDIRECT("Returns!"&E$1&"7:"&E$1&"879"),INDIRECT("Returns!"&E$1&"1399:"&E$1&"2484")),_xlfn.VSTACK(INDIRECT("Returns!"&$A10&"7:"&$A10&"879"),INDIRECT("Returns!"&$A10&"1399:"&$A10&"2484"))) -> 0.64705571 | F10: =CORREL(_xlfn.VSTACK(INDIRECT("Returns!"&F$1&"7:"&F$1&"879"),INDIRECT("Returns!"&F$1&"1399:"&F$1&"2484")),_xlfn.VSTACK(INDIRECT("Returns!"&$A10&"7:"&$A10&"879"),INDIRECT("Returns!"&$A10&"1399:"&$A10&"2484"))) -> -0.02401501 | G10: =CORREL(_xlfn.VSTACK(INDIRECT("Returns!"&G$1&"7:"&G$1&"879"),INDIRECT("Returns!"&G$1&"1399:"&G$1&"2484")),_xlfn.VSTACK(INDIRECT("Returns!"&$A10&"7:"&$A10&"879"),INDIRECT("Returns!"&$A10&"1399:"&$A10&"2484"))) -> 0.68461119 | H10: =CORREL(_xlfn.VSTACK(INDIRECT("Returns!"&H$1&"7:"&H$1&"879"),INDIRECT("Returns!"&H$1&"1399:"&H$1&"2484")),_xlfn.VSTACK(INDIRECT("Returns!"&$A10&"7:"&$A10&"879"),INDIRECT("Returns!"&$A10&"1399:"&$A10&"2484"))) -> 0.12324602 | I10: =CORREL(_xlfn.VSTACK(INDIRECT("Returns!"&I$1&"7:"&I$1&"879"),INDIRECT("Returns!"&I$1&"1399:"&I$1&"2484")),_xlfn.VSTACK(INDIRECT("Returns!"&$A10&"7:"&$A10&"879"),INDIRECT("Returns!"&$A10&"1399:"&$A10&"2484"))) -> 0.69406223 | J10: =CORREL(_xlfn.VSTACK(INDIRECT("Returns!"&J$1&"7:"&J$1&"879"),INDIRECT("Returns!"&J$1&"1399:"&J$1&"2484")),_xlfn.VSTACK(INDIRECT("Returns!"&$A10&"7:"&$A10&"879"),INDIRECT("Returns!"&$A10&"1399:"&$A10&"2484"))) -> 1 | ... P10: =CORREL(_xlfn.VSTACK(INDIRECT("Returns!"&P$1&"7:"&P$1&"879"),INDIRECT("Returns!"&P$1&"1399:"&P$1&"2484")),_xlfn.VSTACK(INDIRECT("Returns!"&$A10&"7:"&$A10&"879"),INDIRECT("Returns!"&$A10&"1399:"&$A10&"2484"))) -> 0.88061643 | S10: ^GSPC | T10: =T9+1 -> 9
A11: J | B11: ^GSPC | C11: =CORREL(_xlfn.VSTACK(INDIRECT("Returns!"&C$1&"7:"&C$1&"879"),INDIRECT("Returns!"&C$1&"1399:"&C$1&"2484")),_xlfn.VSTACK(INDIRECT("Returns!"&$A11&"7:"&$A11&"879"),INDIRECT("Returns!"&$A11&"1399:"&$A11&"2484"))) -> 0.81882142 | D11: =CORREL(_xlfn.VSTACK(INDIRECT("Returns!"&D$1&"7:"&D$1&"879"),INDIRECT("Returns!"&D$1&"1399:"&D$1&"2484")),_xlfn.VSTACK(INDIRECT("Returns!"&$A11&"7:"&$A11&"879"),INDIRECT("Returns!"&$A11&"1399:"&$A11&"2484"))) -> 0.13700426 | E11: =CORREL(_xlfn.VSTACK(INDIRECT("Returns!"&E$1&"7:"&E$1&"879"),INDIRECT("Returns!"&E$1&"1399:"&E$1&"2484")),_xlfn.VSTACK(INDIRECT("Returns!"&$A11&"7:"&$A11&"879"),INDIRECT("Returns!"&$A11&"1399:"&$A11&"2484"))) -> 0.70064437 | F11: =CORREL(_xlfn.VSTACK(INDIRECT("Returns!"&F$1&"7:"&F$1&"879"),INDIRECT("Returns!"&F$1&"1399:"&F$1&"2484")),_xlfn.VSTACK(INDIRECT("Returns!"&$A11&"7:"&$A11&"879"),INDIRECT("Returns!"&$A11&"1399:"&$A11&"2484"))) -> -0.016900284 | G11: =CORREL(_xlfn.VSTACK(INDIRECT("Returns!"&G$1&"7:"&G$1&"879"),INDIRECT("Returns!"&G$1&"1399:"&G$1&"2484")),_xlfn.VSTACK(INDIRECT("Returns!"&$A11&"7:"&$A11&"879"),INDIRECT("Returns!"&$A11&"1399:"&$A11&"2484"))) -> 0.59679677 | H11: =CORREL(_xlfn.VSTACK(INDIRECT("Returns!"&H$1&"7:"&H$1&"879"),INDIRECT("Returns!"&H$1&"1399:"&H$1&"2484")),_xlfn.VSTACK(INDIRECT("Returns!"&$A11&"7:"&$A11&"879"),INDIRECT("Returns!"&$A11&"1399:"&$A11&"2484"))) -> 0.12041591 | I11: =CORREL(_xlfn.VSTACK(INDIRECT("Returns!"&I$1&"7:"&I$1&"879"),INDIRECT("Returns!"&I$1&"1399:"&I$1&"2484")),_xlfn.VSTACK(INDIRECT("Returns!"&$A11&"7:"&$A11&"879"),INDIRECT("Returns!"&$A11&"1399:"&$A11&"2484"))) -> 0.60966834 | J11: =CORREL(_xlfn.VSTACK(INDIRECT("Returns!"&J$1&"7:"&J$1&"879"),INDIRECT("Returns!"&J$1&"1399:"&J$1&"2484")),_xlfn.VSTACK(INDIRECT("Returns!"&$A11&"7:"&$A11&"879"),INDIRECT("Returns!"&$A11&"1399:"&$A11&"2484"))) -> 0.91619799 | ... P11: =CORREL(_xlfn.VSTACK(INDIRECT("Returns!"&P$1&"7:"&P$1&"879"),INDIRECT("Returns!"&P$1&"1399:"&P$1&"2484")),_xlfn.VSTACK(INDIRECT("Returns!"&$A11&"7:"&$A11&"879"),INDIRECT("Returns!"&$A11&"1399:"&$A11&"2484"))) -> 0.85555459 | S11: ^IRX | T11: =T10+1 -> 10
A12: K | B12: ^IRX | C12: =CORREL(_xlfn.VSTACK(INDIRECT("Returns!"&C$1&"7:"&C$1&"879"),INDIRECT("Returns!"&C$1&"1399:"&C$1&"2484")),_xlfn.VSTACK(INDIRECT("Returns!"&$A12&"7:"&$A12&"879"),INDIRECT("Returns!"&$A12&"1399:"&$A12&"2484"))) -> 0.0067133244 | D12: =CORREL(_xlfn.VSTACK(INDIRECT("Returns!"&D$1&"7:"&D$1&"879"),INDIRECT("Returns!"&D$1&"1399:"&D$1&"2484")),_xlfn.VSTACK(INDIRECT("Returns!"&$A12&"7:"&$A12&"879"),INDIRECT("Returns!"&$A12&"1399:"&$A12&"2484"))) -> -0.19972578 | E12: =CORREL(_xlfn.VSTACK(INDIRECT("Returns!"&E$1&"7:"&E$1&"879"),INDIRECT("Returns!"&E$1&"1399:"&E$1&"2484")),_xlfn.VSTACK(INDIRECT("Returns!"&$A12&"7:"&$A12&"879"),INDIRECT("Returns!"&$A12&"1399:"&$A12&"2484"))) -> 0.016294376 | F12: =CORREL(_xlfn.VSTACK(INDIRECT("Returns!"&F$1&"7:"&F$1&"879"),INDIRECT("Returns!"&F$1&"1399:"&F$1&"2484")),_xlfn.VSTACK(INDIRECT("Returns!"&$A12&"7:"&$A12&"879"),INDIRECT("Returns!"&$A12&"1399:"&$A12&"2484"))) -> -0.21285992 | G12: =CORREL(_xlfn.VSTACK(INDIRECT("Returns!"&G$1&"7:"&G$1&"879"),INDIRECT("Returns!"&G$1&"1399:"&G$1&"2484")),_xlfn.VSTACK(INDIRECT("Returns!"&$A12&"7:"&$A12&"879"),INDIRECT("Returns!"&$A12&"1399:"&$A12&"2484"))) -> -0.018492949 | H12: =CORREL(_xlfn.VSTACK(INDIRECT("Returns!"&H$1&"7:"&H$1&"879"),INDIRECT("Returns!"&H$1&"1399:"&H$1&"2484")),_xlfn.VSTACK(INDIRECT("Returns!"&$A12&"7:"&$A12&"879"),INDIRECT("Returns!"&$A12&"1399:"&$A12&"2484"))) -> -0.19969563 | I12: =CORREL(_xlfn.VSTACK(INDIRECT("Returns!"&I$1&"7:"&I$1&"879"),INDIRECT("Returns!"&I$1&"1399:"&I$1&"2484")),_xlfn.VSTACK(INDIRECT("Returns!"&$A12&"7:"&$A12&"879"),INDIRECT("Returns!"&$A12&"1399:"&$A12&"2484"))) -> -0.025467888 | J12: =CORREL(_xlfn.VSTACK(INDIRECT("Returns!"&J$1&"7:"&J$1&"879"),INDIRECT("Returns!"&J$1&"1399:"&J$1&"2484")),_xlfn.VSTACK(INDIRECT("Returns!"&$A12&"7:"&$A12&"879"),INDIRECT("Returns!"&$A12&"1399:"&$A12&"2484"))) -> 0.033366296 | ... P12: =CORREL(_xlfn.VSTACK(INDIRECT("Returns!"&P$1&"7:"&P$1&"879"),INDIRECT("Returns!"&P$1&"1399:"&P$1&"2484")),_xlfn.VSTACK(INDIRECT("Returns!"&$A12&"7:"&$A12&"879"),INDIRECT("Returns!"&$A12&"1399:"&$A12&"2484"))) -> 0.022566479 | S12: ^MID | T12: =T11+1 -> 11
A13: L | B13: ^MID | C13: =CORREL(_xlfn.VSTACK(INDIRECT("Returns!"&C$1&"7:"&C$1&"879"),INDIRECT("Returns!"&C$1&"1399:"&C$1&"2484")),_xlfn.VSTACK(INDIRECT("Returns!"&$A13&"7:"&$A13&"879"),INDIRECT("Returns!"&$A13&"1399:"&$A13&"2484"))) -> 0.78274624 | D13: =CORREL(_xlfn.VSTACK(INDIRECT("Returns!"&D$1&"7:"&D$1&"879"),INDIRECT("Returns!"&D$1&"1399:"&D$1&"2484")),_xlfn.VSTACK(INDIRECT("Returns!"&$A13&"7:"&$A13&"879"),INDIRECT("Returns!"&$A13&"1399:"&$A13&"2484"))) -> 0.14851952 | E13: =CORREL(_xlfn.VSTACK(INDIRECT("Returns!"&E$1&"7:"&E$1&"879"),INDIRECT("Returns!"&E$1&"1399:"&E$1&"2484")),_xlfn.VSTACK(INDIRECT("Returns!"&$A13&"7:"&$A13&"879"),INDIRECT("Returns!"&$A13&"1399:"&$A13&"2484"))) -> 0.65623861 | F13: =CORREL(_xlfn.VSTACK(INDIRECT("Returns!"&F$1&"7:"&F$1&"879"),INDIRECT("Returns!"&F$1&"1399:"&F$1&"2484")),_xlfn.VSTACK(INDIRECT("Returns!"&$A13&"7:"&$A13&"879"),INDIRECT("Returns!"&$A13&"1399:"&$A13&"2484"))) -> 0.00021783018 | G13: =CORREL(_xlfn.VSTACK(INDIRECT("Returns!"&G$1&"7:"&G$1&"879"),INDIRECT("Returns!"&G$1&"1399:"&G$1&"2484")),_xlfn.VSTACK(INDIRECT("Returns!"&$A13&"7:"&$A13&"879"),INDIRECT("Returns!"&$A13&"1399:"&$A13&"2484"))) -> 0.66914421 | H13: =CORREL(_xlfn.VSTACK(INDIRECT("Returns!"&H$1&"7:"&H$1&"879"),INDIRECT("Returns!"&H$1&"1399:"&H$1&"2484")),_xlfn.VSTACK(INDIRECT("Returns!"&$A13&"7:"&$A13&"879"),INDIRECT("Returns!"&$A13&"1399:"&$A13&"2484"))) -> 0.12835482 | I13: =CORREL(_xlfn.VSTACK(INDIRECT("Returns!"&I$1&"7:"&I$1&"879"),INDIRECT("Returns!"&I$1&"1399:"&I$1&"2484")),_xlfn.VSTACK(INDIRECT("Returns!"&$A13&"7:"&$A13&"879"),INDIRECT("Returns!"&$A13&"1399:"&$A13&"2484"))) -> 0.67939285 | J13: =CORREL(_xlfn.VSTACK(INDIRECT("Returns!"&J$1&"7:"&J$1&"879"),INDIRECT("Returns!"&J$1&"1399:"&J$1&"2484")),_xlfn.VSTACK(INDIRECT("Returns!"&$A13&"7:"&$A13&"879"),INDIRECT("Returns!"&$A13&"1399:"&$A13&"2484"))) -> 0.92843061 | ... P13: =CORREL(_xlfn.VSTACK(INDIRECT("Returns!"&P$1&"7:"&P$1&"879"),INDIRECT("Returns!"&P$1&"1399:"&P$1&"2484")),_xlfn.VSTACK(INDIRECT("Returns!"&$A13&"7:"&$A13&"879"),INDIRECT("Returns!"&$A13&"1399:"&$A13&"2484"))) -> 0.96403514 | S13: ^RLG | T13: =T12+1 -> 12
A14: M | B14: ^RLG | C14: =CORREL(_xlfn.VSTACK(INDIRECT("Returns!"&C$1&"7:"&C$1&"879"),INDIRECT("Returns!"&C$1&"1399:"&C$1&"2484")),_xlfn.VSTACK(INDIRECT("Returns!"&$A14&"7:"&$A14&"879"),INDIRECT("Returns!"&$A14&"1399:"&$A14&"2484"))) -> 0.76710718 | D14: =CORREL(_xlfn.VSTACK(INDIRECT("Returns!"&D$1&"7:"&D$1&"879"),INDIRECT("Returns!"&D$1&"1399:"&D$1&"2484")),_xlfn.VSTACK(INDIRECT("Returns!"&$A14&"7:"&$A14&"879"),INDIRECT("Returns!"&$A14&"1399:"&$A14&"2484"))) -> 0.14295954 | E14: =CORREL(_xlfn.VSTACK(INDIRECT("Returns!"&E$1&"7:"&E$1&"879"),INDIRECT("Returns!"&E$1&"1399:"&E$1&"2484")),_xlfn.VSTACK(INDIRECT("Returns!"&$A14&"7:"&$A14&"879"),INDIRECT("Returns!"&$A14&"1399:"&$A14&"2484"))) -> 0.67877146 | F14: =CORREL(_xlfn.VSTACK(INDIRECT("Returns!"&F$1&"7:"&F$1&"879"),INDIRECT("Returns!"&F$1&"1399:"&F$1&"2484")),_xlfn.VSTACK(INDIRECT("Returns!"&$A14&"7:"&$A14&"879"),INDIRECT("Returns!"&$A14&"1399:"&$A14&"2484"))) -> -0.00088116781 | G14: =CORREL(_xlfn.VSTACK(INDIRECT("Returns!"&G$1&"7:"&G$1&"879"),INDIRECT("Returns!"&G$1&"1399:"&G$1&"2484")),_xlfn.VSTACK(INDIRECT("Returns!"&$A14&"7:"&$A14&"879"),INDIRECT("Returns!"&$A14&"1399:"&$A14&"2484"))) -> 0.50402062 | H14: =CORREL(_xlfn.VSTACK(INDIRECT("Returns!"&H$1&"7:"&H$1&"879"),INDIRECT("Returns!"&H$1&"1399:"&H$1&"2484")),_xlfn.VSTACK(INDIRECT("Returns!"&$A14&"7:"&$A14&"879"),INDIRECT("Returns!"&$A14&"1399:"&$A14&"2484"))) -> 0.11514863 | I14: =CORREL(_xlfn.VSTACK(INDIRECT("Returns!"&I$1&"7:"&I$1&"879"),INDIRECT("Returns!"&I$1&"1399:"&I$1&"2484")),_xlfn.VSTACK(INDIRECT("Returns!"&$A14&"7:"&$A14&"879"),INDIRECT("Returns!"&$A14&"1399:"&$A14&"2484"))) -> 0.51916725 | J14: =CORREL(_xlfn.VSTACK(INDIRECT("Returns!"&J$1&"7:"&J$1&"879"),INDIRECT("Returns!"&J$1&"1399:"&J$1&"2484")),_xlfn.VSTACK(INDIRECT("Returns!"&$A14&"7:"&$A14&"879"),INDIRECT("Returns!"&$A14&"1399:"&$A14&"2484"))) -> 0.789125 | ... P14: =CORREL(_xlfn.VSTACK(INDIRECT("Returns!"&P$1&"7:"&P$1&"879"),INDIRECT("Returns!"&P$1&"1399:"&P$1&"2484")),_xlfn.VSTACK(INDIRECT("Returns!"&$A14&"7:"&$A14&"879"),INDIRECT("Returns!"&$A14&"1399:"&$A14&"2484"))) -> 0.79137119 | S14: ^RLV | T14: =T13+1 -> 13
A15: N | B15: ^RLV | C15: =CORREL(_xlfn.VSTACK(INDIRECT("Returns!"&C$1&"7:"&C$1&"879"),INDIRECT("Returns!"&C$1&"1399:"&C$1&"2484")),_xlfn.VSTACK(INDIRECT("Returns!"&$A15&"7:"&$A15&"879"),INDIRECT("Returns!"&$A15&"1399:"&$A15&"2484"))) -> 0.79872019 | D15: =CORREL(_xlfn.VSTACK(INDIRECT("Returns!"&D$1&"7:"&D$1&"879"),INDIRECT("Returns!"&D$1&"1399:"&D$1&"2484")),_xlfn.VSTACK(INDIRECT("Returns!"&$A15&"7:"&$A15&"879"),INDIRECT("Returns!"&$A15&"1399:"&$A15&"2484"))) -> 0.12863524 | E15: =CORREL(_xlfn.VSTACK(INDIRECT("Returns!"&E$1&"7:"&E$1&"879"),INDIRECT("Returns!"&E$1&"1399:"&E$1&"2484")),_xlfn.VSTACK(INDIRECT("Returns!"&$A15&"7:"&$A15&"879"),INDIRECT("Returns!"&$A15&"1399:"&$A15&"2484"))) -> 0.65100938 | F15: =CORREL(_xlfn.VSTACK(INDIRECT("Returns!"&F$1&"7:"&F$1&"879"),INDIRECT("Returns!"&F$1&"1399:"&F$1&"2484")),_xlfn.VSTACK(INDIRECT("Returns!"&$A15&"7:"&$A15&"879"),INDIRECT("Returns!"&$A15&"1399:"&$A15&"2484"))) -> -0.021120193 | G15: =CORREL(_xlfn.VSTACK(INDIRECT("Returns!"&G$1&"7:"&G$1&"879"),INDIRECT("Returns!"&G$1&"1399:"&G$1&"2484")),_xlfn.VSTACK(INDIRECT("Returns!"&$A15&"7:"&$A15&"879"),INDIRECT("Returns!"&$A15&"1399:"&$A15&"2484"))) -> 0.68057686 | H15: =CORREL(_xlfn.VSTACK(INDIRECT("Returns!"&H$1&"7:"&H$1&"879"),INDIRECT("Returns!"&H$1&"1399:"&H$1&"2484")),_xlfn.VSTACK(INDIRECT("Returns!"&$A15&"7:"&$A15&"879"),INDIRECT("Returns!"&$A15&"1399:"&$A15&"2484"))) -> 0.12971278 | I15: =CORREL(_xlfn.VSTACK(INDIRECT("Returns!"&I$1&"7:"&I$1&"879"),INDIRECT("Returns!"&I$1&"1399:"&I$1&"2484")),_xlfn.VSTACK(INDIRECT("Returns!"&$A15&"7:"&$A15&"879"),INDIRECT("Returns!"&$A15&"1399:"&$A15&"2484"))) -> 0.69049267 | J15: =CORREL(_xlfn.VSTACK(INDIRECT("Returns!"&J$1&"7:"&J$1&"879"),INDIRECT("Returns!"&J$1&"1399:"&J$1&"2484")),_xlfn.VSTACK(INDIRECT("Returns!"&$A15&"7:"&$A15&"879"),INDIRECT("Returns!"&$A15&"1399:"&$A15&"2484"))) -> 0.99349983 | ... P15: =CORREL(_xlfn.VSTACK(INDIRECT("Returns!"&P$1&"7:"&P$1&"879"),INDIRECT("Returns!"&P$1&"1399:"&P$1&"2484")),_xlfn.VSTACK(INDIRECT("Returns!"&$A15&"7:"&$A15&"879"),INDIRECT("Returns!"&$A15&"1399:"&$A15&"2484"))) -> 0.87889862 | S15: ^RUT | T15: =T14+1 -> 14
A16: O | B16: ^RUT | C16: =CORREL(_xlfn.VSTACK(INDIRECT("Returns!"&C$1&"7:"&C$1&"879"),INDIRECT("Returns!"&C$1&"1399:"&C$1&"2484")),_xlfn.VSTACK(INDIRECT("Returns!"&$A16&"7:"&$A16&"879"),INDIRECT("Returns!"&$A16&"1399:"&$A16&"2484"))) -> 0.75662886 | D16: =CORREL(_xlfn.VSTACK(INDIRECT("Returns!"&D$1&"7:"&D$1&"879"),INDIRECT("Returns!"&D$1&"1399:"&D$1&"2484")),_xlfn.VSTACK(INDIRECT("Returns!"&$A16&"7:"&$A16&"879"),INDIRECT("Returns!"&$A16&"1399:"&$A16&"2484"))) -> 0.15348626 | E16: =CORREL(_xlfn.VSTACK(INDIRECT("Returns!"&E$1&"7:"&E$1&"879"),INDIRECT("Returns!"&E$1&"1399:"&E$1&"2484")),_xlfn.VSTACK(INDIRECT("Returns!"&$A16&"7:"&$A16&"879"),INDIRECT("Returns!"&$A16&"1399:"&$A16&"2484"))) -> 0.64265609 | F16: =CORREL(_xlfn.VSTACK(INDIRECT("Returns!"&F$1&"7:"&F$1&"879"),INDIRECT("Returns!"&F$1&"1399:"&F$1&"2484")),_xlfn.VSTACK(INDIRECT("Returns!"&$A16&"7:"&$A16&"879"),INDIRECT("Returns!"&$A16&"1399:"&$A16&"2484"))) -> 0.0087472368 | G16: =CORREL(_xlfn.VSTACK(INDIRECT("Returns!"&G$1&"7:"&G$1&"879"),INDIRECT("Returns!"&G$1&"1399:"&G$1&"2484")),_xlfn.VSTACK(INDIRECT("Returns!"&$A16&"7:"&$A16&"879"),INDIRECT("Returns!"&$A16&"1399:"&$A16&"2484"))) -> 0.62327184 | H16: =CORREL(_xlfn.VSTACK(INDIRECT("Returns!"&H$1&"7:"&H$1&"879"),INDIRECT("Returns!"&H$1&"1399:"&H$1&"2484")),_xlfn.VSTACK(INDIRECT("Returns!"&$A16&"7:"&$A16&"879"),INDIRECT("Returns!"&$A16&"1399:"&$A16&"2484"))) -> 0.12512782 | I16: =CORREL(_xlfn.VSTACK(INDIRECT("Returns!"&I$1&"7:"&I$1&"879"),INDIRECT("Returns!"&I$1&"1399:"&I$1&"2484")),_xlfn.VSTACK(INDIRECT("Returns!"&$A16&"7:"&$A16&"879"),INDIRECT("Returns!"&$A16&"1399:"&$A16&"2484"))) -> 0.63683824 | J16: =CORREL(_xlfn.VSTACK(INDIRECT("Returns!"&J$1&"7:"&J$1&"879"),INDIRECT("Returns!"&J$1&"1399:"&J$1&"2484")),_xlfn.VSTACK(INDIRECT("Returns!"&$A16&"7:"&$A16&"879"),INDIRECT("Returns!"&$A16&"1399:"&$A16&"2484"))) -> 0.88061643 | ... P16: =CORREL(_xlfn.VSTACK(INDIRECT("Returns!"&P$1&"7:"&P$1&"879"),INDIRECT("Returns!"&P$1&"1399:"&P$1&"2484")),_xlfn.VSTACK(INDIRECT("Returns!"&$A16&"7:"&$A16&"879"),INDIRECT("Returns!"&$A16&"1399:"&$A16&"2484"))) -> 1

Sheet Fund Stats
A1: Fund Available | B1: INVDDC | C1: INVGIC | D1: INVAFC | E1: CMGH2 | F1: CMGF2 | G1: SSCMG2 | H1: ESPRX | I1: INVMGC | J1: GTSFX | K1: CM7BE | L1: VEVRX | M1: GTDFX | N1: INVIGTC | O1: SSCMGX2 | P1: INVS73 | Q1: CMAI4 | R1: INVPZ | S1: DIPSX | T1: INVS86 | U1: AFRFX | V1: SSCM7FE | W1: CM9N2 | X1: INVSVC2
A2: Expense Ratio | B2: 0.0051 | C2: 0.0051 | D2: 0.0054 | E2: 0.0002 | F2: 0.0002 | G2: 0.0001 | H2: 0.0085 | I2: 0.0067 | J2: 0.0076 | K2: 0.00015 | L2: 0.0054 | M2: 0.01 | N2: 0.0082 | O2: 0.00045 | P2: 0.0085 | Q2: 0.0005 | R2: 0.0046 | S2: 0.0011 | T2: 0.0037 | U2: 0.0081 | V2: 0.0002 | W2: 0.0004 | X2: 0.0053
A3: Applicable Index | B3: Russell 1000 Value Index | C3: Russell 1000 Value Index | D3: Russell 1000 Value Index | E3: Russell 1000 Growth Index | F3: Russell 1000 Value Index | G3: S&P500 Index | H3: Russell 2000 TR USD | I3: Russell Midcap Growth Index | J3: Russell 2000 TR USD | K3: S&P MidCap 400 Index | L3: Russell 2000 TR USD | M3: MSCI EM PR USD | N3: MSCI ACWI ex USA Index | O3: MSCI ACWI ex USA IMI Index | P3: FTSE Nareit All Equity REITs Index | Q3: Dow Jones U.S Select REIT Index | R3: Bloomberg US Treasury Bellwethers 3 Month Index | S3: Bloomberg Intermediate Treasury TR USD | T3: Bloomberg U.S. Aggregate Bond Index | U3: USTREAS T-Bill Auction Ave 3 Mon | V3: Bloomberg U.S. Aggregate Bond Index | W3: Bloomberg U.S. TIPS Index | X3: Bloomberg US Treasury Bellwethers 3 Month Index
A4: Yf ticker/ETF proxy | B4: ^RLV | C4: ^RLV | D4: ^RLV | E4: ^RLG | F4: ^RLV | G4: ^GSPC | H4: ^RUT | I4: VONV | J4: ^RUT | K4: ^MID | L4: ^RUT | M4: EEM | N4: ACWX | O4: ACWX | P4: VNQ | Q4: RWR | R4: ^IRX | S4: IEF | T4: AGG | U4: ^IRX | V4: AGG | W4: TIP | X4: ^IRX
A5: Annual Arithmetic Mean | B5: =HLOOKUP('Fund Stats'!B4,Returns!$B$1:$O$5,2,FALSE) -> 0.070326745 | C5: =HLOOKUP('Fund Stats'!C4,Returns!$B$1:$O$5,2,FALSE) -> 0.070326745 | D5: =HLOOKUP('Fund Stats'!D4,Returns!$B$1:$O$5,2,FALSE) -> 0.070326745 | E5: =HLOOKUP('Fund Stats'!E4,Returns!$B$1:$O$5,2,FALSE) -> 0.14662496 | F5: =HLOOKUP('Fund Stats'!F4,Returns!$B$1:$O$5,2,FALSE) -> 0.070326745 | G5: =HLOOKUP('Fund Stats'!G4,Returns!$B$1:$O$5,2,FALSE) -> 0.11240944 | H5: =HLOOKUP('Fund Stats'!H4,Returns!$B$1:$O$5,2,FALSE) -> 0.069254547 | I5: =HLOOKUP('Fund Stats'!I4,Returns!$B$1:$O$5,2,FALSE) -> 0.094978166 | ... X5: =HLOOKUP('Fund Stats'!X4,Returns!$B$1:$O$5,2,FALSE) -> 0.0054742268
A6: minus annual expense ratio | B6: =B5-B2 -> 0.065226745 | C6: =C5-C2 -> 0.065226745 | D6: =D5-D2 -> 0.064926745 | E6: =E5-E2 -> 0.14642496 | F6: =F5-F2 -> 0.070126745 | G6: =G5-G2 -> 0.11230944 | H6: =H5-H2 -> 0.060754547 | I6: =I5-I2 -> 0.088278166 | ... X6: =X5-X2 -> 0.00017422682
A7: index standard deviation | B7: =HLOOKUP(B4,Returns!$B$1:$O$5,3,FALSE) -> 0.13800609 | C7: =HLOOKUP(C4,Returns!$B$1:$O$5,3,FALSE) -> 0.13800609 | D7: =HLOOKUP(D4,Returns!$B$1:$O$5,3,FALSE) -> 0.13800609 | E7: =HLOOKUP(E4,Returns!$B$1:$O$5,3,FALSE) -> 0.18933466 | F7: =HLOOKUP(F4,Returns!$B$1:$O$5,3,FALSE) -> 0.13800609 | G7: =HLOOKUP(G4,Returns!$B$1:$O$5,3,FALSE) -> 0.15415024 | H7: =HLOOKUP(H4,Returns!$B$1:$O$5,3,FALSE) -> 0.19839628 | I7: =HLOOKUP(I4,Returns!$B$1:$O$5,3,FALSE) -> 0.13754132 | ... X7: =HLOOKUP(X4,Returns!$B$1:$O$5,3,FALSE) -> 0.0055030352
A8: 10yTreas9092026 | B8: 0.0483
A9: Sharpe Ratio | B9: =(B6-$B$8)/B7 -> 0.12265216 | C9: =(C6-$B$8)/C7 -> 0.12265216 | D9: =(D6-$B$8)/D7 -> 0.12047835 | E9: =(E6-$B$8)/E7 -> 0.51826199 | F9: =(F6-$B$8)/F7 -> 0.15815784 | G9: =(G6-$B$8)/G7 -> 0.41524063 | H9: =(H6-$B$8)/H7 -> 0.062776113 | I9: =(I6-$B$8)/I7 -> 0.29066295 | ... X9: =(X6-$B$8)/X7 -> -8.7453144 | Z9: covariance matrix
A10: Correlations | Y10: INVDDC | Z10: INVGIC | AA10: INVAFC | AB10: CMGH2 | AC10: CMGF2 | AD10: SSCMG2 | AE10: ESPRX | AF10: INVMGC | AG10: GTSFX | AH10: CM7BE | AI10: VEVRX | AJ10: GTDFX | AK10: INVIGTC | AL10: SSCMGX2 | AM10: INVS73 | AN10: CMAI4 | AO10: INVPZ | AP10: DIPSX | AQ10: INVS86 | AR10: AFRFX | AS10: SSCM7FE | AT10: CM9N2 | AU10: INVSVC2
A11: INVDDC | B11: {=INDEX('Correlation Matrix'!$C$3:$P$16,VLOOKUP(HLOOKUP($A11,$B$1:$X$4,4,FALSE),'Correlation Matrix'!$S$2:$T$15,2,FALSE),VLOOKUP(B$4,'Correlation Matrix'!$S$2:$T$15,2,FALSE))} -> 1 | C11: {=INDEX('Correlation Matrix'!$C$3:$P$16,VLOOKUP(HLOOKUP($A11,$B$1:$X$4,4,FALSE),'Correlation Matrix'!$S$2:$T$15,2,FALSE),VLOOKUP(C$4,'Correlation Matrix'!$S$2:$T$15,2,FALSE))} -> 1 | D11: {=INDEX('Correlation Matrix'!$C$3:$P$16,VLOOKUP(HLOOKUP($A11,$B$1:$X$4,4,FALSE),'Correlation Matrix'!$S$2:$T$15,2,FALSE),VLOOKUP(D$4,'Correlation Matrix'!$S$2:$T$15,2,FALSE))} -> 1 | E11: {=INDEX('Correlation Matrix'!$C$3:$P$16,VLOOKUP(HLOOKUP($A11,$B$1:$X$4,4,FALSE),'Correlation Matrix'!$S$2:$T$15,2,FALSE),VLOOKUP(E$4,'Correlation Matrix'!$S$2:$T$15,2,FALSE))} -> 0.78573918 | F11: {=INDEX('Correlation Matrix'!$C$3:$P$16,VLOOKUP(HLOOKUP($A11,$B$1:$X$4,4,FALSE),'Correlation Matrix'!$S$2:$T$15,2,FALSE),VLOOKUP(F$4,'Correlation Matrix'!$S$2:$T$15,2,FALSE))} -> 1 | G11: {=INDEX('Correlation Matrix'!$C$3:$P$16,VLOOKUP(HLOOKUP($A11,$B$1:$X$4,4,FALSE),'Correlation Matrix'!$S$2:$T$15,2,FALSE),VLOOKUP(G$4,'Correlation Matrix'!$S$2:$T$15,2,FALSE))} -> 0.91302151 | H11: {=INDEX('Correlation Matrix'!$C$3:$P$16,VLOOKUP(HLOOKUP($A11,$B$1:$X$4,4,FALSE),'Correlation Matrix'!$S$2:$T$15,2,FALSE),VLOOKUP(H$4,'Correlation Matrix'!$S$2:$T$15,2,FALSE))} -> 0.87889862 | I11: {=INDEX('Correlation Matrix'!$C$3:$P$16,VLOOKUP(HLOOKUP($A11,$B$1:$X$4,4,FALSE),'Correlation Matrix'!$S$2:$T$15,2,FALSE),VLOOKUP(I$4,'Correlation Matrix'!$S$2:$T$15,2,FALSE))} -> 0.99349983 | ... X11: {=INDEX('Correlation Matrix'!$C$3:$P$16,VLOOKUP(HLOOKUP($A11,$B$1:$X$4,4,FALSE),'Correlation Matrix'!$S$2:$T$15,2,FALSE),VLOOKUP(X$4,'Correlation Matrix'!$S$2:$T$15,2,FALSE))} -> 0.038353137 | Y11: =B11*B$7*HLOOKUP($A11,$B$1:$X$7,7,FALSE) -> 0.01904568 | Z11: =C11*C$7*HLOOKUP($A11,$B$1:$X$7,7,FALSE) -> 0.01904568 | AA11: =D11*D$7*HLOOKUP($A11,$B$1:$X$7,7,FALSE) -> 0.01904568 | AB11: =E11*E$7*HLOOKUP($A11,$B$1:$X$7,7,FALSE) -> 0.020530843 | AC11: =F11*F$7*HLOOKUP($A11,$B$1:$X$7,7,FALSE) -> 0.01904568 | AD11: =G11*G$7*HLOOKUP($A11,$B$1:$X$7,7,FALSE) -> 0.019423319 | AE11: =H11*H$7*HLOOKUP($A11,$B$1:$X$7,7,FALSE) -> 0.024064151 | AF11: =I11*I$7*HLOOKUP($A11,$B$1:$X$7,7,FALSE) -> 0.018858156 | ... AU11: =X11*X$7*HLOOKUP($A11,$B$1:$X$7,7,FALSE) -> 2.912738e-05
A12: INVGIC | B12: {=INDEX('Correlation Matrix'!$C$3:$P$16,VLOOKUP(HLOOKUP($A12,$B$1:$X$4,4,FALSE),'Correlation Matrix'!$S$2:$T$15,2,FALSE),VLOOKUP(B$4,'Correlation Matrix'!$S$2:$T$15,2,FALSE))} -> 1 | C12: {=INDEX('Correlation Matrix'!$C$3:$P$16,VLOOKUP(HLOOKUP($A12,$B$1:$X$4,4,FALSE),'Correlation Matrix'!$S$2:$T$15,2,FALSE),VLOOKUP(C$4,'Correlation Matrix'!$S$2:$T$15,2,FALSE))} -> 1 | D12: {=INDEX('Correlation Matrix'!$C$3:$P$16,VLOOKUP(HLOOKUP($A12,$B$1:$X$4,4,FALSE),'Correlation Matrix'!$S$2:$T$15,2,FALSE),VLOOKUP(D$4,'Correlation Matrix'!$S$2:$T$15,2,FALSE))} -> 1 | E12: {=INDEX('Correlation Matrix'!$C$3:$P$16,VLOOKUP(HLOOKUP($A12,$B$1:$X$4,4,FALSE),'Correlation Matrix'!$S$2:$T$15,2,FALSE),VLOOKUP(E$4,'Correlation Matrix'!$S$2:$T$15,2,FALSE))} -> 0.78573918 | F12: {=INDEX('Correlation Matrix'!$C$3:$P$16,VLOOKUP(HLOOKUP($A12,$B$1:$X$4,4,FALSE),'Correlation Matrix'!$S$2:$T$15,2,FALSE),VLOOKUP(F$4,'Correlation Matrix'!$S$2:$T$15,2,FALSE))} -> 1 | G12: {=INDEX('Correlation Matrix'!$C$3:$P$16,VLOOKUP(HLOOKUP($A12,$B$1:$X$4,4,FALSE),'Correlation Matrix'!$S$2:$T$15,2,FALSE),VLOOKUP(G$4,'Correlation Matrix'!$S$2:$T$15,2,FALSE))} -> 0.91302151 | H12: {=INDEX('Correlation Matrix'!$C$3:$P$16,VLOOKUP(HLOOKUP($A12,$B$1:$X$4,4,FALSE),'Correlation Matrix'!$S$2:$T$15,2,FALSE),VLOOKUP(H$4,'Correlation Matrix'!$S$2:$T$15,2,FALSE))} -> 0.87889862 | I12: {=INDEX('Correlation Matrix'!$C$3:$P$16,VLOOKUP(HLOOKUP($A12,$B$1:$X$4,4,FALSE),'Correlation Matrix'!$S$2:$T$15,2,FALSE),VLOOKUP(I$4,'Correlation Matrix'!$S$2:$T$15,2,FALSE))} -> 0.99349983 | ... X12: {=INDEX('Correlation Matrix'!$C$3:$P$16,VLOOKUP(HLOOKUP($A12,$B$1:$X$4,4,FALSE),'Correlation Matrix'!$S$2:$T$15,2,FALSE),VLOOKUP(X$4,'Correlation Matrix'!$S$2:$T$15,2,FALSE))} -> 0.038353137 | Y12: =B12*B$7*HLOOKUP($A12,$B$1:$X$7,7,FALSE) -> 0.01904568 | Z12: =C12*C$7*HLOOKUP($A12,$B$1:$X$7,7,FALSE) -> 0.01904568 | AA12: =D12*D$7*HLOOKUP($A12,$B$1:$X$7,7,FALSE) -> 0.01904568 | AB12: =E12*E$7*HLOOKUP($A12,$B$1:$X$7,7,FALSE) -> 0.020530843 | AC12: =F12*F$7*HLOOKUP($A12,$B$1:$X$7,7,FALSE) -> 0.01904568 | AD12: =G12*G$7*HLOOKUP($A12,$B$1:$X$7,7,FALSE) -> 0.019423319 | AE12: =H12*H$7*HLOOKUP($A12,$B$1:$X$7,7,FALSE) -> 0.024064151 | AF12: =I12*I$7*HLOOKUP($A12,$B$1:$X$7,7,FALSE) -> 0.018858156 | ... AU12: =X12*X$7*HLOOKUP($A12,$B$1:$X$7,7,FALSE) -> 2.912738e-05
A13: INVAFC | B13: {=INDEX('Correlation Matrix'!$C$3:$P$16,VLOOKUP(HLOOKUP($A13,$B$1:$X$4,4,FALSE),'Correlation Matrix'!$S$2:$T$15,2,FALSE),VLOOKUP(B$4,'Correlation Matrix'!$S$2:$T$15,2,FALSE))} -> 1 | C13: {=INDEX('Correlation Matrix'!$C$3:$P$16,VLOOKUP(HLOOKUP($A13,$B$1:$X$4,4,FALSE),'Correlation Matrix'!$S$2:$T$15,2,FALSE),VLOOKUP(C$4,'Correlation Matrix'!$S$2:$T$15,2,FALSE))} -> 1 | D13: {=INDEX('Correlation Matrix'!$C$3:$P$16,VLOOKUP(HLOOKUP($A13,$B$1:$X$4,4,FALSE),'Correlation Matrix'!$S$2:$T$15,2,FALSE),VLOOKUP(D$4,'Correlation Matrix'!$S$2:$T$15,2,FALSE))} -> 1 | E13: {=INDEX('Correlation Matrix'!$C$3:$P$16,VLOOKUP(HLOOKUP($A13,$B$1:$X$4,4,FALSE),'Correlation Matrix'!$S$2:$T$15,2,FALSE),VLOOKUP(E$4,'Correlation Matrix'!$S$2:$T$15,2,FALSE))} -> 0.78573918 | F13: {=INDEX('Correlation Matrix'!$C$3:$P$16,VLOOKUP(HLOOKUP($A13,$B$1:$X$4,4,FALSE),'Correlation Matrix'!$S$2:$T$15,2,FALSE),VLOOKUP(F$4,'Correlation Matrix'!$S$2:$T$15,2,FALSE))} -> 1 | G13: {=INDEX('Correlation Matrix'!$C$3:$P$16,VLOOKUP(HLOOKUP($A13,$B$1:$X$4,4,FALSE),'Correlation Matrix'!$S$2:$T$15,2,FALSE),VLOOKUP(G$4,'Correlation Matrix'!$S$2:$T$15,2,FALSE))} -> 0.91302151 | H13: {=INDEX('Correlation Matrix'!$C$3:$P$16,VLOOKUP(HLOOKUP($A13,$B$1:$X$4,4,FALSE),'Correlation Matrix'!$S$2:$T$15,2,FALSE),VLOOKUP(H$4,'Correlation Matrix'!$S$2:$T$15,2,FALSE))} -> 0.87889862 | I13: {=INDEX('Correlation Matrix'!$C$3:$P$16,VLOOKUP(HLOOKUP($A13,$B$1:$X$4,4,FALSE),'Correlation Matrix'!$S$2:$T$15,2,FALSE),VLOOKUP(I$4,'Correlation Matrix'!$S$2:$T$15,2,FALSE))} -> 0.99349983 | ... X13: {=INDEX('Correlation Matrix'!$C$3:$P$16,VLOOKUP(HLOOKUP($A13,$B$1:$X$4,4,FALSE),'Correlation Matrix'!$S$2:$T$15,2,FALSE),VLOOKUP(X$4,'Correlation Matrix'!$S$2:$T$15,2,FALSE))} -> 0.038353137 | Y13: =B13*B$7*HLOOKUP($A13,$B$1:$X$7,7,FALSE) -> 0.01904568 | Z13: =C13*C$7*HLOOKUP($A13,$B$1:$X$7,7,FALSE) -> 0.01904568 | AA13: =D13*D$7*HLOOKUP($A13,$B$1:$X$7,7,FALSE) -> 0.01904568 | AB13: =E13*E$7*HLOOKUP($A13,$B$1:$X$7,7,FALSE) -> 0.020530843 | AC13: =F13*F$7*HLOOKUP($A13,$B$1:$X$7,7,FALSE) -> 0.01904568 | AD13: =G13*G$7*HLOOKUP($A13,$B$1:$X$7,7,FALSE) -> 0.019423319 | AE13: =H13*H$7*HLOOKUP($A13,$B$1:$X$7,7,FALSE) -> 0.024064151 | AF13: =I13*I$7*HLOOKUP($A13,$B$1:$X$7,7,FALSE) -> 0.018858156 | ... AU13: =X13*X$7*HLOOKUP($A13,$B$1:$X$7,7,FALSE) -> 2.912738e-05
A14: CMGH2 | B14: {=INDEX('Correlation Matrix'!$C$3:$P$16,VLOOKUP(HLOOKUP($A14,$B$1:$X$4,4,FALSE),'Correlation Matrix'!$S$2:$T$15,2,FALSE),VLOOKUP(B$4,'Correlation Matrix'!$S$2:$T$15,2,FALSE))} -> 0.78573918 | C14: {=INDEX('Correlation Matrix'!$C$3:$P$16,VLOOKUP(HLOOKUP($A14,$B$1:$X$4,4,FALSE),'Correlation Matrix'!$S$2:$T$15,2,FALSE),VLOOKUP(C$4,'Correlation Matrix'!$S$2:$T$15,2,FALSE))} -> 0.78573918 | D14: {=INDEX('Correlation Matrix'!$C$3:$P$16,VLOOKUP(HLOOKUP($A14,$B$1:$X$4,4,FALSE),'Correlation Matrix'!$S$2:$T$15,2,FALSE),VLOOKUP(D$4,'Correlation Matrix'!$S$2:$T$15,2,FALSE))} -> 0.78573918 | E14: {=INDEX('Correlation Matrix'!$C$3:$P$16,VLOOKUP(HLOOKUP($A14,$B$1:$X$4,4,FALSE),'Correlation Matrix'!$S$2:$T$15,2,FALSE),VLOOKUP(E$4,'Correlation Matrix'!$S$2:$T$15,2,FALSE))} -> 1 | F14: {=INDEX('Correlation Matrix'!$C$3:$P$16,VLOOKUP(HLOOKUP($A14,$B$1:$X$4,4,FALSE),'Correlation Matrix'!$S$2:$T$15,2,FALSE),VLOOKUP(F$4,'Correlation Matrix'!$S$2:$T$15,2,FALSE))} -> 0.78573918 | G14: {=INDEX('Correlation Matrix'!$C$3:$P$16,VLOOKUP(HLOOKUP($A14,$B$1:$X$4,4,FALSE),'Correlation Matrix'!$S$2:$T$15,2,FALSE),VLOOKUP(G$4,'Correlation Matrix'!$S$2:$T$15,2,FALSE))} -> 0.96654702 | H14: {=INDEX('Correlation Matrix'!$C$3:$P$16,VLOOKUP(HLOOKUP($A14,$B$1:$X$4,4,FALSE),'Correlation Matrix'!$S$2:$T$15,2,FALSE),VLOOKUP(H$4,'Correlation Matrix'!$S$2:$T$15,2,FALSE))} -> 0.79137119 | I14: {=INDEX('Correlation Matrix'!$C$3:$P$16,VLOOKUP(HLOOKUP($A14,$B$1:$X$4,4,FALSE),'Correlation Matrix'!$S$2:$T$15,2,FALSE),VLOOKUP(I$4,'Correlation Matrix'!$S$2:$T$15,2,FALSE))} -> 0.789125 | ... X14: {=INDEX('Correlation Matrix'!$C$3:$P$16,VLOOKUP(HLOOKUP($A14,$B$1:$X$4,4,FALSE),'Correlation Matrix'!$S$2:$T$15,2,FALSE),VLOOKUP(X$4,'Correlation Matrix'!$S$2:$T$15,2,FALSE))} -> 0.0016452489 | Y14: =B14*B$7*HLOOKUP($A14,$B$1:$X$7,7,FALSE) -> 0.020530843 | Z14: =C14*C$7*HLOOKUP($A14,$B$1:$X$7,7,FALSE) -> 0.020530843 | AA14: =D14*D$7*HLOOKUP($A14,$B$1:$X$7,7,FALSE) -> 0.020530843 | AB14: =E14*E$7*HLOOKUP($A14,$B$1:$X$7,7,FALSE) -> 0.035847614 | AC14: =F14*F$7*HLOOKUP($A14,$B$1:$X$7,7,FALSE) -> 0.020530843 | AD14: =G14*G$7*HLOOKUP($A14,$B$1:$X$7,7,FALSE) -> 0.028209625 | AE14: =H14*H$7*HLOOKUP($A14,$B$1:$X$7,7,FALSE) -> 0.029726508 | AF14: =I14*I$7*HLOOKUP($A14,$B$1:$X$7,7,FALSE) -> 0.020549872 | ... AU14: =X14*X$7*HLOOKUP($A14,$B$1:$X$7,7,FALSE) -> 1.71421e-06
A15: CMGF2 | B15: {=INDEX('Correlation Matrix'!$C$3:$P$16,VLOOKUP(HLOOKUP($A15,$B$1:$X$4,4,FALSE),'Correlation Matrix'!$S$2:$T$15,2,FALSE),VLOOKUP(B$4,'Correlation Matrix'!$S$2:$T$15,2,FALSE))} -> 1 | C15: {=INDEX('Correlation Matrix'!$C$3:$P$16,VLOOKUP(HLOOKUP($A15,$B$1:$X$4,4,FALSE),'Correlation Matrix'!$S$2:$T$15,2,FALSE),VLOOKUP(C$4,'Correlation Matrix'!$S$2:$T$15,2,FALSE))} -> 1 | D15: {=INDEX('Correlation Matrix'!$C$3:$P$16,VLOOKUP(HLOOKUP($A15,$B$1:$X$4,4,FALSE),'Correlation Matrix'!$S$2:$T$15,2,FALSE),VLOOKUP(D$4,'Correlation Matrix'!$S$2:$T$15,2,FALSE))} -> 1 | E15: {=INDEX('Correlation Matrix'!$C$3:$P$16,VLOOKUP(HLOOKUP($A15,$B$1:$X$4,4,FALSE),'Correlation Matrix'!$S$2:$T$15,2,FALSE),VLOOKUP(E$4,'Correlation Matrix'!$S$2:$T$15,2,FALSE))} -> 0.78573918 | F15: {=INDEX('Correlation Matrix'!$C$3:$P$16,VLOOKUP(HLOOKUP($A15,$B$1:$X$4,4,FALSE),'Correlation Matrix'!$S$2:$T$15,2,FALSE),VLOOKUP(F$4,'Correlation Matrix'!$S$2:$T$15,2,FALSE))} -> 1 | G15: {=INDEX('Correlation Matrix'!$C$3:$P$16,VLOOKUP(HLOOKUP($A15,$B$1:$X$4,4,FALSE),'Correlation Matrix'!$S$2:$T$15,2,FALSE),VLOOKUP(G$4,'Correlation Matrix'!$S$2:$T$15,2,FALSE))} -> 0.91302151 | H15: {=INDEX('Correlation Matrix'!$C$3:$P$16,VLOOKUP(HLOOKUP($A15,$B$1:$X$4,4,FALSE),'Correlation Matrix'!$S$2:$T$15,2,FALSE),VLOOKUP(H$4,'Correlation Matrix'!$S$2:$T$15,2,FALSE))} -> 0.87889862 | I15: {=INDEX('Correlation Matrix'!$C$3:$P$16,VLOOKUP(HLOOKUP($A15,$B$1:$X$4,4,FALSE),'Correlation Matrix'!$S$2:$T$15,2,FALSE),VLOOKUP(I$4,'Correlation Matrix'!$S$2:$T$15,2,FALSE))} -> 0.99349983 | ... X15: {=INDEX('Correlation Matrix'!$C$3:$P$16,VLOOKUP(HLOOKUP($A15,$B$1:$X$4,4,FALSE),'Correlation Matrix'!$S$2:$T$15,2,FALSE),VLOOKUP(X$4,'Correlation Matrix'!$S$2:$T$15,2,FALSE))} -> 0.038353137 | Y15: =B15*B$7*HLOOKUP($A15,$B$1:$X$7,7,FALSE) -> 0.01904568 | Z15: =C15*C$7*HLOOKUP($A15,$B$1:$X$7,7,FALSE) -> 0.01904568 | AA15: =D15*D$7*HLOOKUP($A15,$B$1:$X$7,7,FALSE) -> 0.01904568 | AB15: =E15*E$7*HLOOKUP($A15,$B$1:$X$7,7,FALSE) -> 0.020530843 | AC15: =F15*F$7*HLOOKUP($A15,$B$1:$X$7,7,FALSE) -> 0.01904568 | AD15: =G15*G$7*HLOOKUP($A15,$B$1:$X$7,7,FALSE) -> 0.019423319 | AE15: =H15*H$7*HLOOKUP($A15,$B$1:$X$7,7,FALSE) -> 0.024064151 | AF15: =I15*I$7*HLOOKUP($A15,$B$1:$X$7,7,FALSE) -> 0.018858156 | ... AU15: =X15*X$7*HLOOKUP($A15,$B$1:$X$7,7,FALSE) -> 2.912738e-05
A16: SSCMG2 | B16: {=INDEX('Correlation Matrix'!$C$3:$P$16,VLOOKUP(HLOOKUP($A16,$B$1:$X$4,4,FALSE),'Correlation Matrix'!$S$2:$T$15,2,FALSE),VLOOKUP(B$4,'Correlation Matrix'!$S$2:$T$15,2,FALSE))} -> 0.91302151 | C16: {=INDEX('Correlation Matrix'!$C$3:$P$16,VLOOKUP(HLOOKUP($A16,$B$1:$X$4,4,FALSE),'Correlation Matrix'!$S$2:$T$15,2,FALSE),VLOOKUP(C$4,'Correlation Matrix'!$S$2:$T$15,2,FALSE))} -> 0.91302151 | D16: {=INDEX('Correlation Matrix'!$C$3:$P$16,VLOOKUP(HLOOKUP($A16,$B$1:$X$4,4,FALSE),'Correlation Matrix'!$S$2:$T$15,2,FALSE),VLOOKUP(D$4,'Correlation Matrix'!$S$2:$T$15,2,FALSE))} -> 0.91302151 | E16: {=INDEX('Correlation Matrix'!$C$3:$P$16,VLOOKUP(HLOOKUP($A16,$B$1:$X$4,4,FALSE),'Correlation Matrix'!$S$2:$T$15,2,FALSE),VLOOKUP(E$4,'Correlation Matrix'!$S$2:$T$15,2,FALSE))} -> 0.96654702 | F16: {=INDEX('Correlation Matrix'!$C$3:$P$16,VLOOKUP(HLOOKUP($A16,$B$1:$X$4,4,FALSE),'Correlation Matrix'!$S$2:$T$15,2,FALSE),VLOOKUP(F$4,'Correlation Matrix'!$S$2:$T$15,2,FALSE))} -> 0.91302151 | G16: {=INDEX('Correlation Matrix'!$C$3:$P$16,VLOOKUP(HLOOKUP($A16,$B$1:$X$4,4,FALSE),'Correlation Matrix'!$S$2:$T$15,2,FALSE),VLOOKUP(G$4,'Correlation Matrix'!$S$2:$T$15,2,FALSE))} -> 1 | H16: {=INDEX('Correlation Matrix'!$C$3:$P$16,VLOOKUP(HLOOKUP($A16,$B$1:$X$4,4,FALSE),'Correlation Matrix'!$S$2:$T$15,2,FALSE),VLOOKUP(H$4,'Correlation Matrix'!$S$2:$T$15,2,FALSE))} -> 0.85555459 | I16: {=INDEX('Correlation Matrix'!$C$3:$P$16,VLOOKUP(HLOOKUP($A16,$B$1:$X$4,4,FALSE),'Correlation Matrix'!$S$2:$T$15,2,FALSE),VLOOKUP(I$4,'Correlation Matrix'!$S$2:$T$15,2,FALSE))} -> 0.91619799 | ... X16: {=INDEX('Correlation Matrix'!$C$3:$P$16,VLOOKUP(HLOOKUP($A16,$B$1:$X$4,4,FALSE),'Correlation Matrix'!$S$2:$T$15,2,FALSE),VLOOKUP(X$4,'Correlation Matrix'!$S$2:$T$15,2,FALSE))} -> 0.016108619 | Y16: =B16*B$7*HLOOKUP($A16,$B$1:$X$7,7,FALSE) -> 0.019423319 | Z16: =C16*C$7*HLOOKUP($A16,$B$1:$X$7,7,FALSE) -> 0.019423319 | AA16: =D16*D$7*HLOOKUP($A16,$B$1:$X$7,7,FALSE) -> 0.019423319 | AB16: =E16*E$7*HLOOKUP($A16,$B$1:$X$7,7,FALSE) -> 0.028209625 | AC16: =F16*F$7*HLOOKUP($A16,$B$1:$X$7,7,FALSE) -> 0.019423319 | AD16: =G16*G$7*HLOOKUP($A16,$B$1:$X$7,7,FALSE) -> 0.023762295 | AE16: =H16*H$7*HLOOKUP($A16,$B$1:$X$7,7,FALSE) -> 0.026165284 | AF16: =I16*I$7*HLOOKUP($A16,$B$1:$X$7,7,FALSE) -> 0.019425255 | ... AU16: =X16*X$7*HLOOKUP($A16,$B$1:$X$7,7,FALSE) -> 1.3664848e-05
A17: ESPRX | B17: {=INDEX('Correlation Matrix'!$C$3:$P$16,VLOOKUP(HLOOKUP($A17,$B$1:$X$4,4,FALSE),'Correlation Matrix'!$S$2:$T$15,2,FALSE),VLOOKUP(B$4,'Correlation Matrix'!$S$2:$T$15,2,FALSE))} -> 0.87889862 | C17: {=INDEX('Correlation Matrix'!$C$3:$P$16,VLOOKUP(HLOOKUP($A17,$B$1:$X$4,4,FALSE),'Correlation Matrix'!$S$2:$T$15,2,FALSE),VLOOKUP(C$4,'Correlation Matrix'!$S$2:$T$15,2,FALSE))} -> 0.87889862 | D17: {=INDEX('Correlation Matrix'!$C$3:$P$16,VLOOKUP(HLOOKUP($A17,$B$1:$X$4,4,FALSE),'Correlation Matrix'!$S$2:$T$15,2,FALSE),VLOOKUP(D$4,'Correlation Matrix'!$S$2:$T$15,2,FALSE))} -> 0.87889862 | E17: {=INDEX('Correlation Matrix'!$C$3:$P$16,VLOOKUP(HLOOKUP($A17,$B$1:$X$4,4,FALSE),'Correlation Matrix'!$S$2:$T$15,2,FALSE),VLOOKUP(E$4,'Correlation Matrix'!$S$2:$T$15,2,FALSE))} -> 0.79137119 | F17: {=INDEX('Correlation Matrix'!$C$3:$P$16,VLOOKUP(HLOOKUP($A17,$B$1:$X$4,4,FALSE),'Correlation Matrix'!$S$2:$T$15,2,FALSE),VLOOKUP(F$4,'Correlation Matrix'!$S$2:$T$15,2,FALSE))} -> 0.87889862 | G17: {=INDEX('Correlation Matrix'!$C$3:$P$16,VLOOKUP(HLOOKUP($A17,$B$1:$X$4,4,FALSE),'Correlation Matrix'!$S$2:$T$15,2,FALSE),VLOOKUP(G$4,'Correlation Matrix'!$S$2:$T$15,2,FALSE))} -> 0.85555459 | H17: {=INDEX('Correlation Matrix'!$C$3:$P$16,VLOOKUP(HLOOKUP($A17,$B$1:$X$4,4,FALSE),'Correlation Matrix'!$S$2:$T$15,2,FALSE),VLOOKUP(H$4,'Correlation Matrix'!$S$2:$T$15,2,FALSE))} -> 1 | I17: {=INDEX('Correlation Matrix'!$C$3:$P$16,VLOOKUP(HLOOKUP($A17,$B$1:$X$4,4,FALSE),'Correlation Matrix'!$S$2:$T$15,2,FALSE),VLOOKUP(I$4,'Correlation Matrix'!$S$2:$T$15,2,FALSE))} -> 0.88061643 | ... X17: {=INDEX('Correlation Matrix'!$C$3:$P$16,VLOOKUP(HLOOKUP($A17,$B$1:$X$4,4,FALSE),'Correlation Matrix'!$S$2:$T$15,2,FALSE),VLOOKUP(X$4,'Correlation Matrix'!$S$2:$T$15,2,FALSE))} -> 0.022566479 | Y17: =B17*B$7*HLOOKUP($A17,$B$1:$X$7,7,FALSE) -> 0.024064151 | Z17: =C17*C$7*HLOOKUP($A17,$B$1:$X$7,7,FALSE) -> 0.024064151 | AA17: =D17*D$7*HLOOKUP($A17,$B$1:$X$7,7,FALSE) -> 0.024064151 | AB17: =E17*E$7*HLOOKUP($A17,$B$1:$X$7,7,FALSE) -> 0.029726508 | AC17: =F17*F$7*HLOOKUP($A17,$B$1:$X$7,7,FALSE) -> 0.024064151 | AD17: =G17*G$7*HLOOKUP($A17,$B$1:$X$7,7,FALSE) -> 0.026165284 | AE17: =H17*H$7*HLOOKUP($A17,$B$1:$X$7,7,FALSE) -> 0.039361084 | AF17: =I17*I$7*HLOOKUP($A17,$B$1:$X$7,7,FALSE) -> 0.024029985 | ... AU17: =X17*X$7*HLOOKUP($A17,$B$1:$X$7,7,FALSE) -> 2.4637669e-05
A18: INVMGC | B18: {=INDEX('Correlation Matrix'!$C$3:$P$16,VLOOKUP(HLOOKUP($A18,$B$1:$X$4,4,FALSE),'Correlation Matrix'!$S$2:$T$15,2,FALSE),VLOOKUP(B$4,'Correlation Matrix'!$S$2:$T$15,2,FALSE))} -> 0.99349983 | C18: {=INDEX('Correlation Matrix'!$C$3:$P$16,VLOOKUP(HLOOKUP($A18,$B$1:$X$4,4,FALSE),'Correlation Matrix'!$S$2:$T$15,2,FALSE),VLOOKUP(C$4,'Correlation Matrix'!$S$2:$T$15,2,FALSE))} -> 0.99349983 | D18: {=INDEX('Correlation Matrix'!$C$3:$P$16,VLOOKUP(HLOOKUP($A18,$B$1:$X$4,4,FALSE),'Correlation Matrix'!$S$2:$T$15,2,FALSE),VLOOKUP(D$4,'Correlation Matrix'!$S$2:$T$15,2,FALSE))} -> 0.99349983 | E18: {=INDEX('Correlation Matrix'!$C$3:$P$16,VLOOKUP(HLOOKUP($A18,$B$1:$X$4,4,FALSE),'Correlation Matrix'!$S$2:$T$15,2,FALSE),VLOOKUP(E$4,'Correlation Matrix'!$S$2:$T$15,2,FALSE))} -> 0.789125 | F18: {=INDEX('Correlation Matrix'!$C$3:$P$16,VLOOKUP(HLOOKUP($A18,$B$1:$X$4,4,FALSE),'Correlation Matrix'!$S$2:$T$15,2,FALSE),VLOOKUP(F$4,'Correlation Matrix'!$S$2:$T$15,2,FALSE))} -> 0.99349983 | G18: {=INDEX('Correlation Matrix'!$C$3:$P$16,VLOOKUP(HLOOKUP($A18,$B$1:$X$4,4,FALSE),'Correlation Matrix'!$S$2:$T$15,2,FALSE),VLOOKUP(G$4,'Correlation Matrix'!$S$2:$T$15,2,FALSE))} -> 0.91619799 | H18: {=INDEX('Correlation Matrix'!$C$3:$P$16,VLOOKUP(HLOOKUP($A18,$B$1:$X$4,4,FALSE),'Correlation Matrix'!$S$2:$T$15,2,FALSE),VLOOKUP(H$4,'Correlation Matrix'!$S$2:$T$15,2,FALSE))} -> 0.88061643 | I18: {=INDEX('Correlation Matrix'!$C$3:$P$16,VLOOKUP(HLOOKUP($A18,$B$1:$X$4,4,FALSE),'Correlation Matrix'!$S$2:$T$15,2,FALSE),VLOOKUP(I$4,'Correlation Matrix'!$S$2:$T$15,2,FALSE))} -> 1 | ... X18: {=INDEX('Correlation Matrix'!$C$3:$P$16,VLOOKUP(HLOOKUP($A18,$B$1:$X$4,4,FALSE),'Correlation Matrix'!$S$2:$T$15,2,FALSE),VLOOKUP(X$4,'Correlation Matrix'!$S$2:$T$15,2,FALSE))} -> 0.033366296 | Y18: =B18*B$7*HLOOKUP($A18,$B$1:$X$7,7,FALSE) -> 0.018858156 | Z18: =C18*C$7*HLOOKUP($A18,$B$1:$X$7,7,FALSE) -> 0.018858156 | AA18: =D18*D$7*HLOOKUP($A18,$B$1:$X$7,7,FALSE) -> 0.018858156 | AB18: =E18*E$7*HLOOKUP($A18,$B$1:$X$7,7,FALSE) -> 0.020549872 | AC18: =F18*F$7*HLOOKUP($A18,$B$1:$X$7,7,FALSE) -> 0.018858156 | AD18: =G18*G$7*HLOOKUP($A18,$B$1:$X$7,7,FALSE) -> 0.019425255 | AE18: =H18*H$7*HLOOKUP($A18,$B$1:$X$7,7,FALSE) -> 0.024029985 | AF18: =I18*I$7*HLOOKUP($A18,$B$1:$X$7,7,FALSE) -> 0.018917615 | ... AU18: =X18*X$7*HLOOKUP($A18,$B$1:$X$7,7,FALSE) -> 2.5254774e-05
A19: GTSFX | B19: {=INDEX('Correlation Matrix'!$C$3:$P$16,VLOOKUP(HLOOKUP($A19,$B$1:$X$4,4,FALSE),'Correlation Matrix'!$S$2:$T$15,2,FALSE),VLOOKUP(B$4,'Correlation Matrix'!$S$2:$T$15,2,FALSE))} -> 0.87889862 | C19: {=INDEX('Correlation Matrix'!$C$3:$P$16,VLOOKUP(HLOOKUP($A19,$B$1:$X$4,4,FALSE),'Correlation Matrix'!$S$2:$T$15,2,FALSE),VLOOKUP(C$4,'Correlation Matrix'!$S$2:$T$15,2,FALSE))} -> 0.87889862 | D19: {=INDEX('Correlation Matrix'!$C$3:$P$16,VLOOKUP(HLOOKUP($A19,$B$1:$X$4,4,FALSE),'Correlation Matrix'!$S$2:$T$15,2,FALSE),VLOOKUP(D$4,'Correlation Matrix'!$S$2:$T$15,2,FALSE))} -> 0.87889862 | E19: {=INDEX('Correlation Matrix'!$C$3:$P$16,VLOOKUP(HLOOKUP($A19,$B$1:$X$4,4,FALSE),'Correlation Matrix'!$S$2:$T$15,2,FALSE),VLOOKUP(E$4,'Correlation Matrix'!$S$2:$T$15,2,FALSE))} -> 0.79137119 | F19: {=INDEX('Correlation Matrix'!$C$3:$P$16,VLOOKUP(HLOOKUP($A19,$B$1:$X$4,4,FALSE),'Correlation Matrix'!$S$2:$T$15,2,FALSE),VLOOKUP(F$4,'Correlation Matrix'!$S$2:$T$15,2,FALSE))} -> 0.87889862 | G19: {=INDEX('Correlation Matrix'!$C$3:$P$16,VLOOKUP(HLOOKUP($A19,$B$1:$X$4,4,FALSE),'Correlation Matrix'!$S$2:$T$15,2,FALSE),VLOOKUP(G$4,'Correlation Matrix'!$S$2:$T$15,2,FALSE))} -> 0.85555459 | H19: {=INDEX('Correlation Matrix'!$C$3:$P$16,VLOOKUP(HLOOKUP($A19,$B$1:$X$4,4,FALSE),'Correlation Matrix'!$S$2:$T$15,2,FALSE),VLOOKUP(H$4,'Correlation Matrix'!$S$2:$T$15,2,FALSE))} -> 1 | I19: {=INDEX('Correlation Matrix'!$C$3:$P$16,VLOOKUP(HLOOKUP($A19,$B$1:$X$4,4,FALSE),'Correlation Matrix'!$S$2:$T$15,2,FALSE),VLOOKUP(I$4,'Correlation Matrix'!$S$2:$T$15,2,FALSE))} -> 0.88061643 | ... X19: {=INDEX('Correlation Matrix'!$C$3:$P$16,VLOOKUP(HLOOKUP($A19,$B$1:$X$4,4,FALSE),'Correlation Matrix'!$S$2:$T$15,2,FALSE),VLOOKUP(X$4,'Correlation Matrix'!$S$2:$T$15,2,FALSE))} -> 0.022566479 | Y19: =B19*B$7*HLOOKUP($A19,$B$1:$X$7,7,FALSE) -> 0.024064151 | Z19: =C19*C$7*HLOOKUP($A19,$B$1:$X$7,7,FALSE) -> 0.024064151 | AA19: =D19*D$7*HLOOKUP($A19,$B$1:$X$7,7,FALSE) -> 0.024064151 | AB19: =E19*E$7*HLOOKUP($A19,$B$1:$X$7,7,FALSE) -> 0.029726508 | AC19: =F19*F$7*HLOOKUP($A19,$B$1:$X$7,7,FALSE) -> 0.024064151 | AD19: =G19*G$7*HLOOKUP($A19,$B$1:$X$7,7,FALSE) -> 0.026165284 | AE19: =H19*H$7*HLOOKUP($A19,$B$1:$X$7,7,FALSE) -> 0.039361084 | AF19: =I19*I$7*HLOOKUP($A19,$B$1:$X$7,7,FALSE) -> 0.024029985 | ... AU19: =X19*X$7*HLOOKUP($A19,$B$1:$X$7,7,FALSE) -> 2.4637669e-05
A20: CM7BE | B20: {=INDEX('Correlation Matrix'!$C$3:$P$16,VLOOKUP(HLOOKUP($A20,$B$1:$X$4,4,FALSE),'Correlation Matrix'!$S$2:$T$15,2,FALSE),VLOOKUP(B$4,'Correlation Matrix'!$S$2:$T$15,2,FALSE))} -> 0.92685289 | C20: {=INDEX('Correlation Matrix'!$C$3:$P$16,VLOOKUP(HLOOKUP($A20,$B$1:$X$4,4,FALSE),'Correlation Matrix'!$S$2:$T$15,2,FALSE),VLOOKUP(C$4,'Correlation Matrix'!$S$2:$T$15,2,FALSE))} -> 0.92685289 | D20: {=INDEX('Correlation Matrix'!$C$3:$P$16,VLOOKUP(HLOOKUP($A20,$B$1:$X$4,4,FALSE),'Correlation Matrix'!$S$2:$T$15,2,FALSE),VLOOKUP(D$4,'Correlation Matrix'!$S$2:$T$15,2,FALSE))} -> 0.92685289 | E20: {=INDEX('Correlation Matrix'!$C$3:$P$16,VLOOKUP(HLOOKUP($A20,$B$1:$X$4,4,FALSE),'Correlation Matrix'!$S$2:$T$15,2,FALSE),VLOOKUP(E$4,'Correlation Matrix'!$S$2:$T$15,2,FALSE))} -> 0.80910627 | F20: {=INDEX('Correlation Matrix'!$C$3:$P$16,VLOOKUP(HLOOKUP($A20,$B$1:$X$4,4,FALSE),'Correlation Matrix'!$S$2:$T$15,2,FALSE),VLOOKUP(F$4,'Correlation Matrix'!$S$2:$T$15,2,FALSE))} -> 0.92685289 | G20: {=INDEX('Correlation Matrix'!$C$3:$P$16,VLOOKUP(HLOOKUP($A20,$B$1:$X$4,4,FALSE),'Correlation Matrix'!$S$2:$T$15,2,FALSE),VLOOKUP(G$4,'Correlation Matrix'!$S$2:$T$15,2,FALSE))} -> 0.88933449 | H20: {=INDEX('Correlation Matrix'!$C$3:$P$16,VLOOKUP(HLOOKUP($A20,$B$1:$X$4,4,FALSE),'Correlation Matrix'!$S$2:$T$15,2,FALSE),VLOOKUP(H$4,'Correlation Matrix'!$S$2:$T$15,2,FALSE))} -> 0.96403514 | I20: {=INDEX('Correlation Matrix'!$C$3:$P$16,VLOOKUP(HLOOKUP($A20,$B$1:$X$4,4,FALSE),'Correlation Matrix'!$S$2:$T$15,2,FALSE),VLOOKUP(I$4,'Correlation Matrix'!$S$2:$T$15,2,FALSE))} -> 0.92843061 | ... X20: {=INDEX('Correlation Matrix'!$C$3:$P$16,VLOOKUP(HLOOKUP($A20,$B$1:$X$4,4,FALSE),'Correlation Matrix'!$S$2:$T$15,2,FALSE),VLOOKUP(X$4,'Correlation Matrix'!$S$2:$T$15,2,FALSE))} -> 0.044159076 | Y20: =B20*B$7*HLOOKUP($A20,$B$1:$X$7,7,FALSE) -> 0.022174047 | Z20: =C20*C$7*HLOOKUP($A20,$B$1:$X$7,7,FALSE) -> 0.022174047 | AA20: =D20*D$7*HLOOKUP($A20,$B$1:$X$7,7,FALSE) -> 0.022174047 | AB20: =E20*E$7*HLOOKUP($A20,$B$1:$X$7,7,FALSE) -> 0.026556547 | AC20: =F20*F$7*HLOOKUP($A20,$B$1:$X$7,7,FALSE) -> 0.022174047 | AD20: =G20*G$7*HLOOKUP($A20,$B$1:$X$7,7,FALSE) -> 0.023765406 | AE20: =H20*H$7*HLOOKUP($A20,$B$1:$X$7,7,FALSE) -> 0.033156013 | AF20: =I20*I$7*HLOOKUP($A20,$B$1:$X$7,7,FALSE) -> 0.02213699 | ... AU20: =X20*X$7*HLOOKUP($A20,$B$1:$X$7,7,FALSE) -> 4.2126772e-05
A21: VEVRX | B21: {=INDEX('Correlation Matrix'!$C$3:$P$16,VLOOKUP(HLOOKUP($A21,$B$1:$X$4,4,FALSE),'Correlation Matrix'!$S$2:$T$15,2,FALSE),VLOOKUP(B$4,'Correlation Matrix'!$S$2:$T$15,2,FALSE))} -> 0.87889862 | C21: {=INDEX('Correlation Matrix'!$C$3:$P$16,VLOOKUP(HLOOKUP($A21,$B$1:$X$4,4,FALSE),'Correlation Matrix'!$S$2:$T$15,2,FALSE),VLOOKUP(C$4,'Correlation Matrix'!$S$2:$T$15,2,FALSE))} -> 0.87889862 | D21: {=INDEX('Correlation Matrix'!$C$3:$P$16,VLOOKUP(HLOOKUP($A21,$B$1:$X$4,4,FALSE),'Correlation Matrix'!$S$2:$T$15,2,FALSE),VLOOKUP(D$4,'Correlation Matrix'!$S$2:$T$15,2,FALSE))} -> 0.87889862 | E21: {=INDEX('Correlation Matrix'!$C$3:$P$16,VLOOKUP(HLOOKUP($A21,$B$1:$X$4,4,FALSE),'Correlation Matrix'!$S$2:$T$15,2,FALSE),VLOOKUP(E$4,'Correlation Matrix'!$S$2:$T$15,2,FALSE))} -> 0.79137119 | F21: {=INDEX('Correlation Matrix'!$C$3:$P$16,VLOOKUP(HLOOKUP($A21,$B$1:$X$4,4,FALSE),'Correlation Matrix'!$S$2:$T$15,2,FALSE),VLOOKUP(F$4,'Correlation Matrix'!$S$2:$T$15,2,FALSE))} -> 0.87889862 | G21: {=INDEX('Correlation Matrix'!$C$3:$P$16,VLOOKUP(HLOOKUP($A21,$B$1:$X$4,4,FALSE),'Correlation Matrix'!$S$2:$T$15,2,FALSE),VLOOKUP(G$4,'Correlation Matrix'!$S$2:$T$15,2,FALSE))} -> 0.85555459 | H21: {=INDEX('Correlation Matrix'!$C$3:$P$16,VLOOKUP(HLOOKUP($A21,$B$1:$X$4,4,FALSE),'Correlation Matrix'!$S$2:$T$15,2,FALSE),VLOOKUP(H$4,'Correlation Matrix'!$S$2:$T$15,2,FALSE))} -> 1 | I21: {=INDEX('Correlation Matrix'!$C$3:$P$16,VLOOKUP(HLOOKUP($A21,$B$1:$X$4,4,FALSE),'Correlation Matrix'!$S$2:$T$15,2,FALSE),VLOOKUP(I$4,'Correlation Matrix'!$S$2:$T$15,2,FALSE))} -> 0.88061643 | ... X21: {=INDEX('Correlation Matrix'!$C$3:$P$16,VLOOKUP(HLOOKUP($A21,$B$1:$X$4,4,FALSE),'Correlation Matrix'!$S$2:$T$15,2,FALSE),VLOOKUP(X$4,'Correlation Matrix'!$S$2:$T$15,2,FALSE))} -> 0.022566479 | Y21: =B21*B$7*HLOOKUP($A21,$B$1:$X$7,7,FALSE) -> 0.024064151 | Z21: =C21*C$7*HLOOKUP($A21,$B$1:$X$7,7,FALSE) -> 0.024064151 | AA21: =D21*D$7*HLOOKUP($A21,$B$1:$X$7,7,FALSE) -> 0.024064151 | AB21: =E21*E$7*HLOOKUP($A21,$B$1:$X$7,7,FALSE) -> 0.029726508 | AC21: =F21*F$7*HLOOKUP($A21,$B$1:$X$7,7,FALSE) -> 0.024064151 | AD21: =G21*G$7*HLOOKUP($A21,$B$1:$X$7,7,FALSE) -> 0.026165284 | AE21: =H21*H$7*HLOOKUP($A21,$B$1:$X$7,7,FALSE) -> 0.039361084 | AF21: =I21*I$7*HLOOKUP($A21,$B$1:$X$7,7,FALSE) -> 0.024029985 | ... AU21: =X21*X$7*HLOOKUP($A21,$B$1:$X$7,7,FALSE) -> 2.4637669e-05
A22: GTDFX | B22: {=INDEX('Correlation Matrix'!$C$3:$P$16,VLOOKUP(HLOOKUP($A22,$B$1:$X$4,4,FALSE),'Correlation Matrix'!$S$2:$T$15,2,FALSE),VLOOKUP(B$4,'Correlation Matrix'!$S$2:$T$15,2,FALSE))} -> 0.65100938 | C22: {=INDEX('Correlation Matrix'!$C$3:$P$16,VLOOKUP(HLOOKUP($A22,$B$1:$X$4,4,FALSE),'Correlation Matrix'!$S$2:$T$15,2,FALSE),VLOOKUP(C$4,'Correlation Matrix'!$S$2:$T$15,2,FALSE))} -> 0.65100938 | D22: {=INDEX('Correlation Matrix'!$C$3:$P$16,VLOOKUP(HLOOKUP($A22,$B$1:$X$4,4,FALSE),'Correlation Matrix'!$S$2:$T$15,2,FALSE),VLOOKUP(D$4,'Correlation Matrix'!$S$2:$T$15,2,FALSE))} -> 0.65100938 | E22: {=INDEX('Correlation Matrix'!$C$3:$P$16,VLOOKUP(HLOOKUP($A22,$B$1:$X$4,4,FALSE),'Correlation Matrix'!$S$2:$T$15,2,FALSE),VLOOKUP(E$4,'Correlation Matrix'!$S$2:$T$15,2,FALSE))} -> 0.67877146 | F22: {=INDEX('Correlation Matrix'!$C$3:$P$16,VLOOKUP(HLOOKUP($A22,$B$1:$X$4,4,FALSE),'Correlation Matrix'!$S$2:$T$15,2,FALSE),VLOOKUP(F$4,'Correlation Matrix'!$S$2:$T$15,2,FALSE))} -> 0.65100938 | G22: {=INDEX('Correlation Matrix'!$C$3:$P$16,VLOOKUP(HLOOKUP($A22,$B$1:$X$4,4,FALSE),'Correlation Matrix'!$S$2:$T$15,2,FALSE),VLOOKUP(G$4,'Correlation Matrix'!$S$2:$T$15,2,FALSE))} -> 0.70064437 | H22: {=INDEX('Correlation Matrix'!$C$3:$P$16,VLOOKUP(HLOOKUP($A22,$B$1:$X$4,4,FALSE),'Correlation Matrix'!$S$2:$T$15,2,FALSE),VLOOKUP(H$4,'Correlation Matrix'!$S$2:$T$15,2,FALSE))} -> 0.64265609 | I22: {=INDEX('Correlation Matrix'!$C$3:$P$16,VLOOKUP(HLOOKUP($A22,$B$1:$X$4,4,FALSE),'Correlation Matrix'!$S$2:$T$15,2,FALSE),VLOOKUP(I$4,'Correlation Matrix'!$S$2:$T$15,2,FALSE))} -> 0.64705571 | ... X22: {=INDEX('Correlation Matrix'!$C$3:$P$16,VLOOKUP(HLOOKUP($A22,$B$1:$X$4,4,FALSE),'Correlation Matrix'!$S$2:$T$15,2,FALSE),VLOOKUP(X$4,'Correlation Matrix'!$S$2:$T$15,2,FALSE))} -> 0.016294376 | Y22: =B22*B$7*HLOOKUP($A22,$B$1:$X$7,7,FALSE) -> 0.016732097 | Z22: =C22*C$7*HLOOKUP($A22,$B$1:$X$7,7,FALSE) -> 0.016732097 | AA22: =D22*D$7*HLOOKUP($A22,$B$1:$X$7,7,FALSE) -> 0.016732097 | AB22: =E22*E$7*HLOOKUP($A22,$B$1:$X$7,7,FALSE) -> 0.023934183 | AC22: =F22*F$7*HLOOKUP($A22,$B$1:$X$7,7,FALSE) -> 0.016732097 | AD22: =G22*G$7*HLOOKUP($A22,$B$1:$X$7,7,FALSE) -> 0.020114383 | AE22: =H22*H$7*HLOOKUP($A22,$B$1:$X$7,7,FALSE) -> 0.023745266 | AF22: =I22*I$7*HLOOKUP($A22,$B$1:$X$7,7,FALSE) -> 0.016574474 | ... AU22: =X22*X$7*HLOOKUP($A22,$B$1:$X$7,7,FALSE) -> 1.6699556e-05
... A33: INVSVC2 | B33: {=INDEX('Correlation Matrix'!$C$3:$P$16,VLOOKUP(HLOOKUP($A33,$B$1:$X$4,4,FALSE),'Correlation Matrix'!$S$2:$T$15,2,FALSE),VLOOKUP(B$4,'Correlation Matrix'!$S$2:$T$15,2,FALSE))} -> 0.038353137 | C33: {=INDEX('Correlation Matrix'!$C$3:$P$16,VLOOKUP(HLOOKUP($A33,$B$1:$X$4,4,FALSE),'Correlation Matrix'!$S$2:$T$15,2,FALSE),VLOOKUP(C$4,'Correlation Matrix'!$S$2:$T$15,2,FALSE))} -> 0.038353137 | D33: {=INDEX('Correlation Matrix'!$C$3:$P$16,VLOOKUP(HLOOKUP($A33,$B$1:$X$4,4,FALSE),'Correlation Matrix'!$S$2:$T$15,2,FALSE),VLOOKUP(D$4,'Correlation Matrix'!$S$2:$T$15,2,FALSE))} -> 0.038353137 | E33: {=INDEX('Correlation Matrix'!$C$3:$P$16,VLOOKUP(HLOOKUP($A33,$B$1:$X$4,4,FALSE),'Correlation Matrix'!$S$2:$T$15,2,FALSE),VLOOKUP(E$4,'Correlation Matrix'!$S$2:$T$15,2,FALSE))} -> 0.0016452489 | F33: {=INDEX('Correlation Matrix'!$C$3:$P$16,VLOOKUP(HLOOKUP($A33,$B$1:$X$4,4,FALSE),'Correlation Matrix'!$S$2:$T$15,2,FALSE),VLOOKUP(F$4,'Correlation Matrix'!$S$2:$T$15,2,FALSE))} -> 0.038353137 | G33: {=INDEX('Correlation Matrix'!$C$3:$P$16,VLOOKUP(HLOOKUP($A33,$B$1:$X$4,4,FALSE),'Correlation Matrix'!$S$2:$T$15,2,FALSE),VLOOKUP(G$4,'Correlation Matrix'!$S$2:$T$15,2,FALSE))} -> 0.016108619 | H33: {=INDEX('Correlation Matrix'!$C$3:$P$16,VLOOKUP(HLOOKUP($A33,$B$1:$X$4,4,FALSE),'Correlation Matrix'!$S$2:$T$15,2,FALSE),VLOOKUP(H$4,'Correlation Matrix'!$S$2:$T$15,2,FALSE))} -> 0.022566479 | I33: {=INDEX('Correlation Matrix'!$C$3:$P$16,VLOOKUP(HLOOKUP($A33,$B$1:$X$4,4,FALSE),'Correlation Matrix'!$S$2:$T$15,2,FALSE),VLOOKUP(I$4,'Correlation Matrix'!$S$2:$T$15,2,FALSE))} -> 0.033366296 | ... X33: {=INDEX('Correlation Matrix'!$C$3:$P$16,VLOOKUP(HLOOKUP($A33,$B$1:$X$4,4,FALSE),'Correlation Matrix'!$S$2:$T$15,2,FALSE),VLOOKUP(X$4,'Correlation Matrix'!$S$2:$T$15,2,FALSE))} -> 1 | Y33: =B33*B$7*HLOOKUP($A33,$B$1:$X$7,7,FALSE) -> 2.912738e-05 | Z33: =C33*C$7*HLOOKUP($A33,$B$1:$X$7,7,FALSE) -> 2.912738e-05 | AA33: =D33*D$7*HLOOKUP($A33,$B$1:$X$7,7,FALSE) -> 2.912738e-05 | AB33: =E33*E$7*HLOOKUP($A33,$B$1:$X$7,7,FALSE) -> 1.71421e-06 | AC33: =F33*F$7*HLOOKUP($A33,$B$1:$X$7,7,FALSE) -> 2.912738e-05 | AD33: =G33*G$7*HLOOKUP($A33,$B$1:$X$7,7,FALSE) -> 1.3664848e-05 | AE33: =H33*H$7*HLOOKUP($A33,$B$1:$X$7,7,FALSE) -> 2.4637669e-05 | AF33: =I33*I$7*HLOOKUP($A33,$B$1:$X$7,7,FALSE) -> 2.5254774e-05 | ... AU33: =X33*X$7*HLOOKUP($A33,$B$1:$X$7,7,FALSE) -> 3.0283397e-05
B35: rand | Y35: weight | AV35: sum | AW35: contribution to return | BT35: portfolio return | BV35: portfolio variance
A36: portfolio | B36: INVDDC | C36: INVGIC | D36: INVAFC | E36: CMGH2 | F36: CMGF2 | G36: SSCMG2 | H36: ESPRX | I36: INVMGC | J36: GTSFX | K36: CM7BE | L36: VEVRX | M36: GTDFX | N36: INVIGTC | O36: SSCMGX2 | P36: INVS73 | Q36: CMAI4 | R36: INVPZ | S36: DIPSX | T36: INVS86 | U36: AFRFX | V36: SSCM7FE | W36: CM9N2 | X36: INVSVC2 | Y36: INVDDC | Z36: INVGIC | AA36: INVAFC | AB36: CMGH2 | AC36: CMGF2 | AD36: SSCMG2 | AE36: ESPRX | AF36: INVMGC | AG36: GTSFX | AH36: CM7BE | AI36: VEVRX | AJ36: GTDFX | AK36: INVIGTC | AL36: SSCMGX2 | AM36: INVS73 | AN36: CMAI4 | AO36: INVPZ | AP36: DIPSX | AQ36: INVS86 | AR36: AFRFX | AS36: SSCM7FE | AT36: CM9N2 | AU36: INVSVC2 | AW36: INVDDC | AX36: INVGIC | AY36: INVAFC | AZ36: CMGH2 | BA36: CMGF2 | BB36: SSCMG2 | BC36: ESPRX | BD36: INVMGC | BE36: GTSFX | BF36: CM7BE | BG36: VEVRX | BH36: GTDFX | BI36: INVIGTC | BJ36: SSCMGX2 | BK36: INVS73 | BL36: CMAI4 | BM36: INVPZ | BN36: DIPSX | BO36: INVS86 | BP36: AFRFX | BQ36: SSCM7FE | BR36: CM9N2 | BS36: INVSVC2
A37: 1 | B37: =RAND() -> 0.65528489 | C37: =RAND() -> 0.78435307 | D37: =RAND() -> 0.68720044 | E37: =RAND() -> 0.12778429 | F37: =RAND() -> 0.9555549 | G37: =RAND() -> 0.34512676 | H37: =RAND() -> 0.33610802 | I37: =RAND() -> 0.26456171 | ... X37: =RAND() -> 0.81964182 | Y37: =+B37/SUM($B37:$X37) -> 0.052275564 | Z37: =+C37/SUM($B37:$X37) -> 0.06257202 | AA37: =+D37/SUM($B37:$X37) -> 0.054821637 | AB37: =+E37/SUM($B37:$X37) -> 0.010194033 | AC37: =+F37/SUM($B37:$X37) -> 0.076229702 | AD37: =+G37/SUM($B37:$X37) -> 0.027532599 | AE37: =+H37/SUM($B37:$X37) -> 0.026813126 | AF37: =+I37/SUM($B37:$X37) -> 0.021105496 | ... AU37: =+X37/SUM($B37:$X37) -> 0.065387192 | AV37: =SUM(Y37:AU37) -> 1 | AW37: =Y37*B$6 -> 0.0034097649 | AX37: =Z37*C$6 -> 0.0040813692 | AY37: =AA37*D$6 -> 0.0035593905 | AZ37: =AB37*E$6 -> 0.0014926609 | BA37: =AC37*F$6 -> 0.0053457408 | BB37: =AD37*G$6 -> 0.0030921708 | BC37: =AE37*H$6 -> 0.0016290193 | BD37: =AF37*I$6 -> 0.0018631545 | ... BS37: =AU37*X$6 -> 1.1392203e-05 | BT37: =SUM(AW37:BS37) -> 0.053013812 | BU37: =SQRT(BV37) -> 0.10912037 | BV37: {=MMULT(Y37:AU37,MMULT($Y$11:$AU$33,TRANSPOSE(Y37:AU37)))} -> 0.011907256
A38: =A37+1 -> 2 | B38: =RAND() -> 0.84813916 | C38: =RAND() -> 0.65753199 | D38: =RAND() -> 0.39530935 | E38: =RAND() -> 0.27951765 | F38: =RAND() -> 0.28777804 | G38: =RAND() -> 0.78094195 | H38: =RAND() -> 0.40788113 | I38: =RAND() -> 0.5766564 | ... X38: =RAND() -> 0.12096827 | Y38: =+B38/SUM($B38:$X38) -> 0.075006121 | Z38: =+C38/SUM($B38:$X38) -> 0.058149566 | AA38: =+D38/SUM($B38:$X38) -> 0.034959618 | AB38: =+E38/SUM($B38:$X38) -> 0.024719452 | AC38: =+F38/SUM($B38:$X38) -> 0.025449968 | AD38: =+G38/SUM($B38:$X38) -> 0.069063462 | AE38: =+H38/SUM($B38:$X38) -> 0.036071417 | AF38: =+I38/SUM($B38:$X38) -> 0.050997244 | ... AU38: =+X38/SUM($B38:$X38) -> 0.010697962 | AV38: =SUM(Y38:AU38) -> 1 | AW38: =Y38*B$6 -> 0.0048924052 | AX38: =Z38*C$6 -> 0.0037929069 | AY38: =AA38*D$6 -> 0.0022698142 | AZ38: =AB38*E$6 -> 0.0036195447 | BA38: =AC38*F$6 -> 0.0017847234 | BB38: =AD38*G$6 -> 0.0077564788 | BC38: =AE38*H$6 -> 0.0021915026 | BD38: =AF38*I$6 -> 0.0045019432 | ... BS38: =AU38*X$6 -> 1.8638719e-06 | BT38: =SUM(AW38:BS38) -> 0.055923338 | BU38: =SQRT(BV38) -> 0.11031172 | BV38: {=MMULT(Y38:AU38,MMULT($Y$11:$AU$33,TRANSPOSE(Y38:AU38)))} -> 0.012168674
A39: =A38+1 -> 3 | B39: =RAND() -> 0.96213855 | C39: =RAND() -> 0.98914563 | D39: =RAND() -> 0.7713913 | E39: =RAND() -> 0.54122972 | F39: =RAND() -> 0.477923 | G39: =RAND() -> 0.092721881 | H39: =RAND() -> 0.34083068 | I39: =RAND() -> 0.064750823 | ... X39: =RAND() -> 0.62159341 | Y39: =+B39/SUM($B39:$X39) -> 0.071696898 | Z39: =+C39/SUM($B39:$X39) -> 0.07370942 | AA39: =+D39/SUM($B39:$X39) -> 0.057482743 | AB39: =+E39/SUM($B39:$X39) -> 0.040331502 | AC39: =+F39/SUM($B39:$X39) -> 0.035613994 | AD39: =+G39/SUM($B39:$X39) -> 0.006909474 | AE39: =+H39/SUM($B39:$X39) -> 0.025398112 | AF39: =+I39/SUM($B39:$X39) -> 0.0048251192 | ... AU39: =+X39/SUM($B39:$X39) -> 0.046320064 | AV39: =SUM(Y39:AU39) -> 1 | AW39: =Y39*B$6 -> 0.0046765553 | AX39: =Z39*C$6 -> 0.0048078255 | AY39: =AA39*D$6 -> 0.0037321674 | AZ39: =AB39*E$6 -> 0.0059055385 | BA39: =AC39*F$6 -> 0.0024974935 | BB39: =AD39*G$6 -> 0.00077599917 | BC39: =AE39*H$6 -> 0.0015430508 | BD39: =AF39*I$6 -> 0.00042595267 | ... BS39: =AU39*X$6 -> 8.0701976e-06 | BT39: =SUM(AW39:BS39) -> 0.048989051 | BU39: =SQRT(BV39) -> 0.10329313 | BV39: {=MMULT(Y39:AU39,MMULT($Y$11:$AU$33,TRANSPOSE(Y39:AU39)))} -> 0.010669471
A40: =A39+1 -> 4 | B40: =RAND() -> 0.33331949 | C40: =RAND() -> 0.94969884 | D40: =RAND() -> 0.2979304 | E40: =RAND() -> 0.9076194 | F40: =RAND() -> 0.70405971 | G40: =RAND() -> 0.10921679 | H40: =RAND() -> 0.92509716 | I40: =RAND() -> 0.87917134 | ... X40: =RAND() -> 0.86830882 | Y40: =+B40/SUM($B40:$X40) -> 0.02303634 | Z40: =+C40/SUM($B40:$X40) -> 0.065635483 | AA40: =+D40/SUM($B40:$X40) -> 0.020590533 | AB40: =+E40/SUM($B40:$X40) -> 0.062727293 | AC40: =+F40/SUM($B40:$X40) -> 0.048658898 | AD40: =+G40/SUM($B40:$X40) -> 0.0075481792 | AE40: =+H40/SUM($B40:$X40) -> 0.063935215 | AF40: =+I40/SUM($B40:$X40) -> 0.060761194 | ... AU40: =+X40/SUM($B40:$X40) -> 0.060010465 | AV40: =SUM(Y40:AU40) -> 1 | AW40: =Y40*B$6 -> 0.0015025855 | AX40: =Z40*C$6 -> 0.0042811889 | AY40: =AA40*D$6 -> 0.0013368763 | AZ40: =AB40*E$6 -> 0.0091848414 | BA40: =AC40*F$6 -> 0.0034122901 | BB40: =AD40*G$6 -> 0.00084773179 | BC40: =AE40*H$6 -> 0.003884355 | BD40: =AF40*I$6 -> 0.0053638867 | ... BS40: =AU40*X$6 -> 1.0455433e-05 | BT40: =SUM(AW40:BS40) -> 0.049962047 | BU40: =SQRT(BV40) -> 0.10027206 | BV40: {=MMULT(Y40:AU40,MMULT($Y$11:$AU$33,TRANSPOSE(Y40:AU40)))} -> 0.010054486
A41: =A40+1 -> 5 | B41: =RAND() -> 0.038137323 | C41: =RAND() -> 0.38397439 | D41: =RAND() -> 0.73983437 | E41: =RAND() -> 0.0452985 | F41: =RAND() -> 0.48307209 | G41: =RAND() -> 0.86503333 | H41: =RAND() -> 0.91297705 | I41: =RAND() -> 0.21143498 | ... X41: =RAND() -> 0.93595834 | Y41: =+B41/SUM($B41:$X41) -> 0.00302159 | Z41: =+C41/SUM($B41:$X41) -> 0.030421988 | AA41: =+D41/SUM($B41:$X41) -> 0.058616493 | AB41: =+E41/SUM($B41:$X41) -> 0.0035889644 | AC41: =+F41/SUM($B41:$X41) -> 0.03827342 | AD41: =+G41/SUM($B41:$X41) -> 0.068535908 | AE41: =+H41/SUM($B41:$X41) -> 0.072334451 | AF41: =+I41/SUM($B41:$X41) -> 0.016751826 | ... AU41: =+X41/SUM($B41:$X41) -> 0.07415524 | AV41: =SUM(Y41:AU41) -> 1 | AW41: =Y41*B$6 -> 0.00019708848 | AX41: =Z41*C$6 -> 0.0019843273 | AY41: =AA41*D$6 -> 0.0038057781 | AZ41: =AB41*E$6 -> 0.00052551396 | BA41: =AC41*F$6 -> 0.0026839904 | BB41: =AD41*G$6 -> 0.0076972295 | BC41: =AE41*H$6 -> 0.0043946468 | BD41: =AF41*I$6 -> 0.0014788205 | ... BS41: =AU41*X$6 -> 1.2919832e-05 | BT41: =SUM(AW41:BS41) -> 0.045917723 | BU41: =SQRT(BV41) -> 0.099704749 | BV41: {=MMULT(Y41:AU41,MMULT($Y$11:$AU$33,TRANSPOSE(Y41:AU41)))} -> 0.009941037
A42: =A41+1 -> 6 | B42: =RAND() -> 0.18617121 | C42: =RAND() -> 0.75355086 | D42: =RAND() -> 0.62702955 | E42: =RAND() -> 0.23876112 | F42: =RAND() -> 0.34795952 | G42: =RAND() -> 0.87916919 | H42: =RAND() -> 0.64078932 | I42: =RAND() -> 0.71940995 | ... X42: =RAND() -> 0.79657343 | Y42: =+B42/SUM($B42:$X42) -> 0.017544323 | Z42: =+C42/SUM($B42:$X42) -> 0.071012803 | AA42: =+D42/SUM($B42:$X42) -> 0.059089742 | AB42: =+E42/SUM($B42:$X42) -> 0.022500269 | AC42: =+F42/SUM($B42:$X42) -> 0.03279086 | AD42: =+G42/SUM($B42:$X42) -> 0.082850769 | AE42: =+H42/SUM($B42:$X42) -> 0.060386429 | AF42: =+I42/SUM($B42:$X42) -> 0.067795446 | ... AU42: =+X42/SUM($B42:$X42) -> 0.075067146 | AV42: =SUM(Y42:AU42) -> 1 | AW42: =Y42*B$6 -> 0.0011443591 | AX42: =Z42*C$6 -> 0.004631934 | AY42: =AA42*D$6 -> 0.0038365046 | AZ42: =AB42*E$6 -> 0.0032946009 | BA42: =AC42*F$6 -> 0.0022995163 | BB42: =AD42*G$6 -> 0.0093049236 | BC42: =AE42*H$6 -> 0.0036687502 | BD42: =AF42*I$6 -> 0.0059848577 | ... BS42: =AU42*X$6 -> 1.307871e-05 | BT42: =SUM(AW42:BS42) -> 0.058082495 | BU42: =SQRT(BV42) -> 0.11266551 | BV42: {=MMULT(Y42:AU42,MMULT($Y$11:$AU$33,TRANSPOSE(Y42:AU42)))} -> 0.012693516
A43: =A42+1 -> 7 | B43: =RAND() -> 0.34164614 | C43: =RAND() -> 0.90586567 | D43: =RAND() -> 0.64225088 | E43: =RAND() -> 0.7697752 | F43: =RAND() -> 0.64991791 | G43: =RAND() -> 0.3572712 | H43: =RAND() -> 0.072206403 | I43: =RAND() -> 0.68801681 | ... X43: =RAND() -> 0.026986187 | Y43: =+B43/SUM($B43:$X43) -> 0.027947942 | Z43: =+C43/SUM($B43:$X43) -> 0.074103228 | AA43: =+D43/SUM($B43:$X43) -> 0.052538544 | AB43: =+E43/SUM($B43:$X43) -> 0.062970514 | AC43: =+F43/SUM($B43:$X43) -> 0.053165735 | AD43: =+G43/SUM($B43:$X43) -> 0.029226131 | AE43: =+H43/SUM($B43:$X43) -> 0.005906756 | AF43: =+I43/SUM($B43:$X43) -> 0.056282369 | ... AU43: =+X43/SUM($B43:$X43) -> 0.0022075718 | AV43: =SUM(Y43:AU43) -> 1 | AW43: =Y43*B$6 -> 0.0018229533 | AX43: =Z43*C$6 -> 0.0048335123 | AY43: =AA43*D$6 -> 0.0034111566 | AZ43: =AB43*E$6 -> 0.009220455 | BA43: =AC43*F$6 -> 0.00372834 | BB43: =AD43*G$6 -> 0.0032823705 | BC43: =AE43*H$6 -> 0.00035886229 | BD43: =AF43*I$6 -> 0.0049685043 | ... BS43: =AU43*X$6 -> 3.8461823e-07 | BT43: =SUM(AW43:BS43) -> 0.059809631 | BU43: =SQRT(BV43) -> 0.11586161 | BV43: {=MMULT(Y43:AU43,MMULT($Y$11:$AU$33,TRANSPOSE(Y43:AU43)))} -> 0.013423912
A44: =A43+1 -> 8 | B44: =RAND() -> 0.62670323 | C44: =RAND() -> 0.12174378 | D44: =RAND() -> 0.87141224 | E44: =RAND() -> 0.7164198 | F44: =RAND() -> 0.90948466 | G44: =RAND() -> 0.76927988 | H44: =RAND() -> 0.71357683 | I44: =RAND() -> 0.87904781 | ... X44: =RAND() -> 0.064576069 | Y44: =+B44/SUM($B44:$X44) -> 0.055500943 | Z44: =+C44/SUM($B44:$X44) -> 0.010781649 | AA44: =+D44/SUM($B44:$X44) -> 0.077172413 | AB44: =+E44/SUM($B44:$X44) -> 0.063446257 | AC44: =+F44/SUM($B44:$X44) -> 0.080544113 | AD44: =+G44/SUM($B44:$X44) -> 0.068127554 | AE44: =+H44/SUM($B44:$X44) -> 0.063194482 | AF44: =+I44/SUM($B44:$X44) -> 0.07784862 | ... AU44: =+X44/SUM($B44:$X44) -> 0.0057188674 | AV44: =SUM(Y44:AU44) -> 1 | AW44: =Y44*B$6 -> 0.0036201458 | AX44: =Z44*C$6 -> 0.0007032519 | AY44: =AA44*D$6 -> 0.0050105536 | AZ44: =AB44*E$6 -> 0.0092901155 | BA44: =AC44*F$6 -> 0.0056482965 | BB44: =AD44*G$6 -> 0.0076513675 | BC44: =AE44*H$6 -> 0.0038393522 | BD44: =AF44*I$6 -> 0.0068723334 | ... BS44: =AU44*X$6 -> 9.9638011e-07 | BT44: =SUM(AW44:BS44) -> 0.061227625 | BU44: =SQRT(BV44) -> 0.1146051 | BV44: {=MMULT(Y44:AU44,MMULT($Y$11:$AU$33,TRANSPOSE(Y44:AU44)))} -> 0.013134329
A45: =A44+1 -> 9 | B45: =RAND() -> 0.58095277 | C45: =RAND() -> 0.3805032 | D45: =RAND() -> 0.27377455 | E45: =RAND() -> 0.55283574 | F45: =RAND() -> 0.55342904 | G45: =RAND() -> 0.1481745 | H45: =RAND() -> 0.26099425 | I45: =RAND() -> 0.72512424 | ... X45: =RAND() -> 0.36137773 | Y45: =+B45/SUM($B45:$X45) -> 0.059542757 | Z45: =+C45/SUM($B45:$X45) -> 0.038998368 | AA45: =+D45/SUM($B45:$X45) -> 0.028059581 | AB45: =+E45/SUM($B45:$X45) -> 0.056660999 | AC45: =+F45/SUM($B45:$X45) -> 0.056721807 | AD45: =+G45/SUM($B45:$X45) -> 0.015186637 | AE45: =+H45/SUM($B45:$X45) -> 0.026749709 | AF45: =+I45/SUM($B45:$X45) -> 0.074319117 | ... AU45: =+X45/SUM($B45:$X45) -> 0.037038168 | AV45: =SUM(Y45:AU45) -> 1 | AW45: =Y45*B$6 -> 0.0038837803 | AX45: =Z45*C$6 -> 0.0025437366 | AY45: =AA45*D$6 -> 0.0018218173 | AZ45: =AB45*E$6 -> 0.0082965844 | BA45: =AC45*F$6 -> 0.0039777157 | BB45: =AD45*G$6 -> 0.0017056027 | BC45: =AE45*H$6 -> 0.0016251665 | BD45: =AF45*I$6 -> 0.0065607553 | ... BS45: =AU45*X$6 -> 6.4530424e-06 | BT45: =SUM(AW45:BS45) -> 0.058159402 | BU45: =SQRT(BV45) -> 0.11528912 | BV45: {=MMULT(Y45:AU45,MMULT($Y$11:$AU$33,TRANSPOSE(Y45:AU45)))} -> 0.013291582
A46: =A45+1 -> 10 | B46: =RAND() -> 0.010238691 | C46: =RAND() -> 0.20525297 | D46: =RAND() -> 0.66835559 | E46: =RAND() -> 0.15626033 | F46: =RAND() -> 0.033524079 | G46: =RAND() -> 0.12072412 | H46: =RAND() -> 0.081925865 | I46: =RAND() -> 0.53916314 | ... X46: =RAND() -> 0.20497796 | Y46: =+B46/SUM($B46:$X46) -> 0.0013019944 | Z46: =+C46/SUM($B46:$X46) -> 0.026100818 | AA46: =+D46/SUM($B46:$X46) -> 0.084990864 | AB46: =+E46/SUM($B46:$X46) -> 0.01987071 | AC46: =+F46/SUM($B46:$X46) -> 0.0042630607 | AD46: =+G46/SUM($B46:$X46) -> 0.01535178 | AE46: =+H46/SUM($B46:$X46) -> 0.010418032 | AF46: =+I46/SUM($B46:$X46) -> 0.068562217 | ... AU46: =+X46/SUM($B46:$X46) -> 0.026065847 | AV46: =SUM(Y46:AU46) -> 1 | AW46: =Y46*B$6 -> 8.4924857e-05 | AX46: =Z46*C$6 -> 0.0017024714 | AY46: =AA46*D$6 -> 0.0055181802 | AZ46: =AB46*E$6 -> 0.0029095679 | BA46: =AC46*F$6 -> 0.00029895457 | BB46: =AD46*G$6 -> 0.0017241498 | BC46: =AE46*H$6 -> 0.00063294283 | BD46: =AF46*I$6 -> 0.0060525468 | ... BS46: =AU46*X$6 -> 4.5413697e-06 | BT46: =SUM(AW46:BS46) -> 0.04660411 | BU46: =SQRT(BV46) -> 0.10574397 | BV46: {=MMULT(Y46:AU46,MMULT($Y$11:$AU$33,TRANSPOSE(Y46:AU46)))} -> 0.011181788
A47: =A46+1 -> 11 | B47: =RAND() -> 0.81900419 | C47: =RAND() -> 0.38703287 | D47: =RAND() -> 0.69671967 | E47: =RAND() -> 0.89402372 | F47: =RAND() -> 0.081954815 | G47: =RAND() -> 0.31822105 | H47: =RAND() -> 0.081563671 | I47: =RAND() -> 0.62188821 | ... X47: =RAND() -> 0.89474612 | Y47: =+B47/SUM($B47:$X47) -> 0.065185389 | Z47: =+C47/SUM($B47:$X47) -> 0.030804346 | AA47: =+D47/SUM($B47:$X47) -> 0.055452638 | AB47: =+E47/SUM($B47:$X47) -> 0.071156271 | AC47: =+F47/SUM($B47:$X47) -> 0.0065228684 | AD47: =+G47/SUM($B47:$X47) -> 0.025327542 | AE47: =+H47/SUM($B47:$X47) -> 0.0064917368 | AF47: =+I47/SUM($B47:$X47) -> 0.049496725 | ... AU47: =+X47/SUM($B47:$X47) -> 0.071213768 | AV47: =SUM(Y47:AU47) -> 1 | AW47: =Y47*B$6 -> 0.0042518308 | AX47: =Z47*C$6 -> 0.0020092672 | AY47: =AA47*D$6 -> 0.0036003593 | AZ47: =AB47*E$6 -> 0.010419054 | BA47: =AC47*F$6 -> 0.00045742753 | BB47: =AD47*G$6 -> 0.0028445221 | BC47: =AE47*H$6 -> 0.00039440253 | BD47: =AF47*I$6 -> 0.0043694801 | ... BS47: =AU47*X$6 -> 1.2407348e-05 | BT47: =SUM(AW47:BS47) -> 0.055561295 | BU47: =SQRT(BV47) -> 0.10414792 | BV47: {=MMULT(Y47:AU47,MMULT($Y$11:$AU$33,TRANSPOSE(Y47:AU47)))} -> 0.010846789
A48: =A47+1 -> 12 | B48: =RAND() -> 0.83795018 | C48: =RAND() -> 0.3555797 | D48: =RAND() -> 0.61380883 | E48: =RAND() -> 0.8073202 | F48: =RAND() -> 0.64268833 | G48: =RAND() -> 0.35233809 | H48: =RAND() -> 0.50583006 | I48: =RAND() -> 0.9275585 | ... X48: =RAND() -> 0.30610819 | Y48: =+B48/SUM($B48:$X48) -> 0.063866101 | Z48: =+C48/SUM($B48:$X48) -> 0.02710124 | AA48: =+D48/SUM($B48:$X48) -> 0.046782706 | AB48: =+E48/SUM($B48:$X48) -> 0.061531574 | AC48: =+F48/SUM($B48:$X48) -> 0.048983816 | AD48: =+G48/SUM($B48:$X48) -> 0.026854174 | AE48: =+H48/SUM($B48:$X48) -> 0.038552881 | AF48: =+I48/SUM($B48:$X48) -> 0.070695784 | ... AU48: =+X48/SUM($B48:$X48) -> 0.023330667 | AV48: =SUM(Y48:AU48) -> 1 | AW48: =Y48*B$6 -> 0.0041657779 | AX48: =Z48*C$6 -> 0.0017677257 | AY48: =AA48*D$6 -> 0.0030374488 | AZ48: =AB48*E$6 -> 0.0090097582 | BA48: =AC48*F$6 -> 0.0034350756 | BB48: =AD48*G$6 -> 0.0030159773 | BC48: =AE48*H$6 -> 0.0023422629 | BD48: =AF48*I$6 -> 0.0062408942 | ... BS48: =AU48*X$6 -> 4.064828e-06 | BT48: =SUM(AW48:BS48) -> 0.056550735 | BU48: =SQRT(BV48) -> 0.113482 | BV48: {=MMULT(Y48:AU48,MMULT($Y$11:$AU$33,TRANSPOSE(Y48:AU48)))} -> 0.012878163
A49: =A48+1 -> 13 | B49: =RAND() -> 0.98298905 | C49: =RAND() -> 0.46382797 | D49: =RAND() -> 0.52203943 | E49: =RAND() -> 0.025048883 | F49: =RAND() -> 0.19598197 | G49: =RAND() -> 0.27875071 | H49: =RAND() -> 0.69266322 | I49: =RAND() -> 0.0090096954 | ... X49: =RAND() -> 0.22127265 | Y49: =+B49/SUM($B49:$X49) -> 0.091572722 | Z49: =+C49/SUM($B49:$X49) -> 0.043209017 | AA49: =+D49/SUM($B49:$X49) -> 0.048631846 | AB49: =+E49/SUM($B49:$X49) -> 0.0023334893 | AC49: =+F49/SUM($B49:$X49) -> 0.018257175 | AD49: =+G49/SUM($B49:$X49) -> 0.025967697 | AE49: =+H49/SUM($B49:$X49) -> 0.064526718 | AF49: =+I49/SUM($B49:$X49) -> 0.00083931997 | ... AU49: =+X49/SUM($B49:$X49) -> 0.020613189 | AV49: =SUM(Y49:AU49) -> 1 | AW49: =Y49*B$6 -> 0.0059729906 | AX49: =Z49*C$6 -> 0.0028183835 | AY49: =AA49*D$6 -> 0.0031575075 | AZ49: =AB49*E$6 -> 0.00034168108 | BA49: =AC49*F$6 -> 0.0012803163 | BB49: =AD49*G$6 -> 0.0029164176 | BC49: =AE49*H$6 -> 0.0039202915 | BD49: =AF49*I$6 -> 7.4093628e-05 | ... BS49: =AU49*X$6 -> 3.5913704e-06 | BT49: =SUM(AW49:BS49) -> 0.047868455 | BU49: =SQRT(BV49) -> 0.10480626 | BV49: {=MMULT(Y49:AU49,MMULT($Y$11:$AU$33,TRANSPOSE(Y49:AU49)))} -> 0.010984351
... A1036: =A1035+1 -> 1000 | B1036: =RAND() -> 0.42041783 | C1036: =RAND() -> 0.46012192 | D1036: =RAND() -> 0.30734918 | E1036: =RAND() -> 0.24394137 | F1036: =RAND() -> 0.2374735 | G1036: =RAND() -> 0.51775432 | H1036: =RAND() -> 0.56235501 | I1036: =RAND() -> 0.47027249 | ... X1036: =RAND() -> 0.12673978 | Y1036: =+B1036/SUM($B1036:$X1036) -> 0.039156018 | Z1036: =+C1036/SUM($B1036:$X1036) -> 0.042853897 | AA1036: =+D1036/SUM($B1036:$X1036) -> 0.028625261 | AB1036: =+E1036/SUM($B1036:$X1036) -> 0.022719714 | AC1036: =+F1036/SUM($B1036:$X1036) -> 0.022117322 | AD1036: =+G1036/SUM($B1036:$X1036) -> 0.048221546 | AE1036: =+H1036/SUM($B1036:$X1036) -> 0.052375474 | AF1036: =+I1036/SUM($B1036:$X1036) -> 0.04379928 | ... AU1036: =+X1036/SUM($B1036:$X1036) -> 0.011804031 | AV1036: =SUM(Y1036:AU1036) -> 1 | AW1036: =Y1036*B$6 -> 0.0025540196 | AX1036: =Z1036*C$6 -> 0.0027952202 | AY1036: =AA1036*D$6 -> 0.001858545 | AZ1036: =AB1036*E$6 -> 0.0033267332 | BA1036: =AC1036*F$6 -> 0.0015510158 | BB1036: =AD1036*G$6 -> 0.0054157349 | BC1036: =AE1036*H$6 -> 0.0031820482 | BD1036: =AF1036*I$6 -> 0.0038665201 | ... BS1036: =AU1036*X$6 -> 2.0565789e-06 | BT1036: =SUM(AW1036:BS1036) -> 0.054817796 | BU1036: =SQRT(BV1036) -> 0.11493058 | BV1036: {=MMULT(Y1036:AU1036,MMULT($Y$11:$AU$33,TRANSPOSE(Y1036:AU1036)))} -> 0.013209039

Sheet Optimal Weights
A1: Fund Available | B1: INVDDC | C1: INVGIC | D1: INVAFC | E1: CMGH2 | F1: CMGF2 | G1: SSCMG2 | H1: ESPRX | I1: INVMGC | J1: GTSFX | K1: CM7BE | L1: VEVRX | M1: GTDFX | N1: INVIGTC | O1: SSCMGX2 | P1: INVS73 | Q1: CMAI4 | R1: INVPZ | S1: DIPSX | T1: INVS86 | U1: AFRFX | V1: SSCM7FE | W1: CM9N2 | X1: INVSVC2
A2: Benchmark | B2: Russell 1000 Value Index | C2: Russell 1000 Value Index | D2: Russell 1000 Value Index | E2: Russell 1000 Growth Index | F2: Russell 1000 Value Index | G2: S&P500 Index | H2: Russell 2000 TR USD | I2: Russell Midcap Growth Index | J2: Russell 2000 TR USD | K2: S&P MidCap 400 Index | L2: Russell 2000 TR USD | M2: MSCI EM PR USD | N2: MSCI ACWI ex USA Index | O2: MSCI ACWI ex USA IMI Index | P2: FTSE Nareit All Equity REITs Index | Q2: Dow Jones U.S Select REIT Index | R2: Bloomberg US Treasury Bellwethers 3 Month Index | S2: Bloomberg Intermediate Treasury TR USD | T2: Bloomberg U.S. Aggregate Bond Index | U2: USTREAS T-Bill Auction Ave 3 Mon | V2: Bloomberg U.S. Aggregate Bond Index | W2: Bloomberg U.S. TIPS Index | X2: Bloomberg US Treasury Bellwethers 3 Month Index
A3: Expense Ratio | B3: 0.0051 | C3: 0.0051 | D3: 0.0054 | E3: 0.0002 | F3: 0.0002 | G3: 0.0001 | H3: 0.0085 | I3: 0.0067 | J3: 0.0076 | K3: 0.00015 | L3: 0.0054 | M3: 0.01 | N3: 0.0082 | O3: 0.00045 | P3: 0.0085 | Q3: 0.0005 | R3: 0.0046 | S3: 0.0011 | T3: 0.0037 | U3: 0.0081 | V3: 0.0002 | W3: 0.0004 | X3: 0.0053
A4: Expected Net Return | B4: 0.065226745 | C4: 0.065226745 | D4: 0.064926745 | E4: 0.14642496 | F4: 0.070126745 | G4: 0.11230944 | H4: 0.060754547 | I4: 0.088278166 | J4: 0.061654547 | K4: 0.063911718 | L4: 0.063854547 | M4: 0.069635892 | N4: 0.07602986 | O4: 0.08377986 | P4: 0.022691862 | Q4: 0.032521617 | R4: 0.00087422682 | S4: 0.013226235 | T4: 0.019642289 | U4: -0.0026257732 | V4: 0.023142289 | W4: 0.014386153 | X4: 0.00017422682
A5: index standard deviation | B5: 0.13800609 | C5: 0.13800609 | D5: 0.13800609 | E5: 0.18933466 | F5: 0.13800609 | G5: 0.15415024 | H5: 0.19839628 | I5: 0.13754132 | J5: 0.19839628 | K5: 0.17335482 | L5: 0.19839628 | M5: 0.18623654 | N5: 0.14870493 | O5: 0.14870493 | P5: 0.17137514 | Q5: 0.17371515 | R5: 0.0055030352 | S5: 0.066325712 | T5: 0.050775353 | U5: 0.0055030352 | V5: 0.050775353 | W5: 0.051998938 | X5: 0.0055030352
A6: 10yTreas9092026 | B6: 0.0483
A7: Sharpe Ratio | B7: 0.12265216 | C7: 0.12265216 | D7: 0.12047835 | E7: 0.51826199 | F7: 0.15815784 | G7: 0.41524063 | H7: 0.062776113 | I7: 0.29066295 | J7: 0.067312488 | K7: 0.090056441 | L7: 0.078401406 | M7: 0.11456341 | N7: 0.18647572 | O7: 0.23859235 | P7: -0.14942737 | Q7: -0.09082906 | R7: -8.6181119 | S7: -0.52881098 | T7: -0.56440201 | U7: -9.2541245 | V7: -0.49547092 | W7: -0.65220267 | X7: -8.7453144
Y8: sum
A9: Weights | B9: 0 | C9: 0 | D9: 0 | E9: 0.78565553 | F9: 0 | G9: 0 | H9: 0 | I9: 0 | J9: 0 | K9: 0 | L9: 0 | M9: 0 | N9: 0 | O9: 0 | P9: 0 | Q9: 0 | R9: 0 | S9: 0 | T9: 0 | U9: 0 | V9: 0.21434447 | W9: 0 | X9: 0 | Y9: =SUM(B9:X9) -> 1
A10: Contribution to Portfolio Return | B10: =B9*B4 -> 0 | C10: =C9*C4 -> 0 | D10: =D9*D4 -> 0 | E10: =E9*E4 -> 0.11503958 | F10: =F9*F4 -> 0 | G10: =G9*G4 -> 0 | H10: =H9*H4 -> 0 | I10: =I9*I4 -> 0 | ... X10: =X9*X4 -> 0
A12: Portfolio variance | B12: {=MMULT(B9:X9,MMULT('Fund Stats'!Y11:AU33,TRANSPOSE(B9:X9)))} -> 0.022708436
A13: Standard Deviation | B13: =SQRT(B12) -> 0.15069319
A14: portfolio return | B14: =SUM(B10:X10) -> 0.12
A15: Portfolio Sharpe | B15: =(B14-'Fund Stats'!B8)/'Optimal Weights'!B13 -> 0.47580121
A17: Return Maximizing Portfolio | B17: INVDDC | C17: INVGIC | D17: INVAFC | E17: CMGH2 | F17: CMGF2 | G17: SSCMG2 | H17: ESPRX | I17: INVMGC | J17: GTSFX | K17: CM7BE | L17: VEVRX | M17: GTDFX | N17: INVIGTC | O17: SSCMGX2 | P17: INVS73 | Q17: CMAI4 | R17: INVPZ | S17: DIPSX | T17: INVS86 | U17: AFRFX | V17: SSCM7FE | W17: CM9N2 | X17: INVSVC2 | Y17: sum
A18: Weights | B18: 0 | C18: 0 | D18: 0 | E18: 1 | F18: 0 | G18: 0 | H18: 0 | I18: 0 | J18: 0 | K18: 0 | L18: 0 | M18: 0 | N18: 0 | O18: 0 | P18: 0 | Q18: 0 | R18: 0 | S18: 0 | T18: 0 | U18: 0 | V18: 0 | W18: 0 | X18: 0 | Y18: 1
A19: Contribution to Portfolio Return | B19: 0 | C19: 0 | D19: 0 | E19: 0.14642496 | F19: 0 | G19: 0 | H19: 0 | I19: 0 | J19: 0 | K19: 0 | L19: 0 | M19: 0 | N19: 0 | O19: 0 | P19: 0 | Q19: 0 | R19: 0 | S19: 0 | T19: 0 | U19: 0 | V19: 0 | W19: 0 | X19: 0
A21: Portfolio variance | B21: 0.035847614
A22: Standard Deviation | B22: 0.18933466
A23: portfolio return | B23: 0.14642496
A25: Variance Minimum Portfolio | B25: INVDDC | C25: INVGIC | D25: INVAFC | E25: CMGH2 | F25: CMGF2 | G25: SSCMG2 | H25: ESPRX | I25: INVMGC | J25: GTSFX | K25: CM7BE | L25: VEVRX | M25: GTDFX | N25: INVIGTC | O25: SSCMGX2 | P25: INVS73 | Q25: CMAI4 | R25: INVPZ | S25: DIPSX | T25: INVS86 | U25: AFRFX | V25: SSCM7FE | W25: CM9N2 | X25: INVSVC2 | Y25: sum
A26: Weights | B26: 0 | C26: 0 | D26: 0 | E26: 0 | F26: 0 | G26: 0 | H26: 0 | I26: 0 | J26: 0 | K26: 0 | L26: 0 | M26: 0 | N26: 0 | O26: 0 | P26: 0 | Q26: 0 | R26: 0.40750217 | S26: 0 | T26: 0.008917516 | U26: 0.27942426 | V26: 0.008917516 | W26: 0.015814272 | X26: 0.27942426 | Y26: 1
A27: Contribution to Portfolio Return | B27: 0 | C27: 0 | D27: 0 | E27: 0 | F27: 0 | G27: 0 | H27: 0 | I27: 0 | J27: 0 | K27: 0 | L27: 0 | M27: 0 | N27: 0 | O27: 0 | P27: 0 | Q27: 0 | R27: 0.00035624933 | S27: 0 | T27: 0.00017516043 | U27: -0.00073370473 | V27: 0.00020637173 | W27: 0.00022750655 | X27: 4.8683202e-05
A29: Portfolio variance | B29: 2.736538e-05
A30: Standard Deviation | B30: 0.005231193
A31: portfolio return | B31: 0.0002802665
A33: Sharpe Optimal Portfolio | B33: INVDDC | C33: INVGIC | D33: INVAFC | E33: CMGH2 | F33: CMGF2 | G33: SSCMG2 | H33: ESPRX | I33: INVMGC | J33: GTSFX | K33: CM7BE | L33: VEVRX | M33: GTDFX | N33: INVIGTC | O33: SSCMGX2 | P33: INVS73 | Q33: CMAI4 | R33: INVPZ | S33: DIPSX | T33: INVS86 | U33: AFRFX | V33: SSCM7FE | W33: CM9N2 | X33: INVSVC2 | Y33: sum
A34: Weights | B34: 0 | C34: 0 | D34: 0 | E34: 0.99999998 | F34: 0 | G34: 0 | H34: 0 | I34: 0 | J34: 0 | K34: 0 | L34: 0 | M34: 0 | N34: 0 | O34: 0 | P34: 0 | Q34: 0 | R34: 0 | S34: 0 | T34: 0 | U34: 0 | V34: 0 | W34: 0 | X34: 0 | Y34: 0.99999998
A35: Contribution to Portfolio Return | B35: 0 | C35: 0 | D35: 0 | E35: 0.14642496 | F35: 0 | G35: 0 | H35: 0 | I35: 0 | J35: 0 | K35: 0 | L35: 0 | M35: 0 | N35: 0 | O35: 0 | P35: 0 | Q35: 0 | R35: 0 | S35: 0 | T35: 0 | U35: 0 | V35: 0 | W35: 0 | X35: 0
A37: Portfolio variance | B37: 0.035847613
A38: Standard Deviation | B38: 0.18933466
A39: portfolio return | B39: 0.14642496
A40: Portfolio Sharpe | B40: 0.51826199
A42: Sharpe Optimal contingent on standard deviation <11% | B42: INVDDC | C42: INVGIC | D42: INVAFC | E42: CMGH2 | F42: CMGF2 | G42: SSCMG2 | H42: ESPRX | I42: INVMGC | J42: GTSFX | K42: CM7BE | L42: VEVRX | M42: GTDFX | N42: INVIGTC | O42: SSCMGX2 | P42: INVS73 | Q42: CMAI4 | R42: INVPZ | S42: DIPSX | T42: INVS86 | U42: AFRFX | V42: SSCM7FE | W42: CM9N2 | X42: INVSVC2 | Y42: sum
A43: Weights | B43: 0 | C43: 0 | D43: 0 | E43: 0.55145725 | F43: 0 | G43: 0 | H43: 0 | I43: 0 | J43: 0 | K43: 0 | L43: 0 | M43: 0 | N43: 0 | O43: 0 | P43: 0 | Q43: 0 | R43: 0 | S43: 0 | T43: 0 | U43: 0 | V43: 0.44854275 | W43: 0 | X43: 0 | Y43: 1
A44: Contribution to Portfolio Return | B44: 0 | C44: 0 | D44: 0 | E44: 0.080747105 | F44: 0 | G44: 0 | H44: 0 | I44: 0 | J44: 0 | K44: 0 | L44: 0 | M44: 0 | N44: 0 | O44: 0 | P44: 0 | Q44: 0 | R44: 0 | S44: 0 | T44: 0 | U44: 0 | V44: 0.010380306 | W44: 0 | X44: 0
A46: Portfolio variance | B46: 0.012100034
A47: Standard Deviation | B47: 0.11000015
A48: portfolio return | B48: 0.091127411
A49: Portfolio Sharpe | B49: 0.38933955
A51: Sharpe Optimal Required Return = 12% | B51: INVDDC | C51: INVGIC | D51: INVAFC | E51: CMGH2 | F51: CMGF2 | G51: SSCMG2 | H51: ESPRX | I51: INVMGC | J51: GTSFX | K51: CM7BE | L51: VEVRX | M51: GTDFX | N51: INVIGTC | O51: SSCMGX2 | P51: INVS73 | Q51: CMAI4 | R51: INVPZ | S51: DIPSX | T51: INVS86 | U51: AFRFX | V51: SSCM7FE | W51: CM9N2 | X51: INVSVC2 | Y51: sum
A52: Weights | B52: 0 | C52: 0 | D52: 0 | E52: 0.78565627 | F52: 0 | G52: 0 | H52: 0 | I52: 0 | J52: 0 | K52: 0 | L52: 0 | M52: 0 | N52: 0 | O52: 0 | P52: 0 | Q52: 0 | R52: 0 | S52: 0 | T52: 0 | U52: 0 | V52: 0.21434374 | W52: 0 | X52: 0 | Y52: 1
A53: Contribution to Portfolio Return | B53: 0 | C53: 0 | D53: 0 | E53: 0.11503969 | F53: 0 | G53: 0 | H53: 0 | I53: 0 | J53: 0 | K53: 0 | L53: 0 | M53: 0 | N53: 0 | O53: 0 | P53: 0 | Q53: 0 | R53: 0 | S53: 0 | T53: 0 | U53: 0 | V53: 0.0049604047 | W53: 0 | X53: 0
A55: Portfolio variance | B55: 0.022708476
A56: Standard Deviation | B56: 0.15069332
A57: portfolio return | B57: 0.12000009
A58: Portfolio Sharpe | B58: 0.4758014

Sheet MC SIM Dot Com Bubble
A1: SAA | Q1: Simulation | R1: rand() | S1: return
A2: Objective: | B2: Highest Sharpe Ratio | Q2: 1 | R2: 0.46813174 | S2: =_xlfn.NORM.INV(R2,$K$12,$K$14) -> -0.0013267255
A3: Required Return: | B3: 0.12 | Q3: 2 | R3: 0.33031399 | S3: =_xlfn.NORM.INV(R3,$K$12,$K$14) -> -0.0054128521
A4: Fund ID | B4: CMGH2 | C4: SSCM7FE | Q4: 3 | R4: 0.093346797 | S4: =_xlfn.NORM.INV(R4,$K$12,$K$14) -> -0.015442447
A5: Weights | B5: 0.78565627 | C5: 0.21434374 | Q5: 4 | R5: 0.36787823 | S5: =_xlfn.NORM.INV(R5,$K$12,$K$14) -> -0.0042570621
A6: Benchmark | B6: Russell 1000 Growth Index | C6: Bloomberg U.S. Aggregate Bond Index | Q6: 5 | R6: 0.80473493 | S6: =_xlfn.NORM.INV(R6,$K$12,$K$14) -> 0.0093542973
A7: Proxy | B7: ^GSPC | C7: VBMFX | Q7: 6 | R7: 0.62763819 | S7: =_xlfn.NORM.INV(R7,$K$12,$K$14) -> 0.0032884573
Q8: 7 | R8: 0.082898961 | S8: =_xlfn.NORM.INV(R8,$K$12,$K$14) -> -0.016186768
Q9: 8 | R9: 0.80735293 | S9: =_xlfn.NORM.INV(R9,$K$12,$K$14) -> 0.009462706
D10: Returns | Q10: 9 | R10: 0.85415634 | S10: =_xlfn.NORM.INV(R10,$K$12,$K$14) -> 0.011582064
A11: Date | B11: ^GSPC | C11: VBMFX | D11: ^GSPC | E11: VBMFX | F11: CMGH2 | G11: SSCM7FE | H11: daily portfolio return | J11: Compounded Annual Portfolio Return: | K11: {=GEOMEAN(H13:H743+1)^252-1} -> -0.11425657 | Q11: 10 | R11: 0.93224111 | S11: =_xlfn.NORM.INV(R11,$K$12,$K$14) -> 0.01656928
A12: 36556 | B12: 1394.46 | C12: 3.5543921 | J12: Average Daily Return | K12: =AVERAGE(H13:H743) -> -0.0004167443 | Q12: 11 | R12: 0.46377271 | S12: =_xlfn.NORM.INV(R12,$K$12,$K$14) -> -0.0014515181
A13: 36557 | B13: 1409.28 | C13: 3.5618789 | D13: =LN(B13/B12) -> 0.010571741 | E13: =LN(C13/C12) -> 0.0021041422 | F13: =D13*$B$5 -> 0.0083057545 | G13: =E13*$C$5 -> 0.0004510097 | H13: =SUM(F13:G13) -> 0.0087567642 | J13: Average Annual Return | K13: =(1+K12)^252-1 -> -0.099712798 | Q13: 12 | R13: 0.41556428 | S13: =_xlfn.NORM.INV(R13,$K$12,$K$14) -> -0.0028434629
A14: 36558 | B14: 1409.12 | C14: 3.5618789 | D14: =LN(B14/B13) -> -0.00011356385 | E14: =LN(C14/C13) -> 0 | F14: =D14*$B$5 -> -8.9222151e-05 | G14: =E14*$C$5 -> 0 | H14: =SUM(F14:G14) -> -8.9222151e-05 | J14: Volatility (Daily) | K14: =_xlfn.STDEV.S(H13:H743) -> 0.011379455 | Q14: 13 | R14: 0.3193577 | S14: =_xlfn.NORM.INV(R14,$K$12,$K$14) -> -0.005759349
A15: 36559 | B15: 1424.97 | C15: 3.5768647 | D15: =LN(B15/B14) -> 0.011185348 | E15: =LN(C15/C14) -> 0.004198448 | F15: =D15*$B$5 -> 0.0087878385 | G15: =E15*$C$5 -> 0.00089991102 | H15: =SUM(F15:G15) -> 0.0096877495 | J15: Rf | K15: 0.0165 | Q15: 14 | R15: 0.56045638 | S15: =_xlfn.NORM.INV(R15,$K$12,$K$14) -> 0.0013143714
A16: 36560 | B16: 1424.37 | C16: 3.5693748 | D16: =LN(B16/B15) -> -0.00042113304 | E16: =LN(C16/C15) -> -0.0020961857 | F16: =D16*$B$5 -> -0.00033086581 | G16: =E16*$C$5 -> -0.00044930427 | H16: =SUM(F16:G16) -> -0.00078017008 | J16: Sharpe | K16: =(K13-K15)/K14 -> -10.21251 | Q16: 15 | R16: 0.59812357 | S16: =_xlfn.NORM.INV(R16,$K$12,$K$14) -> 0.0024109727
A17: 36563 | B17: 1424.24 | C17: 3.5543921 | D17: =LN(B17/B16) -> -9.1276014e-05 | E17: =LN(C17/C16) -> -0.0042064045 | F17: =D17*$B$5 -> -7.1711573e-05 | G17: =E17*$C$5 -> -0.00090161645 | H17: =SUM(F17:G17) -> -0.00097332802 | Q17: 16 | R17: 0.019394749 | S17: =_xlfn.NORM.INV(R17,$K$12,$K$14) -> -0.023931399
A18: 36564 | B18: 1441.72 | C18: 3.5656304 | D18: =LN(B18/B17) -> 0.012198494 | E18: =LN(C18/C17) -> 0.0031568287 | F18: =D18*$B$5 -> 0.009583823 | G18: =E18*$C$5 -> 0.00067664647 | H18: =SUM(F18:G18) -> 0.010260469 | J18: Simulation Average Annual Return | K18: =((1+AVERAGE(S2:S7501))^252)-1 -> -0.0556342 | Q18: 17 | R18: 0.45611075 | S18: =_xlfn.NORM.INV(R18,$K$12,$K$14) -> -0.0016711802
A19: 36565 | B19: 1411.71 | C19: 3.5581367 | D19: =LN(B19/B18) -> -0.021035117 | E19: =LN(C19/C18) -> -0.0021038692 | F19: =D19*$B$5 -> -0.016526372 | G19: =E19*$C$5 -> -0.00045095119 | H19: =SUM(F19:G19) -> -0.016977323 | J19: Simulation Average Annual Volatility | K19: =_xlfn.STDEV.S(S2:S7501) -> 0.011371128 | Q19: 18 | R19: 0.53861925 | S19: =_xlfn.NORM.INV(R19,$K$12,$K$14) -> 0.00068655972
A20: 36566 | B20: 1416.83 | C20: 3.5506463 | D20: =LN(B20/B19) -> 0.0036202429 | E20: =LN(C20/C19) -> -0.0021073647 | F20: =D20*$B$5 -> 0.0028442665 | G20: =E20*$C$5 -> -0.00045170043 | H20: =SUM(F20:G20) -> 0.0023925661 | Q20: 19 | R20: 0.096481053 | S20: =_xlfn.NORM.INV(R20,$K$12,$K$14) -> -0.015231273
A21: 36567 | B21: 1387.12 | C21: 3.5543921 | D21: =LN(B21/B20) -> -0.021192299 | E21: =LN(C21/C20) -> 0.0010544052 | F21: =D21*$B$5 -> -0.016649862 | G21: =E21*$C$5 -> 0.00022600515 | H21: =SUM(F21:G21) -> -0.016423857 | J21: Sharpe | K21: =K18/K19 -> -4.8925839 | Q21: 20 | R21: 0.28587239 | S21: =_xlfn.NORM.INV(R21,$K$12,$K$14) -> -0.0068516415
A22: 36570 | B22: 1389.9399 | C22: 3.5656304 | D22: =LN(B22/B21) -> 0.0020308869 | E22: =LN(C22/C21) -> 0.0031568287 | F22: =D22*$B$5 -> 0.001595579 | G22: =E22*$C$5 -> 0.00067664647 | H22: =SUM(F22:G22) -> 0.0022722255 | Q22: 21 | R22: 0.60324571 | S22: =_xlfn.NORM.INV(R22,$K$12,$K$14) -> 0.002561911
A23: 36571 | B23: 1402.05 | C23: 3.5618789 | D23: =LN(B23/B22) -> 0.0086749476 | E23: =LN(C23/C22) -> -0.0010526866 | F23: =D23*$B$5 -> 0.0068155269 | G23: =E23*$C$5 -> -0.00022563677 | H23: =SUM(F23:G23) -> 0.0065898901 | Q23: 22 | R23: 0.74620481 | S23: =_xlfn.NORM.INV(R23,$K$12,$K$14) -> 0.0071232188
A24: 36572 | B24: 1387.67 | C24: 3.5581367 | D24: =LN(B24/B23) -> -0.010309373 | E24: =LN(C24/C23) -> -0.0010511826 | F24: =D24*$B$5 -> -0.0080996233 | G24: =E24*$C$5 -> -0.00022531441 | H24: =SUM(F24:G24) -> -0.0083249378 | Q24: 23 | R24: 0.83129657 | S24: =_xlfn.NORM.INV(R24,$K$12,$K$14) -> 0.010499585
A25: 36573 | B25: 1388.26 | C25: 3.5543921 | D25: =LN(B25/B24) -> 0.00042505814 | E25: =LN(C25/C24) -> -0.0010529595 | F25: =D25*$B$5 -> 0.00033394959 | G25: =E25*$C$5 -> -0.00022569528 | H25: =SUM(F25:G25) -> 0.0001082543 | Q25: 24 | R25: 0.35508212 | S25: =_xlfn.NORM.INV(R25,$K$12,$K$14) -> -0.0046457542
A26: 36574 | B26: 1346.09 | C26: 3.5656304 | D26: =LN(B26/B25) -> -0.030847103 | E26: =LN(C26/C25) -> 0.0031568287 | F26: =D26*$B$5 -> -0.02423522 | G26: =E26*$C$5 -> 0.00067664647 | H26: =SUM(F26:G26) -> -0.023558573 | Q26: 25 | R26: 0.02032419 | S26: =_xlfn.NORM.INV(R26,$K$12,$K$14) -> -0.023711614
A27: 36578 | B27: 1352.17 | C27: 3.5881011 | D27: =LN(B27/B26) -> 0.0045066735 | E27: =LN(C27/C26) -> 0.006282256 | F27: =D27*$B$5 -> 0.0035406963 | G27: =E27*$C$5 -> 0.0013465622 | H27: =SUM(F27:G27) -> 0.0048872585 | Q27: 26 | R27: 0.71177908 | S27: =_xlfn.NORM.INV(R27,$K$12,$K$14) -> 0.0059397013
A28: 36579 | B28: 1360.6899 | C28: 3.5731175 | D28: =LN(B28/B27) -> 0.0062811391 | E28: =LN(C28/C27) -> -0.0041846721 | F28: =D28*$B$5 -> 0.0049348163 | G28: =E28*$C$5 -> -0.00089695825 | H28: =SUM(F28:G28) -> 0.004037858 | Q28: 27 | R28: 0.61238911 | S28: =_xlfn.NORM.INV(R28,$K$12,$K$14) -> 0.0028326743
A29: 36580 | B29: 1353.4301 | C29: 3.5843558 | D29: =LN(B29/B28) -> -0.0053497303 | E29: =LN(C29/C28) -> 0.0031403109 | F29: =D29*$B$5 -> -0.0042030491 | G29: =E29*$C$5 -> 0.00067310598 | H29: =SUM(F29:G29) -> -0.0035299432 | Q29: 28 | R29: 0.092104742 | S29: =_xlfn.NORM.INV(R29,$K$12,$K$14) -> -0.01552758
A30: 36581 | B30: 1333.36 | C30: 3.5843558 | D30: =LN(B30/B29) -> -0.014940089 | E30: =LN(C30/C29) -> 0 | F30: =D30*$B$5 -> -0.011737775 | G30: =E30*$C$5 -> 0 | H30: =SUM(F30:G30) -> -0.011737775 | Q30: 29 | R30: 0.17121087 | S30: =_xlfn.NORM.INV(R30,$K$12,$K$14) -> -0.011220298
A31: 36584 | B31: 1348.05 | C31: 3.5731175 | D31: =LN(B31/B30) -> 0.010957079 | E31: =LN(C31/C30) -> -0.0031403109 | F31: =D31*$B$5 -> 0.0086084976 | G31: =E31*$C$5 -> -0.00067310598 | H31: =SUM(F31:G31) -> 0.0079353916 | Q31: 30 | R31: 0.26379834 | S31: =_xlfn.NORM.INV(R31,$K$12,$K$14) -> -0.0076049067
A32: 36585 | B32: 1366.42 | C32: 3.5964689 | D32: =LN(B32/B31) -> 0.013535073 | E32: =LN(C32/C31) -> 0.0065140476 | F32: =D32*$B$5 -> 0.010633915 | G32: =E32*$C$5 -> 0.0013962453 | H32: =SUM(F32:G32) -> 0.01203016 | Q32: 31 | R32: 0.24897553 | S32: =_xlfn.NORM.INV(R32,$K$12,$K$14) -> -0.0081287961
A33: 36586 | B33: 1379.1899 | C33: 3.6002352 | D33: =LN(B33/B32) -> 0.0093021147 | E33: =LN(C33/C32) -> 0.0010466732 | F33: =D33*$B$5 -> 0.0073082647 | G33: =E33*$C$5 -> 0.00022434784 | H33: =SUM(F33:G33) -> 0.0075326126 | Q33: 32 | R33: 0.51346362 | S33: =_xlfn.NORM.INV(R33,$K$12,$K$14) -> -3.2634226e-05
... A743: 37620 | B743: 879.39001 | C743: 4.6496444 | D743: =LN(B743/B742) -> 0.0045475493 | E743: =LN(C743/C742) -> 0.00096323573 | F743: =D743*$B$5 -> 0.0035728106 | G743: =E743*$C$5 -> 0.00020646354 | H743: =SUM(F743:G743) -> 0.0037792741 | Q743: 742 | R743: 0.96282089 | S743: =_xlfn.NORM.INV(R743,$K$12,$K$14) -> 0.019888789
Q744: 743 | R744: 0.11270244 | S744: =_xlfn.NORM.INV(R744,$K$12,$K$14) -> -0.01421184
Q745: 744 | R745: 0.0754176 | S745: =_xlfn.NORM.INV(R745,$K$12,$K$14) -> -0.016764329
Q746: 745 | R746: 0.41290532 | S746: =_xlfn.NORM.INV(R746,$K$12,$K$14) -> -0.0029211088
Q747: 746 | R747: 0.81487028 | S747: =_xlfn.NORM.INV(R747,$K$12,$K$14) -> 0.0097791057
Q748: 747 | R748: 0.089988298 | S748: =_xlfn.NORM.INV(R748,$K$12,$K$14) -> -0.015674626
Q749: 748 | R749: 0.73951449 | S749: =_xlfn.NORM.INV(R749,$K$12,$K$14) -> 0.0068871515
Q750: 749 | R750: 0.76402695 | S750: =_xlfn.NORM.INV(R750,$K$12,$K$14) -> 0.0077686826
Q751: 750 | R751: 0.72085416 | S751: =_xlfn.NORM.INV(R751,$K$12,$K$14) -> 0.0062445708
Q752: 751 | R752: 0.86826648 | S752: =_xlfn.NORM.INV(R752,$K$12,$K$14) -> 0.012308151
Q753: 752 | R753: 0.47955963 | S753: =_xlfn.NORM.INV(R753,$K$12,$K$14) -> -0.001000042
Q754: 753 | R754: 0.81659245 | S754: =_xlfn.NORM.INV(R754,$K$12,$K$14) -> 0.0098527048
Q755: 754 | R755: 0.18488196 | S755: =_xlfn.NORM.INV(R755,$K$12,$K$14) -> -0.010623156
... Q7501: 7500 | R7501: 0.91181506 | S7501: =_xlfn.NORM.INV(R7501,$K$12,$K$14) -> 0.014968473

Sheet Note - Data 
